Workbook
Name YearList: OFFSET('BN DASH DATA'!$X$4,0,0,SUMPRODUCT(--('BN DASH DATA'!$X$4:$X$12<>"")),1)

Sheet BN DASHBOARD
B2: BN LOGISTICS — SALES & FLEET DASHBOARD
B3: =IF($K$3="All years","Auburn brokerage + market loads + fleet utilisation · all history","Auburn brokerage + market loads + fleet utilisation · calendar year "&$K$3) -> Auburn brokerage + market loads + fleet utilisation · calendar year 2026 | J3: VIEW YEAR | K3: 2026
B5: TOTAL SALE | D5: AUBURN BILLED | F5: LORRY COST | H5: AUBURN MARGIN % | J5: LOADS | L5: FLEET USE
B6: =SUMIFS(AUBURN[BILLING RATE (₹)],AUBURN[LOADING DATE],">="&$C$61,AUBURN[LOADING DATE],"<="&$C$62)+SUMIFS(MARKET[RATE (₹)],MARKET[LOAD DATE],">="&$C$61,MARKET[LOAD DATE],"<="&$C$62) -> 30912850 | D6: =SUMIFS(AUBURN[BILLING RATE (₹)],AUBURN[LOADING DATE],">="&$C$61,AUBURN[LOADING DATE],"<="&$C$62) -> 26390330 | F6: =SUMIFS(AUBURN[LORRY RATE (₹)],AUBURN[LOADING DATE],">="&$C$61,AUBURN[LOADING DATE],"<="&$C$62) -> 13666890 | H6: =IFERROR(($D$6-$F$6)/$D$6,"") -> 0.48212508 | J6: =COUNTIFS(AUBURN[LOADING DATE],">="&$C$61,AUBURN[LOADING DATE],"<="&$C$62)+COUNTIFS(MARKET[LOAD DATE],">="&$C$61,MARKET[LOAD DATE],"<="&$C$62) -> 419 | L6: =IF($G$21=0,"n/a",$F$21/$G$21) -> 0.70046667
B7: =TEXT($D$6,"₹#,##0")&" from Auburn" -> ₹26,390,330 from Auburn | D7: =TEXT($F$6,"₹#,##0")&" paid to lorries" -> ₹13,666,890 paid to lorries | F7: =TEXT($D$6-$F$6,"₹#,##0")&" gross margin" -> ₹12,723,440 gross margin | H7: ="on "&TEXT(COUNTIFS(AUBURN[LOADING DATE],">="&$C$61,AUBURN[LOADING DATE],"<="&$C$62),"#,##0")&" Auburn loads" -> on 295 Auburn loads | J7: =TEXT(COUNTIFS(MARKET[LOAD DATE],">="&$C$61,MARKET[LOAD DATE],"<="&$C$62),"#,##0")&" market loads" -> 124 market loads | L7: =IF($G$21=0,"km log starts Mar-2026",TEXT($F$21,"#,##0")&" km run") -> 630,420 km run
B9: =IF($G$21=0,"PER-TRUCK UTILISATION — no KM log for "&$K$3&" (log starts Mar-2026)","PER-TRUCK UTILISATION") -> PER-TRUCK UTILISATION
B10: TRUCK | C10: MAKE | D10: CAPACITY | E10: DRIVER | F10: ACTUAL KM | G10: TARGET KM | H10: UTILISATION %
B11: 2417 | C11: =IFERROR(INDEX(KMRUN[MAKE],MATCH($B11,KMRUN[TRUCK NO.],0)),"") -> Tata | D11: =IFERROR(INDEX(KMRUN[CAPACITY],MATCH($B11,KMRUN[TRUCK NO.],0)),"") -> 32 Feet | E11: =IFERROR(INDEX(KMRUN[DRIVER],MATCH($B11,KMRUN[TRUCK NO.],0)),"") -> Driver A | F11: =SUMIFS(KMRUN[ACTUAL KM],KMRUN[TRUCK NO.],$B11,KMRUN[MONTH],">="&$C$61,KMRUN[MONTH],"<="&$C$62) -> 70130 | G11: =SUMIFS(KMRUN[TARGET KM],KMRUN[TRUCK NO.],$B11,KMRUN[MONTH],">="&$C$61,KMRUN[MONTH],"<="&$C$62) -> 90000 | H11: =IFERROR($F11/$G11,"") -> 0.77922222
B12: 0526 | C12: =IFERROR(INDEX(KMRUN[MAKE],MATCH($B12,KMRUN[TRUCK NO.],0)),"") -> Tata | D12: =IFERROR(INDEX(KMRUN[CAPACITY],MATCH($B12,KMRUN[TRUCK NO.],0)),"") -> 32 Feet | E12: =IFERROR(INDEX(KMRUN[DRIVER],MATCH($B12,KMRUN[TRUCK NO.],0)),"") -> Driver B | F12: =SUMIFS(KMRUN[ACTUAL KM],KMRUN[TRUCK NO.],$B12,KMRUN[MONTH],">="&$C$61,KMRUN[MONTH],"<="&$C$62) -> 73250 | G12: =SUMIFS(KMRUN[TARGET KM],KMRUN[TRUCK NO.],$B12,KMRUN[MONTH],">="&$C$61,KMRUN[MONTH],"<="&$C$62) -> 90000 | H12: =IFERROR($F12/$G12,"") -> 0.81388889
B13: 3958 | C13: =IFERROR(INDEX(KMRUN[MAKE],MATCH($B13,KMRUN[TRUCK NO.],0)),"") -> Tata | D13: =IFERROR(INDEX(KMRUN[CAPACITY],MATCH($B13,KMRUN[TRUCK NO.],0)),"") -> 32 Feet | E13: =IFERROR(INDEX(KMRUN[DRIVER],MATCH($B13,KMRUN[TRUCK NO.],0)),"") -> Driver C | F13: =SUMIFS(KMRUN[ACTUAL KM],KMRUN[TRUCK NO.],$B13,KMRUN[MONTH],">="&$C$61,KMRUN[MONTH],"<="&$C$62) -> 73250 | G13: =SUMIFS(KMRUN[TARGET KM],KMRUN[TRUCK NO.],$B13,KMRUN[MONTH],">="&$C$61,KMRUN[MONTH],"<="&$C$62) -> 90000 | H13: =IFERROR($F13/$G13,"") -> 0.81388889
B14: 6142 | C14: =IFERROR(INDEX(KMRUN[MAKE],MATCH($B14,KMRUN[TRUCK NO.],0)),"") -> Tata | D14: =IFERROR(INDEX(KMRUN[CAPACITY],MATCH($B14,KMRUN[TRUCK NO.],0)),"") -> 32 Feet | E14: =IFERROR(INDEX(KMRUN[DRIVER],MATCH($B14,KMRUN[TRUCK NO.],0)),"") -> Driver D | F14: =SUMIFS(KMRUN[ACTUAL KM],KMRUN[TRUCK NO.],$B14,KMRUN[MONTH],">="&$C$61,KMRUN[MONTH],"<="&$C$62) -> 78320 | G14: =SUMIFS(KMRUN[TARGET KM],KMRUN[TRUCK NO.],$B14,KMRUN[MONTH],">="&$C$61,KMRUN[MONTH],"<="&$C$62) -> 90000 | H14: =IFERROR($F14/$G14,"") -> 0.87022222
B15: 8803 | C15: =IFERROR(INDEX(KMRUN[MAKE],MATCH($B15,KMRUN[TRUCK NO.],0)),"") -> Ashok | D15: =IFERROR(INDEX(KMRUN[CAPACITY],MATCH($B15,KMRUN[TRUCK NO.],0)),"") -> 32 Feet | E15: =IFERROR(INDEX(KMRUN[DRIVER],MATCH($B15,KMRUN[TRUCK NO.],0)),"") -> Driver E | F15: =SUMIFS(KMRUN[ACTUAL KM],KMRUN[TRUCK NO.],$B15,KMRUN[MONTH],">="&$C$61,KMRUN[MONTH],"<="&$C$62) -> 68000 | G15: =SUMIFS(KMRUN[TARGET KM],KMRUN[TRUCK NO.],$B15,KMRUN[MONTH],">="&$C$61,KMRUN[MONTH],"<="&$C$62) -> 90000 | H15: =IFERROR($F15/$G15,"") -> 0.75555556
B16: 4371 | C16: =IFERROR(INDEX(KMRUN[MAKE],MATCH($B16,KMRUN[TRUCK NO.],0)),"") -> Ashok | D16: =IFERROR(INDEX(KMRUN[CAPACITY],MATCH($B16,KMRUN[TRUCK NO.],0)),"") -> 24 Feet | E16: =IFERROR(INDEX(KMRUN[DRIVER],MATCH($B16,KMRUN[TRUCK NO.],0)),"") -> Driver F | F16: =SUMIFS(KMRUN[ACTUAL KM],KMRUN[TRUCK NO.],$B16,KMRUN[MONTH],">="&$C$61,KMRUN[MONTH],"<="&$C$62) -> 57150 | G16: =SUMIFS(KMRUN[TARGET KM],KMRUN[TRUCK NO.],$B16,KMRUN[MONTH],">="&$C$61,KMRUN[MONTH],"<="&$C$62) -> 90000 | H16: =IFERROR($F16/$G16,"") -> 0.635
B17: 1695 | C17: =IFERROR(INDEX(KMRUN[MAKE],MATCH($B17,KMRUN[TRUCK NO.],0)),"") -> Tata | D17: =IFERROR(INDEX(KMRUN[CAPACITY],MATCH($B17,KMRUN[TRUCK NO.],0)),"") -> 32 Feet | E17: =IFERROR(INDEX(KMRUN[DRIVER],MATCH($B17,KMRUN[TRUCK NO.],0)),"") -> Driver G | F17: =SUMIFS(KMRUN[ACTUAL KM],KMRUN[TRUCK NO.],$B17,KMRUN[MONTH],">="&$C$61,KMRUN[MONTH],"<="&$C$62) -> 61100 | G17: =SUMIFS(KMRUN[TARGET KM],KMRUN[TRUCK NO.],$B17,KMRUN[MONTH],">="&$C$61,KMRUN[MONTH],"<="&$C$62) -> 90000 | H17: =IFERROR($F17/$G17,"") -> 0.67888889
B18: 7230 | C18: =IFERROR(INDEX(KMRUN[MAKE],MATCH($B18,KMRUN[TRUCK NO.],0)),"") -> Tata | D18: =IFERROR(INDEX(KMRUN[CAPACITY],MATCH($B18,KMRUN[TRUCK NO.],0)),"") -> 32 Feet | E18: =IFERROR(INDEX(KMRUN[DRIVER],MATCH($B18,KMRUN[TRUCK NO.],0)),"") -> Driver H | F18: =SUMIFS(KMRUN[ACTUAL KM],KMRUN[TRUCK NO.],$B18,KMRUN[MONTH],">="&$C$61,KMRUN[MONTH],"<="&$C$62) -> 58420 | G18: =SUMIFS(KMRUN[TARGET KM],KMRUN[TRUCK NO.],$B18,KMRUN[MONTH],">="&$C$61,KMRUN[MONTH],"<="&$C$62) -> 90000 | H18: =IFERROR($F18/$G18,"") -> 0.64911111
B19: 9064 | C19: =IFERROR(INDEX(KMRUN[MAKE],MATCH($B19,KMRUN[TRUCK NO.],0)),"") -> Tata | D19: =IFERROR(INDEX(KMRUN[CAPACITY],MATCH($B19,KMRUN[TRUCK NO.],0)),"") -> 32 Feet | E19: =IFERROR(INDEX(KMRUN[DRIVER],MATCH($B19,KMRUN[TRUCK NO.],0)),"") -> Driver I | F19: =SUMIFS(KMRUN[ACTUAL KM],KMRUN[TRUCK NO.],$B19,KMRUN[MONTH],">="&$C$61,KMRUN[MONTH],"<="&$C$62) -> 47300 | G19: =SUMIFS(KMRUN[TARGET KM],KMRUN[TRUCK NO.],$B19,KMRUN[MONTH],">="&$C$61,KMRUN[MONTH],"<="&$C$62) -> 90000 | H19: =IFERROR($F19/$G19,"") -> 0.52555556
B20: 5582 | C20: =IFERROR(INDEX(KMRUN[MAKE],MATCH($B20,KMRUN[TRUCK NO.],0)),"") -> Tata | D20: =IFERROR(INDEX(KMRUN[CAPACITY],MATCH($B20,KMRUN[TRUCK NO.],0)),"") -> 32 Feet | E20: =IFERROR(INDEX(KMRUN[DRIVER],MATCH($B20,KMRUN[TRUCK NO.],0)),"") -> Driver J | F20: =SUMIFS(KMRUN[ACTUAL KM],KMRUN[TRUCK NO.],$B20,KMRUN[MONTH],">="&$C$61,KMRUN[MONTH],"<="&$C$62) -> 43500 | G20: =SUMIFS(KMRUN[TARGET KM],KMRUN[TRUCK NO.],$B20,KMRUN[MONTH],">="&$C$61,KMRUN[MONTH],"<="&$C$62) -> 90000 | H20: =IFERROR($F20/$G20,"") -> 0.48333333
B21: FLEET | F21: =SUM(F11:F20) -> 630420 | G21: =SUM(G11:G20) -> 900000 | H21: =IFERROR($F$21/$G$21,"") -> 0.70046667
B23: MONTHLY REVENUE — AUBURN vs MARKET
B40: AUBURN MARGIN % TREND | H40: UTILISATION BY TRUCK
B57: =IF($K$3="All years","Charts show each calendar month totalled across 2024–2026. Auburn margin = billing rate less lorry rate. Market loads are own trucks, so no lorry cost applies. Fleet km log starts Mar-2026.","Charts show Jan–Dec of the selected year and respond to VIEW YEAR. Auburn margin = billing rate less lorry rate. Market loads are own trucks, so no lorry cost applies. Fleet km log starts Mar-2026.") -> Charts show Jan–Dec of the selected year and respond to VIEW YEAR. Auburn margin = billing rate less lorry rate. Market loads are own trucks, so no lorry cost applies. Fleet km log starts Mar-2026.
B60: Filter bounds (helper — driven by VIEW YEAR)
B61: FROM | C61: =IF($K$3="All years",DATE(1990,1,1),DATE($K$3,1,1)) -> 46023
B62: TO | C62: =IF($K$3="All years",DATE(2100,12,31),DATE($K$3,12,31)) -> 46387

Sheet Auburn Load 
A1: S.NO. | B1: Month | C1: LOADING DATE | D1: Provider | E1: LORRY NO. | F1: MOBILE NO. | G1: FROM | H1: POINT GR NO. | I1: TO GR NO. | J1: LORRY MAKE | K1: LORRY RATE | L1: Billing Rate Charges | M1: Net Saving | N1: Adance Paid (INR) | O1: Balance To pay | P1: BILL STATUS | Q1: Invoice No. | R1: Payment Status | S1: REACH UNLOADING POINT | T1: UNLOADING DATE | U1: Current Status | V1: BROAKER ADRESS | W1: REMARKS
A2: 1 | B2: May | C2: 10.05.2024 | D2: 3rd Party | E2: TN52TM-7760 | F2: 9686844715 | G2: RANCHI | H2: HASSAN.176610,BOX 04 | I2: BOMMANSA.562608,BOX 578 | J2: 32FEET SXL | K2: 38590 | L2: 46620 | M2: =Table1[[#This Row],[Billing Rate Charges]]-Table1[[#This Row],[ LORRY RATE ]] -> 8030 | N2: 38590 | O2: =Table1[[#This Row],[ LORRY RATE ]]-Table1[[#This Row],[Adance Paid (INR)]] -> 0 | P2: DONE | Q2: 01 | R2: RECEIPT | S2: SAME DAY | T2: 15/05/2024./18/05/2024 | U2: Closed | V2: Transporter 01
A3: 2 | B3: May | C3: 15.05.2024 | D3: 3rd Party | E3: TN52TM-1398 | F3: 9941053951 | G3: RANCHI | H3: HOSKOTE.749378,BOX 983 | I3: HASSAN,772300,BOX 004 | J3: 32FEET SXL | K3: 36450 | L3: 46620 | M3: =Table1[[#This Row],[Billing Rate Charges]]-Table1[[#This Row],[ LORRY RATE ]] -> 10170 | N3: 36450 | O3: =Table1[[#This Row],[ LORRY RATE ]]-Table1[[#This Row],[Adance Paid (INR)]] -> 0 | P3: DONE | Q3: 02 | R3: RECEIPT | S3: 45431 | T3: 20/05/2024./22/05/2024 | U3: Closed | V3: Transporter 02
A4: 3 | B4: May | C4: 45431 | D4: 3rd Party | E4: KA05TT-6944 | F4: 9295512602 | G4: RANCHI | H4: NARSAPUR.043922.BOX | I4: HASSAN,978172.BOX | J4: 24FEET | K4: 31930 | L4: 45040 | M4: =Table1[[#This Row],[Billing Rate Charges]]-Table1[[#This Row],[ LORRY RATE ]] -> 13110 | N4: 31930 | O4: =Table1[[#This Row],[ LORRY RATE ]]-Table1[[#This Row],[Adance Paid (INR)]] -> 0 | P4: DONE | Q4: 03 | R4: RECEIPT | S4: 45433 | T4: 21/05/2024./22/05/2024 | U4: Closed | V4: Transporter 02
A5: 4 | B5: May | C5: 45430 | D5: 3rd Party | E5: KA02GM-9724 | F5: 9149905009 | G5: RANCHI | H5: N/A | I5: HASSAN.909686.BOX 312 | J5: 22FEET | K5: 28300 | L5: 38740 | M5: =Table1[[#This Row],[Billing Rate Charges]]-Table1[[#This Row],[ LORRY RATE ]] -> 10440 | N5: 28300 | O5: =Table1[[#This Row],[ LORRY RATE ]]-Table1[[#This Row],[Adance Paid (INR)]] -> 0 | P5: DONE | Q5: 04 | R5: RECEIPT | S5: 45433 | T5: 45433 | U5: Closed | V5: Transporter 02
A6: 5 | B6: May | C6: 45431 | D6: 3rd Party | E6: TN12RW-1972 | F6: 9678275995 | G6: RANCHI | H6: N/A | I6: HOSKOTE.125550.BOX 729 | J6: 20FEET | K6: 27830 | L6: 35600 | M6: =Table1[[#This Row],[Billing Rate Charges]]-Table1[[#This Row],[ LORRY RATE ]] -> 7770 | N6: 27830 | O6: =Table1[[#This Row],[ LORRY RATE ]]-Table1[[#This Row],[Adance Paid (INR)]] -> 0 | P6: DONE | Q6: 05 | R6: RECEIPT | S6: 45433 | T6: 45433 | U6: Closed | V6: Transporter 02
A7: 6 | B7: May | C7: 45436 | D7: 3rd Party | E7: KA51DJ-2589 | F7: 9087547668 | G7: RANCHI | H7: NARSAPUR,803363 | I7: HOSKOTE,467212 | J7: 20FEET | K7: 29850 | L7: 41900 | M7: =Table1[[#This Row],[Billing Rate Charges]]-Table1[[#This Row],[ LORRY RATE ]] -> 12050 | N7: 29850 | O7: =Table1[[#This Row],[ LORRY RATE ]]-Table1[[#This Row],[Adance Paid (INR)]] -> 0 | P7: DONE | Q7: 06 | R7: RECEIPT | S7: 45440 | T7: 45440 | U7: Closed | V7: Transporter 02
A8: 7 | B8: May | C8: 45442 | D8: 3rd Party | E8: PB13MM-3286 | F8: 9757815238 | G8: RANCHI | H8: N/A | I8: HOKOTE,579908 | J8: 32FEET SXL | K8: 32290 | L8: 40320 | M8: =Table1[[#This Row],[Billing Rate Charges]]-Table1[[#This Row],[ LORRY RATE ]] -> 8030 | N8: 32290 | O8: =Table1[[#This Row],[ LORRY RATE ]]-Table1[[#This Row],[Adance Paid (INR)]] -> 0 | P8: DONE | Q8: 07 | R8: RECEIPT | S8: 45417 | T8: 45417 | U8: Closed | V8: Transporter 01
A9: 9 | B9: May | C9: 45436 | D9: BN | E9: JH01KM-4371 | F9: 9025368773 | G9: RANCHI | H9: N/A | I9: HOSKOTE,749252 | J9: 24FEET SXL | K9: 43990 | L9: 38740 | M9: =Table1[[#This Row],[Billing Rate Charges]]-Table1[[#This Row],[ LORRY RATE ]] -> -5250 | P9: DONE | Q9: 08 | R9: RECEIPT | S9: 45439 | T9: 45440 | U9: Closed | V9: BN
A10: 10 | B10: May | C10: 45440 | D10: BN | E10: JH01KM-4371 | F10: 9025368773 | G10: HOSKOTE | H10: BOMMANHALLI | I10: DODABALLAPUR | J10: 24FEET SXL | L10: 6300 | M10: =Table1[[#This Row],[Billing Rate Charges]]-Table1[[#This Row],[ LORRY RATE ]] -> 6300 | P10: DONE | Q10: 09 | R10: RECEIPT | S10: LOADING | U10: Closed | V10: BN
A11: 11 | B11: May | C11: 45442 | D11: BN | E11: JH01KM-4371 | F11: 9025368773 | G11: DODABALLAPUR | H11: N/A | I11: RANCHI ,872415/27 | J11: 24FEET SXL | K11: 48290 | L11: 67410 | M11: =Table1[[#This Row],[Billing Rate Charges]]-Table1[[#This Row],[ LORRY RATE ]] -> 19120 | P11: DONE | Q11: 09 | R11: RECEIPT | S11: 45445 | T11: 45446 | U11: Closed | V11: BN
A12: 12 | B12: May | C12: 45436 | D12: BN | E12: JH01KM-8803 | F12: 9589264337 | G12: RANCHI | H12: N/A | I12: HOSKOTE ,140915 | J12: 32FEET SXL | K12: 44220 | L12: 40320 | M12: =L12-K12 -> -3900 | P12: DONE | Q12: 10 | R12: RECEIPT | S12: 45439 | T12: 45439 | U12: Closed | V12: BN
A13: 13 | B13: May | C13: 45439 | D13: BN | E13: JH01KM-8803 | F13: 9589264337 | G13: TIRUPUR | H13: N/A | I13: RANCHI,407449 | J13: 32FEET SXL | K13: 51030 | L13: 85680 | M13: =L13-K13 -> 34650 | P13: DONE | Q13: 011 | R13: RECEIPT | S13: 45443 | T13: 45443 | U13: Closed | V13: BN
A14: 14 | B14: JUNE | C14: 45444 | D14: 3rd Party | E14: KA02YH-5646 | F14: 9198923795 | G14: RANCHI | H14: N/A | I14: HOSKOTE,264810 | J14: 20FEET | K14: 27290 | L14: 35600 | M14: 8310 | N14: 27290 | O14: =Table1[[#This Row],[ LORRY RATE ]]-Table1[[#This Row],[Adance Paid (INR)]] -> 0 | P14: DONE | Q14: 012 | R14: RECEIPT | S14: 45447 | T14: 45447 | U14: closed | V14: Transporter 02
A15: 15 | B15: JUNE | C15: 45444 | D15: 3rd Party | E15: KA05RX-6944 | F15: 9295512602 | G15: RANCHI | H15: N/A | I15: HASSAN,872860 | J15: 24FEET | K15: 29110 | L15: 38740 | M15: =Table1[[#This Row],[Billing Rate Charges]]-Table1[[#This Row],[ LORRY RATE ]] -> 9630 | N15: 29110 | O15: =Table1[[#This Row],[ LORRY RATE ]]-Table1[[#This Row],[Adance Paid (INR)]] -> 0 | P15: DONE | Q15: 013 | R15: RECEIPT | S15: 45447 | T15: 45447 | U15: closed | V15: Transporter 02
A16: 16 | B16: JUNE | C16: 45444 | D16: BN | E16: JH01KM-8803 | F16: 9589264337 | G16: RANCHI | H16: N/A | I16: HASSAN,913653 | J16: 32FEET SXL | K16: 44220 | L16: 40320 | M16: =Table1[[#This Row],[Billing Rate Charges]]-Table1[[#This Row],[ LORRY RATE ]] -> -3900 | P16: DONE | Q16: 014 | R16: RECEIPT | S16: 45448 | T16: 45448 | U16: closed | V16: BN
A17: 17 | B17: JUNE | C17: 45446 | D17: BN | E17: JH01KM-4371 | F17: 9025368773 | G17: RANCHI | H17: NARSAPUR,970325+HOSKOTE,425534 | I17: BOMMANSANDRA ,890248 | J17: 24 FEET SXL | K17: 45880 | L17: 51340 | M17: =Table1[[#This Row],[Billing Rate Charges]]-Table1[[#This Row],[ LORRY RATE ]] -> 5460 | P17: DONE | Q17: 015 | R17: RECEIPT | S17: 45449 | T17: 45450 | U17: closed | V17: BN
A18: 18 | B18: JUNE | C18: 45449 | D18: BN | E18: JH01KM8803 | F18: 9589264337 | G18: TIRUPUR | H18: N/A | I18: RANCHI,476477 | J18: 32 FEET SXL | K18: 51690 | L18: 90090 | M18: =Table1[[#This Row],[Billing Rate Charges]]-Table1[[#This Row],[ LORRY RATE ]] -> 38400 | P18: DONE | Q18: 016 | R18: RECEIPT | S18: 45452 | T18: 45453 | U18: closed | V18: BN
A19: 19 | B19: JUNE | C19: 45450 | D19: 3rd Party | E19: KA02GM-9724 | F19: 9149905009 | G19: RANCHI | H19: BOMMANSANDRA,933942 | I19: HOSKOTE,387835 | J19: 22FEET | K19: 27640 | L19: 45040 | M19: =Table1[[#This Row],[Billing Rate Charges]]-Table1[[#This Row],[ LORRY RATE ]] -> 17400 | N19: 27640 | O19: =Table1[[#This Row],[ LORRY RATE ]]-Table1[[#This Row],[Adance Paid (INR)]] -> 0 | P19: DONE | Q19: 017 | R19: RECEIPT | S19: 45454 | T19: 45454 | U19: closed | V19: Transporter 02
A20: 20 | B20: JUNE | C20: 45450 | D20: BN | E20: JH01KM-4371 | F20: 9025368773 | G20: ERODE | H20: N/A | I20: RANCHI,187030 | J20: 24FEET | K20: 48290 | L20: 67410 | M20: =Table1[[#This Row],[Billing Rate Charges]]-Table1[[#This Row],[ LORRY RATE ]] -> 19120 | P20: DONE | Q20: 018 | R20: RECEIPT | S20: 45452 | T20: 45453 | U20: closed | V20: BN
A21: 21 | B21: JUNE | C21: 45455 | D21: BN | E21: JH01KM-4371 | F21: 9025368773 | G21: RANCHI | H21: HOSKOTE,900316 | I21: BOMMANSA,863494 | J21: 24FEET | K21: 44930 | L21: 45040 | M21: =Table1[[#This Row],[Billing Rate Charges]]-Table1[[#This Row],[ LORRY RATE ]] -> 110 | P21: DONE | Q21: 019 | R21: RECEIPT | S21: 45458 | T21: 45458 | U21: closed | V21: BN
A22: 22 | B22: JUNE | C22: 45456 | D22: BN | E22: JH01KM-8803 | F22: 9589264337 | G22: RANCHI | H22: NARSAPUR,763576 | I22: BOMMANSANDRA,516517 | J22: 32FEET SXL | K22: 45170 | L22: 46620 | M22: =Table1[[#This Row],[Billing Rate Charges]]-Table1[[#This Row],[ LORRY RATE ]] -> 1450 | P22: DONE | Q22: 020 | R22: RECEIPT | S22: 45459 | T22: 45462 | U22: closed | V22: BN | W22: LORRY HALTING - EXTRA CHARGE
A23: 23 | B23: JUNE | C23: 45457 | D23: 3rd Party | E23: WB23J-3143 | F23: 9372267009 | G23: ERODE | H23: N/A | I23: RANCHI,241257 | J23: 32FEET MXL | K23: 75570 | L23: 93240 | M23: =Table1[[#This Row],[Billing Rate Charges]]-Table1[[#This Row],[ LORRY RATE ]] -> 17670 | N23: 75570 | O23: =Table1[[#This Row],[ LORRY RATE ]]-Table1[[#This Row],[Adance Paid (INR)]] -> 0 | P23: DONE | Q23: 021 | R23: RECEIPT | S23: 19-06-2024 | T23: 19-06-2024 | U23: closed | V23: Transporter 03
A24: 24 | B24: JUNE | C24: 45458 | D24: 3rd Party | E24: KA05TT-6944 | F24: 9295512602 | G24: RANCHI | H24: N/A | I24: HASSAN,857821 | J24: 24FEET | K24: 27770 | L24: 38740 | M24: =Table1[[#This Row],[Billing Rate Charges]]-Table1[[#This Row],[ LORRY RATE ]] -> 10970 | N24: 27770 | O24: =Table1[[#This Row],[ LORRY RATE ]]-Table1[[#This Row],[Adance Paid (INR)]] -> 0 | P24: DONE | Q24: 022 | R24: RECEIPT | S24: 19-06-2024 | T24: 19-06-2024 | U24: closed | V24: Transporter 02
A25: 25 | B25: JUNE | C25: 45459 | D25: BN | E25: JH01KM-4371 | F25: 9025368773 | G25: ERODE | H25: N/A | I25: RANCHI,454688 | J25: 24FEET | K25: 48290 | L25: 67410 | M25: =Table1[[#This Row],[Billing Rate Charges]]-Table1[[#This Row],[ LORRY RATE ]] -> 19120 | P25: DONE | Q25: 023 | R25: RECEIPT | S25: 18-06-2024 | T25: 18-06-2024 | U25: closed | V25: BN | W25: OVERLOAD - EXTRA CHARGE
A26: 26 | B26: JUNE | C26: 45460 | D26: 3rd Party | E26: KA53T-7407 | F26: 9684865656 | G26: RANCHI | H26: NARSAPUR,795057 | I26: HASSAN,857821 | J26: 20FEET | K26: 26100 | L26: 41900 | M26: =Table1[[#This Row],[Billing Rate Charges]]-Table1[[#This Row],[ LORRY RATE ]] -> 15800 | N26: 26100 | O26: =Table1[[#This Row],[ LORRY RATE ]]-Table1[[#This Row],[Adance Paid (INR)]] -> 0 | P26: DONE | Q26: 025 | R26: RECEIPT | S26: 21-06-2024 | T26: 22-06-2024 | U26: closed | V26: Transporter 02
A27: 27 | B27: JUNE | C27: 45462 | D27: BN | E27: JH01KM-4371 | F27: 9025368773 | G27: RANCHI | H27: N/A | I27: HASSAN,493930 | J27: 24FEET | K27: 46520 | L27: 55600 | M27: =Table1[[#This Row],[Billing Rate Charges]]-Table1[[#This Row],[ LORRY RATE ]] -> 9080 | P27: DONE | Q27: 024 | R27: RECEIPT | S27: 22-06-2024 | T27: 22-06-2024 | U27: closed | V27: BN
A28: 28 | B28: JUNE | C28: 45463 | D28: BN | E28: JH01KM-8803 | F28: 9589264337 | G28: TIRUPUR,484647 | H28: ERODE,743866 | I28: RANCHI | J28: 32FEET SXL | K28: 52820 | L28: 97650 | M28: =Table1[[#This Row],[Billing Rate Charges]]-Table1[[#This Row],[ LORRY RATE ]] -> 44830 | P28: DONE | Q28: 026 | R28: RECEIPT | S28: 23-06-2024 | T28: 23-06-2024 | U28: closed | V28: BN | W28: SPEED MODE MATERIAL EXTRA CHARGE
A29: 29 | B29: JUNE | C29: 45464 | D29: 3rd Party | E29: TN93L-8071 | F29: 9754088991 | G29: RANCHI | H29: NARSAPUR,912069+HOSKOTE,483982 | I29: BOMMANSANDRA,607558 | J29: 32FEET SXL | K29: 33110 | L29: 52920 | M29: =Table1[[#This Row],[Billing Rate Charges]]-Table1[[#This Row],[ LORRY RATE ]] -> 19810 | N29: 33110 | O29: =Table1[[#This Row],[ LORRY RATE ]]-Table1[[#This Row],[Adance Paid (INR)]] -> 0 | P29: DONE | Q29: 027 | R29: RECEIPT | S29: 25-06-2024 | T29: 26-06-2024 | U29: closed | V29: Transporter 02 | W29: MISC NOTE
A30: 30 | B30: JUNE | C30: 45467 | D30: BN | E30: JH01KM-8803 | F30: 9589264337 | G30: RANCHI | H30: HOSKOTE,742750 | I30: HASSAN ,377936 | J30: 32 FEET SXL | K30: 45170 | L30: 46620 | M30: =Table1[[#This Row],[Billing Rate Charges]]-Table1[[#This Row],[ LORRY RATE ]] -> 1450 | O30: 0 | P30: DONE | Q30: 028 | R30: RECEIPT | S30: 27-06-2024 | T30: 27-06-2024 | U30: closed | V30: BN
A31: 31 | B31: JUNE | C31: 45468 | D31: BN | E31: JH01KM-4371 | F31: 9025368773 | G31: HOSUR | H31: N/A | I31: RANCHI,261832 | J31: 24FEET | K31: 48290 | L31: 67410 | M31: =Table1[[#This Row],[Billing Rate Charges]]-Table1[[#This Row],[ LORRY RATE ]] -> 19120 | O31: 0 | P31: DONE | Q31: 029 | R31: RECEIPT | S31: 28-06-2024 | T31: 28-06-2024 | U31: closed | V31: BN
A32: 32 | B32: JUNE | C32: 45469 | D32: 3rd Party | E32: TN52TM-1398 | F32: 9941053951 | G32: RANCHI | H32: N/A | I32: HOSKOTE,491423 | J32: 32FEET SXL | K32: 33890 | L32: 40320 | M32: =Table1[[#This Row],[Billing Rate Charges]]-Table1[[#This Row],[ LORRY RATE ]] -> 6430 | N32: 33890 | O32: =Table1[[#This Row],[ LORRY RATE ]]-Table1[[#This Row],[Adance Paid (INR)]] -> 0 | P32: DONE | Q32: 030 | R32: RECEIPT | S32: 30-06-2024 | T32: 01-07-2024 | U32: closed | V32: Transporter 02
A33: 33 | B33: JUNE | C33: 45470 | D33: 3rd Party | E33: TN18GS-5854 | F33: 9834816284 | G33: RANCHI | H33: N/A | I33: NARSAPUR,366358 | J33: 32FEET SXL | K33: 34840 | L33: 46620 | M33: =Table1[[#This Row],[Billing Rate Charges]]-Table1[[#This Row],[ LORRY RATE ]] -> 11780 | N33: 34840 | O33: =Table1[[#This Row],[ LORRY RATE ]]-Table1[[#This Row],[Adance Paid (INR)]] -> 0 | P33: DONE | Q33: 031 | R33: RECEIPT | S33: 03-07-2024 | T33: 03-07-2024 | U33: closed | V33: Transporter 02 | W33: LORRY HALTING - EXTRA CHARGE
A34: 34 | B34: JULY | C34: 45474 | D34: 3rd Party | E34: GJ27K-9382 | F34: 9660512245 | G34: AHM. | H34: N/A | I34: RANCHI,862761 | J34: 20FEET | K34: 44920 | L34: 56700 | M34: =Table1[[#This Row],[Billing Rate Charges]]-Table1[[#This Row],[ LORRY RATE ]] -> 11780 | N34: 41620 | O34: =Table1[[#This Row],[ LORRY RATE ]]-Table1[[#This Row],[Adance Paid (INR)]] -> 3300 | P34: DONE | Q34: 037 | R34: PENDING | S34: 05-07-2024 | T34: 05-07-2024 | U34: closed | V34: Transporter 04 | W34: MATERIAL SHIFTED TO ANOTHER VEHICLE
A35: 35 | B35: JULY | C35: 45474 | D35: BN | E35: JH01KM-4371 | F35: 9025368773 | G35: RANCHI | H35: HOSKOTE,136530 | I35: HASSAN,323165 | J35: 24FEET | K35: 45740 | L35: 50400 | M35: =Table1[[#This Row],[Billing Rate Charges]]-Table1[[#This Row],[ LORRY RATE ]] -> 4660 | O35: 0 | P35: DONE | Q35: 032 | R35: RECEIPT | S35: 04-07-2024 | T35: 05-07-2024 | U35: closed | V35: BN
A36: 36 | B36: JULY | C36: 45474 | D36: BN | E36: JH01KM-8803 | F36: 9025368773 | G36: TIRUPUR,211792/56 | H36: ERODE,377051 | I36: RANCHI | J36: 32FEET | K36: 53580 | L36: 102690 | M36: =Table1[[#This Row],[Billing Rate Charges]]-Table1[[#This Row],[ LORRY RATE ]] -> 49110 | O36: 0 | P36: DONE | Q36: 033 | R36: RECEIPT | S36: 04-07-2024 | T36: 05-07-2024 | U36: closed | V36: BN
A37: 37 | B37: JULY | C37: 45475 | D37: 3rd Party | E37: KA52W-2643 | F37: 9578386887 | G37: RANCHI | H37: HOSKOTE,042648 | I37: BOMMANSANDRA,693938 | J37: 24FEET | K37: 29180 | L37: 48200 | M37: =Table1[[#This Row],[Billing Rate Charges]]-Table1[[#This Row],[ LORRY RATE ]] -> 19020 | N37: 29180 | O37: =Table1[[#This Row],[ LORRY RATE ]]-Table1[[#This Row],[Adance Paid (INR)]] -> 0 | P37: DONE | Q37: 034 | R37: RECEIPT | S37: 05-07-2024 | T37: 06-07-2024 | U37: closed | V37: Transporter 02 | W37: LORRY HALTING - EXTRA CHARGE
A38: 38 | B38: JULY | C38: 45475 | D38: 3rd Party | E38: TN12XD-6346 | F38: 9678275995 | G38: RANCHI | H38: N/A | I38: NARSAPUR,362044 | J38: 20FEET | K38: 25150 | L38: 35600 | M38: =Table1[[#This Row],[Billing Rate Charges]]-Table1[[#This Row],[ LORRY RATE ]] -> 10450 | N38: 25150 | O38: =Table1[[#This Row],[ LORRY RATE ]]-Table1[[#This Row],[Adance Paid (INR)]] -> 0 | P38: DONE | Q38: 035 | R38: RECEIPT | S38: 09-07-2024 | T38: 09-07-2024 | U38: closed | V38: Transporter 02
A39: 39 | B39: JULY | C39: 45475 | D39: 3rd Party | E39: TN12XD-6346 | F39: 9678275995 | G39: RANCHI | H39: PART LOAD | I39: HOSUR,398331 | J39: 20FEET | K39: 0 | L39: 11500 | M39: =Table1[[#This Row],[Billing Rate Charges]]-Table1[[#This Row],[ LORRY RATE ]] -> 11500 | O39: =Table1[[#This Row],[ LORRY RATE ]]-Table1[[#This Row],[Adance Paid (INR)]] -> 0 | P39: DONE | Q39: 036 | R39: RECEIPT | S39: 09-07-2024 | T39: 09-07-2024 | U39: closed | V39: Transporter 02 | W39: WEIGHT-BASED BILLING (PART LOAD)
A40: 40 | B40: JULY | C40: 45476 | D40: 3rd Party | E40: NL01N-2927 | F40: 9513184912 | G40: RANCHI | H40: NARSAPUR,199550 | I40: BOMMANSANDRA, 387363 | J40: 32 FEET SXL | K40: 35310 | L40: 49770 | M40: =Table1[[#This Row],[Billing Rate Charges]]-Table1[[#This Row],[ LORRY RATE ]] -> 14460 | N40: 35310 | O40: =Table1[[#This Row],[ LORRY RATE ]]-Table1[[#This Row],[Adance Paid (INR)]] -> 0 | P40: DONE | Q40: 038 | R40: RECEIPT | S40: 09-07-2024 | T40: 10-07-2024 | U40: closed | V40: Transporter 05 | W40: LORRY HALTING - EXTRA CHARGE
A41: 41 | B41: JULY | C41: 45477 | D41: 3rd Party | E41: TN88W-4748 | F41: 9593083336 | G41: RANCHI | H41: NARSAPUR,590354 | I41: HASSAN, 125936 | J41: 32FEET SXL | K41: 34810 | L41: 53550 | M41: =Table1[[#This Row],[Billing Rate Charges]]-Table1[[#This Row],[ LORRY RATE ]] -> 18740 | N41: 34810 | O41: =Table1[[#This Row],[ LORRY RATE ]]-Table1[[#This Row],[Adance Paid (INR)]] -> 0 | P41: DONE | Q41: 039 | R41: RECEIPT | S41: 09-07-2024 | T41: 10-07-2024 | U41: closed | V41: Transporter 02
A42: 42 | B42: JULY | C42: 45478 | D42: 3rd Party | E42: JH01DH-4340 | F42: 9137963915 | G42: RANCHI | H42: LOCAL | I42: RANCHI | J42: 10FEET | K42: 1870 | L42: 2840 | M42: =Table1[[#This Row],[Billing Rate Charges]]-Table1[[#This Row],[ LORRY RATE ]] -> 970 | N42: 1870 | O42: =Table1[[#This Row],[ LORRY RATE ]]-Table1[[#This Row],[Adance Paid (INR)]] -> 0 | P42: DONE | Q42: 040 | R42: RECEIPT | S42: 05-07-2024 | T42: 05-07-2024 | U42: closed | V42: Transporter 06 | W42: PICK-UP AND DELIVERY CHARGE ADDED
A43: 43 | B43: JULY | C43: 45478 | D43: 3rd Party | E43: KA52K-7153 | F43: 9599281983 | G43: RANCHI | H43: N/A | I43: NARSAPUR,602705 | J43: 20FEET | K43: 25150 | L43: 35600 | M43: =Table1[[#This Row],[Billing Rate Charges]]-Table1[[#This Row],[ LORRY RATE ]] -> 10450 | N43: 25150 | O43: =Table1[[#This Row],[ LORRY RATE ]]-Table1[[#This Row],[Adance Paid (INR)]] -> 0 | P43: DONE | Q43: 041 | R43: RECEIPT | S43: 09-07-2024 | T43: 09-07-2024 | U43: closed | V43: Transporter 02
A44: 44 | B44: JULY | C44: 45479 | D44: BN | E44: JH01KM-8803 | F44: 9589264337 | G44: RANCHI | H44: HOSKOTE+BMS,185224,176322 | I44: HASSAN,299082 | J44: 32FEET SXL | K44: 47150 | L44: 59850 | M44: =Table1[[#This Row],[Billing Rate Charges]]-Table1[[#This Row],[ LORRY RATE ]] -> 12700 | O44: 0 | P44: DONE | Q44: 042 | R44: RECEIPT | S44: 09-07-2024 | T44: 10-07-2024 | U44: closed | V44: BN
A45: 45 | B45: JULY | C45: 45479 | D45: 3rd Party | E45: TN18DH-3563 | F45: 9343626927 | G45: RANCHI | H45: NARSAPUR,309027 | I45: HOSKOTE,234717 | J45: 32FEET SXL | K45: 33770 | L45: 46620 | M45: =Table1[[#This Row],[Billing Rate Charges]]-Table1[[#This Row],[ LORRY RATE ]] -> 12850 | N45: 33770 | O45: =Table1[[#This Row],[ LORRY RATE ]]-Table1[[#This Row],[Adance Paid (INR)]] -> 0 | P45: DONE | Q45: 043 | R45: RECEIPT | S45: 11-07-2024 | T45: 12-07-2024 | U45: closed | V45: Transporter 07 | W45: LORRY DELAY
A46: 46 | B46: JULY | C46: 45481 | D46: BN | E46: JH01KM-4371 | F46: 9097762415 | G46: ERODE | H46: N/A | I46: RANCHI | J46: 24FEET | K46: 49140 | L46: 73080 | M46: 23940 | O46: 0 | P46: DONE | Q46: 044 | R46: RECEIPT | S46: 10-07-2024 | T46: 11-07-2024 | U46: closed | V46: BN | W46: SPEED MODE MATERIAL EXTRA CHARGE
A47: 47 | B47: JULY | C47: 45482 | D47: 3rd Party | E47: UP21LJ-1159 | F47: 9457796730 | G47: RANCHI | H47: N/A | I47: HASSAN,568746 | J47: 32FEET SXL | K47: 33860 | L47: 47250 | M47: =Table1[[#This Row],[Billing Rate Charges]]-Table1[[#This Row],[ LORRY RATE ]] -> 13390 | N47: 33860 | O47: =Table1[[#This Row],[ LORRY RATE ]]-Table1[[#This Row],[Adance Paid (INR)]] -> 0 | P47: DONE | Q47: 045 | R47: RECEIPT | S47: 12-07-2024 | T47: 12-07-2024 | U47: closed | V47: Transporter 02
A48: 48 | B48: JULY | C48: 45483 | D48: 3rd Party | E48: KA52J-5960 | F48: 9291434058 | G48: RANCHI | H48: NARSAPUR,297445 | I48: HOSUR,469253 | J48: 24FEET | K48: 28710 | L48: 45040 | M48: =Table1[[#This Row],[Billing Rate Charges]]-Table1[[#This Row],[ LORRY RATE ]] -> 16330 | N48: 28710 | O48: =Table1[[#This Row],[ LORRY RATE ]]-Table1[[#This Row],[Adance Paid (INR)]] -> 0 | P48: DONE | Q48: 046 | R48: RECEIPT | S48: 15-07-2024 | T48: 15-07-2024 | U48: closed | V48: Transporter 02
A49: 49 | B49: JULY | C49: 45484 | D49: BN | E49: JH01KM-4371 | F49: 9097762415 | G49: RANCHI | H49: NARSAPUR+HOSKOTE+BMS,862275,600470,484009 | I49: HASSAN,590477 | J49: 24FEET | K49: 47630 | L49: 63000 | M49: =Table1[[#This Row],[Billing Rate Charges]]-Table1[[#This Row],[ LORRY RATE ]] -> 15370 | O49: 0 | P49: DONE | Q49: 047 | R49: RECEIPT | S49: 16-07-2024 | T49: 16-07-2024 | U49: closed | V49: BN
A50: 50 | B50: JULY | C50: 45486 | D50: BN | E50: JH01KM8803 | F50: 9589264337 | G50: TIRUPUR | H50: ERODE,090919 | I50: RANCHI,612989 | J50: 32FEET SXL | K50: 53580 | L50: 102690 | M50: =Table1[[#This Row],[Billing Rate Charges]]-Table1[[#This Row],[ LORRY RATE ]] -> 49110 | O50: 0 | P50: DONE | Q50: 048 | R50: RECEIPT | S50: 16-07-2024 | T50: 16-07-2024 | U50: closed | V50: BN
A51: 51 | B51: JULY | C51: 45486 | D51: 3rd Party | E51: UP21SV-4401 | F51: 9057895037 | G51: LUDHIANA | H51: N/A | I51: RANCHI,473378 | J51: 32FEET SXL | K51: 63160 | L51: 81900 | M51: =Table1[[#This Row],[Billing Rate Charges]]-Table1[[#This Row],[ LORRY RATE ]] -> 18740 | N51: 63160 | O51: =Table1[[#This Row],[ LORRY RATE ]]-Table1[[#This Row],[Adance Paid (INR)]] -> 0 | P51: DONE | Q51: 049 | R51: RECEIPT | S51: 19-07-2024 | T51: 19-07-2024 | U51: closed | V51: Transporter 08
A52: 52 | B52: JULY | C52: 45486 | D52: 3rd Party | E52: TN93L-3191 | F52: 9237773119 | G52: RANCHI | H52: NARSAPUR+BMS,932329,620472 | I52: HOSUR,412908 | J52: 32FEET SXL | K52: 33640 | L52: 52920 | M52: =Table1[[#This Row],[Billing Rate Charges]]-Table1[[#This Row],[ LORRY RATE ]] -> 19280 | N52: 33640 | O52: =Table1[[#This Row],[ LORRY RATE ]]-Table1[[#This Row],[Adance Paid (INR)]] -> 0 | P52: DONE | Q52: 050 | R52: RECEIPT | S52: 18-07-2024 | T52: 18-07-2024 | U52: closed | V52: Transporter 02
A53: 53 | B53: JULY | C53: 45489 | D53: BN | E53: JH01KM-8803 | F53: 9589264337 | G53: RANCHI | H53: NARSAPUR,002622+BMS,068162 | I53: HOSKOTE,102073 | J53: 32FEET SXL | K53: 46960 | L53: 58590 | M53: =Table1[[#This Row],[Billing Rate Charges]]-Table1[[#This Row],[ LORRY RATE ]] -> 11630 | O53: 0 | P53: DONE | Q53: 051 | R53: RECEIPT | S53: 20-07-2024 | T53: 20-07-2024 | U53: closed | V53: BN | W53: SPEED MODE MATERIAL EXTRA CHARGE
A54: 54 | B54: JULY | C54: 45489 | D54: 3rd Party | E54: NL01YH-1190 | F54: 9124137850 | G54: RANCHI | H54: N/A | I54: HASSAN,117872 | J54: 32FEET SXL | K54: 35740 | L54: 47250 | M54: =Table1[[#This Row],[Billing Rate Charges]]-Table1[[#This Row],[ LORRY RATE ]] -> 11510 | N54: 35740 | O54: =Table1[[#This Row],[ LORRY RATE ]]-Table1[[#This Row],[Adance Paid (INR)]] -> 0 | P54: DONE | Q54: 052 | R54: RECEIPT | S54: 20-07-2024 | T54: 20-07-2024 | U54: closed | V54: Transporter 05
A55: 55 | B55: JULY | C55: 45492 | D55: BN | E55: JH01KM-4371 | F55: 9097762415 | G55: ERODE | H55: N/A | I55: RANCHI,448558 | J55: 24FEET | K55: 48290 | L55: 67410 | M55: =Table1[[#This Row],[Billing Rate Charges]]-Table1[[#This Row],[ LORRY RATE ]] -> 19120 | O55: 0 | P55: DONE | Q55: 053 | R55: RECEIPT | S55: 21-07-2024 | T55: 22-07-2024 | U55: closed | V55: BN
A56: 56 | B56: JULY | C56: 45492 | D56: 3rd Party | E56: TN52NV-3691 | F56: 9045944352 | G56: RANCHI | H56: NARSAPUR,220963 | I56: HOSKOTE,617581 | J56: 32FEET SXL | K56: 33230 | L56: 46620 | M56: =Table1[[#This Row],[Billing Rate Charges]]-Table1[[#This Row],[ LORRY RATE ]] -> 13390 | N56: 33230 | O56: =Table1[[#This Row],[ LORRY RATE ]]-Table1[[#This Row],[Adance Paid (INR)]] -> 0 | P56: DONE | Q56: 054 | R56: RECEIPT | S56: 25-07-2024 | T56: 25-07-2024 | U56: closed | V56: Transporter 02 | W56: LORRY BREAK DOWN
A57: 57 | B57: JULY | C57: 45494 | D57: 3rd Party | E57: TN18DH-3563 | F57: 9343626927 | G57: RANCHI | H57: N/A | I57: HASSAN,241354 | J57: 32FEET SXL | K57: 34930 | L57: 47250 | M57: =Table1[[#This Row],[Billing Rate Charges]]-Table1[[#This Row],[ LORRY RATE ]] -> 12320 | N57: 34930 | O57: =Table1[[#This Row],[ LORRY RATE ]]-Table1[[#This Row],[Adance Paid (INR)]] -> 0 | P57: DONE | Q57: 055 | R57: RECEIPT | S57: 25-07-2024 | T57: 25-07-2024 | U57: closed | V57: Transporter 07
A58: 58 | B58: JULY | C58: 45495 | D58: BN | E58: JH01KM-4371 | F58: 9097762415 | G58: RANCHI | H58: N/A | I58: HOSKOTE,471302 | J58: 24FEET | K58: 44930 | L58: 45040 | M58: =Table1[[#This Row],[Billing Rate Charges]]-Table1[[#This Row],[ LORRY RATE ]] -> 110 | O58: 0 | P58: DONE | Q58: 056 | R58: RECEIPT | S58: 25-07-2024 | T58: 25-07-2024 | U58: closed | V58: BN | W58: SPEED MODE MATERIAL EXTRA CHARGE
A59: 59 | B59: JULY | C59: 45496 | D59: 3rd Party | E59: NL01BJ-0985 | F59: 9062194812 | G59: RANCHI | H59: HOSKOTE,659144 | I59: HOSUR,535479 | J59: 32FEET SXL | K59: 31090 | L59: 46620 | M59: =Table1[[#This Row],[Billing Rate Charges]]-Table1[[#This Row],[ LORRY RATE ]] -> 15530 | N59: 31090 | O59: =Table1[[#This Row],[ LORRY RATE ]]-Table1[[#This Row],[Adance Paid (INR)]] -> 0 | P59: DONE | Q59: 057 | R59: RECEIPT | S59: 26-07-2024 | T59: 27-07-2024 | U59: closed | V59: Transporter 02
A60: 60 | B60: JULY | C60: 45496 | D60: BN | E60: JH01KM-8803 | F60: 9589264337 | G60: TIRUPUR,700296 | H60: ERODE,39067 | I60: RANCHI | J60: 32FEET SXL | K60: 53580 | L60: 102690 | M60: =Table1[[#This Row],[Billing Rate Charges]]-Table1[[#This Row],[ LORRY RATE ]] -> 49110 | O60: 0 | P60: DONE | Q60: 058 | R60: RECEIPT | S60: 27-07-2024 | T60: 27-07-2024 | U60: closed | V60: BN
A61: 61 | B61: JULY | C61: 45497 | D61: 3rd Party | E61: KA52W-2384 | F61: 9564370374 | G61: RANCHI | H61: NARSAPUR,701529 | I61: HOSKOTE,550035 | J61: 24FEET | K61: 28710 | L61: 45040 | M61: =Table1[[#This Row],[Billing Rate Charges]]-Table1[[#This Row],[ LORRY RATE ]] -> 16330 | N61: 28710 | O61: =Table1[[#This Row],[ LORRY RATE ]]-Table1[[#This Row],[Adance Paid (INR)]] -> 0 | P61: DONE | Q61: 059 | R61: RECEIPT | S61: 28-07-2024 | T61: 29-07-2024 | U61: closed | V61: Transporter 02
A62: 62 | B62: JULY | C62: 45500 | D62: 3rd Party | E62: NL01TM-4272 | F62: 9124747909 | G62: RANCHI | H62: NARSAPUR,118909 | I62: HASSAN,216580 | J62: 32FEET SXL | K62: 37220 | L62: 53550 | M62: =Table1[[#This Row],[Billing Rate Charges]]-Table1[[#This Row],[ LORRY RATE ]] -> 16330 | N62: 37220 | O62: =Table1[[#This Row],[ LORRY RATE ]]-Table1[[#This Row],[Adance Paid (INR)]] -> 0 | P62: DONE | Q62: 060 | R62: RECEIPT | S62: 30-07-2024 | T62: 31-07-2024 | U62: closed | V62: Transporter 05
A63: 63 | B63: JULY | C63: 45501 | D63: 3rd Party | E63: JH01KM-8803 | F63: 9589264337 | G63: RANCHI | H63: NARSAPUR,362297+HOSKOTE,334147+HOSUR,693307 | I63: BMS,778726 | J63: 32FEET SXL | K63: 47910 | L63: 64890 | M63: =Table1[[#This Row],[Billing Rate Charges]]-Table1[[#This Row],[ LORRY RATE ]] -> 16980 | O63: 0 | P63: DONE | Q63: 061 | R63: RECEIPT | S63: 31-07-2024 | T63: 01-08-2024 | U63: closed | V63: BN | W63: SPEED MODE MATERIAL EXTRA CHARGE
A64: 64 | B64: JULY | C64: 45502 | D64: 3rd Party | E64: JH01KM-4371 | F64: 9097762415 | G64: ERODE | H64: N/A | I64: RANCHI,858226 | J64: 24FEET | K64: 48290 | L64: 67410 | M64: =Table1[[#This Row],[Billing Rate Charges]]-Table1[[#This Row],[ LORRY RATE ]] -> 19120 | O64: 0 | P64: DONE | Q64: 062 | R64: RECEIPT | S64: 02-08-2024 | T64: 02-08-2024 | U64: closed | V64: BN
A65: 65 | B65: JULY | C65: 45503 | D65: 3rd Party | E65: TN05WJ-5569 | F65: 9021782276 | G65: RANCHI | H65: HOSKOTE,150285 | I65: HASSAN,436347 | J65: 20FEET | K65: 29110 | L65: 44100 | M65: =Table1[[#This Row],[Billing Rate Charges]]-Table1[[#This Row],[ LORRY RATE ]] -> 14990 | N65: 29110 | O65: =Table1[[#This Row],[ LORRY RATE ]]-Table1[[#This Row],[Adance Paid (INR)]] -> 0 | P65: DONE | Q65: 063 | R65: RECEIPT | S65: 08-08-2024 | T65: 08-08-2024 | U65: closed | V65: Transporter 02
A66: 66 | B66: JULY | C66: 45504 | D66: 3rd Party | E66: KA52K-5945 | F66: 9926313971 | G66: RANCHI | H66: HOSKOTE,328759 | I66: HASSAN,562566 | J66: 22FEET | K66: 30180 | L66: 44100 | M66: =Table1[[#This Row],[Billing Rate Charges]]-Table1[[#This Row],[ LORRY RATE ]] -> 13920 | N66: 30180 | O66: =Table1[[#This Row],[ LORRY RATE ]]-Table1[[#This Row],[Adance Paid (INR)]] -> 0 | P66: DONE | Q66: 064 | R66: RECEIPT | S66: 05-08-2024 | T66: 06-08-2024 | U66: closed | V66: Transporter 02
A67: 67 | B67: AUGUST | C67: 45505 | D67: 3rd Party | E67: WB17-0431 | F67: 9286629206 | G67: HOSUR | H67: N/A | I67: RANCHI,128779 | J67: 32FEET MXL | K67: 82150 | L67: 112140 | M67: =Table1[[#This Row],[Billing Rate Charges]]-Table1[[#This Row],[ LORRY RATE ]] -> 29990 | N67: 82150 | O67: =Table1[[#This Row],[ LORRY RATE ]]-Table1[[#This Row],[Adance Paid (INR)]] -> 0 | P67: DONE | Q67: 065 | R67: RECEIPT | S67: 05-08-2024 | T67: 05-08-2024 | U67: closed | V67: Transporter 09 | W67: OVERLOAD - EXTRA CHARGE
A68: 68 | B68: AUGUST | C68: 45506 | D68: BN | E68: JH01KM-8803 | F68: 9589264337 | G68: TIRUPUR | H68: ERODE,156406 | I68: RANCHI,505803 | J68: 32FEET SXL | K68: 53580 | L68: 102690 | M68: =Table1[[#This Row],[Billing Rate Charges]]-Table1[[#This Row],[ LORRY RATE ]] -> 49110 | O68: 0 | P68: DONE | Q68: 066 | R68: RECEIPT | S68: 05-08-2024 | T68: 06-08-2024 | U68: closed | V68: BN
A69: 69 | B69: AUGUST | C69: 45507 | D69: 3rd Party | E69: PB10UW-4147 | F69: 9976081007 | G69: LUDHIANA | H69: N/A | I69: RANCHI,093231 | J69: 32FEET SXL | K69: 64230 | L69: 81900 | M69: =Table1[[#This Row],[Billing Rate Charges]]-Table1[[#This Row],[ LORRY RATE ]] -> 17670 | N69: 64230 | O69: =Table1[[#This Row],[ LORRY RATE ]]-Table1[[#This Row],[Adance Paid (INR)]] -> 0 | P69: DONE | Q69: 067 | R69: RECEIPT | S69: 09-08-2024 | T69: 09-08-2024 | U69: closed | V69: Transporter 10
A70: 70 | B70: AUGUST | C70: 45508 | D70: BN | E70: JH01KM-4371 | F70: 9515412075 | G70: RANCHI | H70: HOSUR,044633+BMS,889749+WHITEFIELD,361169 | I70: HASSAN,149999 | J70: 24FEET SXL | K70: 47630 | L70: 63000 | M70: =Table1[[#This Row],[Billing Rate Charges]]-Table1[[#This Row],[ LORRY RATE ]] -> 15370 | O70: 0 | P70: DONE | Q70: 068 | R70: RECEIPT | S70: 08-08-2024 | T70: 08-08-2024 | U70: closed | V70: BN
A71: 71 | B71: AUGUST | C71: 45510 | D71: BN | E71: JH01KM-8803 | F71: 9589264337 | G71: RANCHI | H71: NARSAPUR,090549+HOSKOTE,595919+HOSUR,927 | I71: HASSAN,596476 | J71: 32FEETSXL | K71: 48100 | L71: 66150 | M71: =Table1[[#This Row],[Billing Rate Charges]]-Table1[[#This Row],[ LORRY RATE ]] -> 18050 | O71: 0 | P71: DONE | Q71: 069 | R71: RECEIPT | S71: 11-08-2024 | T71: 12-08-2024 | U71: closed | V71: BN
A72: 72 | B72: AUGUST | C72: 45510 | D72: 3rd Party | E72: TN25MM-5315 | F72: 9663777426 | G72: RANCHI | H72: HOSKOTE,613421 | I72: HOSUR,903559(AMOUNT 76215) | J72: 22FEET | K72: 29590 | L72: 54500 | M72: =Table1[[#This Row],[Billing Rate Charges]]-Table1[[#This Row],[ LORRY RATE ]] -> 24910 | N72: 29590 | O72: =Table1[[#This Row],[ LORRY RATE ]]-Table1[[#This Row],[Adance Paid (INR)]] -> 0 | P72: DONE | Q72: 82 | R72: PENDING | S72: 11-08-2024 | T72: 12-08-2024 | U72: closed | V72: Transporter 02
A73: 73 | B73: AUGUST | C73: 45513 | D73: 3rd Party | E73: HR38K-4865 | F73: 9946150873 | G73: ERODE | H73: N/A | I73: RANCHI | J73: 32FEET SXL | K73: 69080 | L73: 96390 | M73: =Table1[[#This Row],[Billing Rate Charges]]-Table1[[#This Row],[ LORRY RATE ]] -> 27310 | N73: 69080 | O73: =Table1[[#This Row],[ LORRY RATE ]]-Table1[[#This Row],[Adance Paid (INR)]] -> 0 | P73: DONE | Q73: 83 | R73: PENDING | S73: 13-08-2024 | T73: 13-08-2024 | U73: closed | V73: Transporter 11
A74: 74 | B74: AUGUST | C74: 45513 | D74: 3rd Party | E74: KA51DJ-7560 | F74: 9493729110 | G74: RANCHI | H74: BMS,415100+HSOKOTE,050034 | I74: HASSAN,969311 | J74: 22FEET | K74: 30590 | L74: 50400 | M74: =Table1[[#This Row],[Billing Rate Charges]]-Table1[[#This Row],[ LORRY RATE ]] -> 19810 | N74: 30590 | O74: =Table1[[#This Row],[ LORRY RATE ]]-Table1[[#This Row],[Adance Paid (INR)]] -> 0 | P74: DONE | Q74: 84 | R74: PENDING | S74: 14-08-2024 | T74: 14-08-2024 | U74: closed | V74: Transporter 02
A75: 75 | B75: AUGUST | C75: 45514 | D75: 3rd Party | E75: TN02ZE-2186 | F75: 9065465756 | G75: RANCHI | H75: NARSAPUR,592+HOSKOTE,189304 | I75: BMS,864438 | J75: 32FEET SXL | K75: 32570 | L75: 52920 | M75: =Table1[[#This Row],[Billing Rate Charges]]-Table1[[#This Row],[ LORRY RATE ]] -> 20350 | N75: 32570 | O75: =Table1[[#This Row],[ LORRY RATE ]]-Table1[[#This Row],[Adance Paid (INR)]] -> 0 | P75: DONE | Q75: 85 | R75: PENDING | S75: 16-08-2024 | T75: 16-08-2024 | U75: closed | V75: Transporter 12
A76: 76 | B76: AUGUST | C76: 45515 | D76: 3rd party | E76: TN01FG-7374 | F76: 9892288874 | G76: RANCHI | H76: HOSKOTE,987663 | I76: BMS,789024 | J76: 32FEET SXL | K76: 31630 | L76: 46620 | M76: =Table1[[#This Row],[Billing Rate Charges]]-Table1[[#This Row],[ LORRY RATE ]] -> 14990 | N76: 31630 | O76: =Table1[[#This Row],[ LORRY RATE ]]-Table1[[#This Row],[Adance Paid (INR)]] -> 0 | P76: DONE | Q76: 86 | R76: PENDING | S76: 16-08-2024 | T76: 16-08-2024 | U76: closed | V76: Transporter 12
A77: 77 | B77: AUGUST | C77: 45515 | D77: BN | E77: JH01KM-4371 | F77: 9515412075 | G77: ERODE | H77: N/A | I77: RANCHI,068347 | J77: 24FEET | K77: 49140 | L77: 73080 | M77: =Table1[[#This Row],[Billing Rate Charges]]-Table1[[#This Row],[ LORRY RATE ]] -> 23940 | O77: 0 | P77: DONE | Q77: 87 | R77: PENDING | S77: 16-08-2024 | T77: 16-08-2024 | U77: closed | V77: BN | W77: SPEED MODE MATERIAL EXTRA CHARGE
A78: 78 | B78: AUGUST | C78: 45517 | D78: 3rd Party | E78: KA52K-1206 | F78: 9139770277 | G78: RANCHI | H78: HOSKOTE,781390 | I78: HASSAN,975201 | J78: 20FEET | K78: 29520 | L78: 50400 | M78: =Table1[[#This Row],[Billing Rate Charges]]-Table1[[#This Row],[ LORRY RATE ]] -> 20880 | N78: 29520 | O78: =Table1[[#This Row],[ LORRY RATE ]]-Table1[[#This Row],[Adance Paid (INR)]] -> 0 | P78: DONE | Q78: 88 | R78: PENDING | S78: 16-08-2024 | T78: 16-08-2024 | U78: closed | V78: Transporter 02
A79: 79 | B79: AUGUST | C79: 45518 | D79: BN | E79: JH01KM-4371 | F79: 9515412075 | G79: RANCHI | H79: BMS,846401 | I79: HASSAN,928118 | J79: 24FEET | K79: 46590 | L79: 56070 | M79: =Table1[[#This Row],[Billing Rate Charges]]-Table1[[#This Row],[ LORRY RATE ]] -> 9480 | N79: 46590 | O79: =Table1[[#This Row],[ LORRY RATE ]]-Table1[[#This Row],[Adance Paid (INR)]] -> 0 | P79: DONE | Q79: 89 | R79: PENDING | S79: 16-08-2024 | T79: 16-08-2024 | U79: closed | V79: BN | W79: SPEED MODE MATERIAL EXTRA CHARGE
A80: 80 | B80: AUGUST | C80: 45518 | D80: 3rd Party | E80: NL01JS-2253 | F80: 9577978275 | G80: RANCHI | H80: NARSAPUR,542310 | I80: HOSKOTE,530353 | J80: 32FEET SXL | K80: 31630 | L80: 46620 | M80: =Table1[[#This Row],[Billing Rate Charges]]-Table1[[#This Row],[ LORRY RATE ]] -> 14990 | N80: 31630 | O80: =Table1[[#This Row],[ LORRY RATE ]]-Table1[[#This Row],[Adance Paid (INR)]] -> 0 | P80: DONE | Q80: 90 | R80: PENDING | S80: 19-08-2024 | T80: 19-08-2024 | U80: closed | V80: Transporter 02
A81: 81 | B81: AUGUST | C81: 45518 | D81: 3rd Party | E81: KA51YH-4062 | F81: 9573610475 | G81: RANCHI | H81: N/A | I81: HASSAN,421295 | J81: 32FEET SXL | K81: 36540 | L81: 47250 | M81: =Table1[[#This Row],[Billing Rate Charges]]-Table1[[#This Row],[ LORRY RATE ]] -> 10710 | N81: 36540 | O81: =Table1[[#This Row],[ LORRY RATE ]]-Table1[[#This Row],[Adance Paid (INR)]] -> 0 | P81: DONE | Q81: 91 | R81: PENDING | S81: 18-08-2024 | T81: 18-08-2024 | U81: closed | V81: Transporter 02
A82: 82 | B82: AUGUST | C82: 45518 | D82: 3rd Party | E82: BY AIR | G82: RANCHI | H82: N/A | I82: BMS,334059 | J82: FLIGHT | K82: 209420 | L82: 264250 | M82: =Table1[[#This Row],[Billing Rate Charges]]-Table1[[#This Row],[ LORRY RATE ]] -> 54830 | N82: 209420 | O82: =Table1[[#This Row],[ LORRY RATE ]]-Table1[[#This Row],[Adance Paid (INR)]] -> 0 | P82: PENDING | R82: PENDING | S82: 16-08-2024 | T82: 16-08-2024 | U82: closed | V82: BY AIR
A83: 83 | B83: AUGUST | C83: 45519 | D83: BN | E83: JH01KM-8803 | F83: 9589264337 | G83: ERODE | H83: N/A | I83: RANCHI,506848 | J83: 32FEET SXL | K83: 52630 | L83: 96390 | M83: =Table1[[#This Row],[Billing Rate Charges]]-Table1[[#This Row],[ LORRY RATE ]] -> 43760 | O83: 0 | P83: DONE | Q83: 92 | R83: PENDING | S83: 18-08-2024 | T83: 18-08-2024 | U83: closed | V83: BN
A84: 84 | B84: AUGUST | C84: 45520 | D84: 3rd Party | E84: KL59NV-3787 | F84: 9316665035 | G84: RANCHI | H84: N/A | I84: HASSAN,820548 | J84: 25FEET | K84: 30710 | L84: 44100 | M84: =Table1[[#This Row],[Billing Rate Charges]]-Table1[[#This Row],[ LORRY RATE ]] -> 13390 | N84: 30710 | O84: =Table1[[#This Row],[ LORRY RATE ]]-Table1[[#This Row],[Adance Paid (INR)]] -> 0 | P84: DONE | Q84: 93 | R84: PENDING | S84: 20-08-2024 | T84: 20-08-2024 | U84: closed | V84: Transporter 02
A85: 85 | B85: AUGUST | C85: 45520 | D85: 3rd Party | E85: KA13T-7124 | F85: 9742039597 | G85: RANCHI | H85: HOSKOTE,090684+HOSUR,678655 | I85: HASSAN,729295 | J85: 24FEET | K85: 33140 | L85: 56700 | M85: =Table1[[#This Row],[Billing Rate Charges]]-Table1[[#This Row],[ LORRY RATE ]] -> 23560 | N85: 33140 | O85: =Table1[[#This Row],[ LORRY RATE ]]-Table1[[#This Row],[Adance Paid (INR)]] -> 0 | P85: DONE | Q85: 94 | R85: PENDING | S85: 21-08-2024 | T85: 21-08-2024 | U85: closed | V85: Transporter 02
A86: 86 | B86: AUGUST | C86: 45524 | D86: BN | E86: JH01KM-4371 | F86: 9515412075 | G86: RANCHI | H86: N/A | I86: HASSAN | J86: 24FEET | K86: 51880 | L86: 91350 | M86: =Table1[[#This Row],[Billing Rate Charges]]-Table1[[#This Row],[ LORRY RATE ]] -> 39470 | O86: 0 | P86: DONE | Q86: 95 | R86: PENDING | S86: 23-08-2024 | T86: 24-08-2024 | U86: closed | V86: BN
A87: 87 | B87: AUGUST | C87: 45525 | D87: BN | E87: JH01KM-8803 | F87: 9589264337 | G87: RANCHI | H87: BOMMANSANDRA,467189 | I87: HOSUR,630362 (76215) | J87: 32FEET SXL | K87: 45170 | L87: 46620 | M87: =Table1[[#This Row],[Billing Rate Charges]]-Table1[[#This Row],[ LORRY RATE ]] -> 1450 | O87: 0 | P87: DONE | Q87: 96 | R87: PENDING | S87: 25-08-2024 | T87: 26-08-2024 | U87: closed | V87: BN
A88: 88 | B88: AUGUST | C88: 45528 | D88: 3rd Party | E88: TN02EV-8853 | F88: 9772336065 | G88: RANCHI | H88: NARSAPUR,219420 | I88: BOMMANSANDRA,071351 | J88: 32FEET SXL | K88: 33770 | L88: 46620 | M88: =Table1[[#This Row],[Billing Rate Charges]]-Table1[[#This Row],[ LORRY RATE ]] -> 12850 | N88: 33770 | O88: =Table1[[#This Row],[ LORRY RATE ]]-Table1[[#This Row],[Adance Paid (INR)]] -> 0 | P88: DONE | Q88: 97 | R88: PENDING | S88: 28-08-2024 | T88: 28-08-2024 | U88: closed | V88: Transporter 02
A89: 89 | B89: AUGUST | C89: 45528 | D89: 3rd Party | E89: MH14CY-6391 | F89: 9788395365 | G89: ERODE | H89: N/A | I89: RANCHI | J89: 32FEET SXL | K89: 67210 | L89: 96390 | M89: =Table1[[#This Row],[Billing Rate Charges]]-Table1[[#This Row],[ LORRY RATE ]] -> 29180 | N89: 67210 | O89: =Table1[[#This Row],[ LORRY RATE ]]-Table1[[#This Row],[Adance Paid (INR)]] -> 0 | P89: DONE | Q89: 98 | R89: PENDING | S89: 29-08-2024 | T89: 29-08-2024 | U89: closed | V89: Transporter 13
A90: 90 | B90: AUGUST | C90: 45528 | D90: 3rd Party | E90: TN02ZE-2186 | F90: 9065465756 | G90: RANCHI | H90: N/A | I90: HASSAN,452608 | J90: 32FEET SXL | K90: 40160 | L90: 53550 | M90: =Table1[[#This Row],[Billing Rate Charges]]-Table1[[#This Row],[ LORRY RATE ]] -> 13390 | N90: 40160 | O90: =Table1[[#This Row],[ LORRY RATE ]]-Table1[[#This Row],[Adance Paid (INR)]] -> 0 | P90: DONE | Q90: 99 | R90: PENDING | S90: 29-08-2024 | T90: 29-08-2024 | U90: closed | V90: Transporter 12 | W90: OVERLOAD - EXTRA CHARGE
A91: 91 | B91: AUGUST | C91: 45528 | D91: 3rd Party | E91: KA05GM-9110 | F91: 9748894966 | G91: RANCHI | H91: N/A | I91: HOSUR,731673(78679) | J91: 20FEET | K91: 25690 | L91: 35600 | M91: =Table1[[#This Row],[Billing Rate Charges]]-Table1[[#This Row],[ LORRY RATE ]] -> 9910 | N91: 25690 | O91: =Table1[[#This Row],[ LORRY RATE ]]-Table1[[#This Row],[Adance Paid (INR)]] -> 0 | P91: DONE | Q91: 100 | R91: PENDING | S91: 28-08-2024 | T91: 28-08-2024 | U91: closed | V91: Transporter 02
A92: 92 | B92: AUGUST | C92: 45528 | D92: 3rd Party | E92: TN93L-8071 | F92: 9950818773 | G92: RANCHI | H92: NARSAPUR,415768 +HOSKOTE,364185 | I92: BOMMANSANDRA,901796 | J92: 32FEET SXL | K92: 33640 | L92: 52920 | M92: =Table1[[#This Row],[Billing Rate Charges]]-Table1[[#This Row],[ LORRY RATE ]] -> 19280 | N92: 33640 | O92: =Table1[[#This Row],[ LORRY RATE ]]-Table1[[#This Row],[Adance Paid (INR)]] -> 0 | P92: DONE | Q92: 101 | R92: PENDING | S92: 28-08-2024 | T92: 28-08-2024 | U92: closed | V92: Transporter 02
A93: 93 | B93: AUGUST | C93: 45531 | D93: 3rd Party | E93: KA52K-7446 | F93: 9923171297 | G93: RANCHI | H93: N/A | I93: HOSUR,556621 (89221) | J93: 22FEET | K93: 25690 | L93: 35600 | M93: =Table1[[#This Row],[Billing Rate Charges]]-Table1[[#This Row],[ LORRY RATE ]] -> 9910 | N93: 25690 | O93: =Table1[[#This Row],[ LORRY RATE ]]-Table1[[#This Row],[Adance Paid (INR)]] -> 0 | P93: DONE | Q93: 102 | R93: PENDING | S93: 30-08-2024 | T93: 30-08-2024 | U93: closed | V93: Transporter 02
A94: 94 | B94: AUGUST | C94: 45531 | D94: 3rd Party | E94: TN18DH-3563 | F94: 9358929187 | G94: RANCHI | H94: N/A | I94: HOSUR,450806 (86986) | J94: 32FEET SXL | K94: 34300 | L94: 46620 | M94: =Table1[[#This Row],[Billing Rate Charges]]-Table1[[#This Row],[ LORRY RATE ]] -> 12320 | N94: 34300 | O94: =Table1[[#This Row],[ LORRY RATE ]]-Table1[[#This Row],[Adance Paid (INR)]] -> 0 | P94: DONE | Q94: 103 | R94: PENDING | S94: 31-08-2024 | T94: 31-08-2024 | U94: closed | V94: Transporter 07 | W94: OVERLOAD - EXTRA CHARGE
A95: 95 | B95: AUGUST | C95: 45531 | D95: 3rd Party | E95: KA53NV-5673 | F95: 9165942602 | G95: RANCHI | H95: BMS | I95: HASSAN | J95: 22FEET | K95: 29550 | L95: 43470 | M95: =Table1[[#This Row],[Billing Rate Charges]]-Table1[[#This Row],[ LORRY RATE ]] -> 13920 | N95: 29550 | O95: =Table1[[#This Row],[ LORRY RATE ]]-Table1[[#This Row],[Adance Paid (INR)]] -> 0 | P95: DONE | Q95: 104 | R95: PENDING | S95: 31-08-2024 | T95: 31-08-2024 | U95: closed | V95: Transporter 02 | W95: SPEED MODE MATERIAL EXTRA CHARGE
A96: 96 | B96: AUGUST | C96: 45531 | D96: BN | E96: JH01KM-4371 | F96: 9515412075 | G96: RANCHI | H96: HOSKOTE | I96: BOMMANSANDRA | J96: 24FEET | K96: 44930 | L96: 45040 | M96: =Table1[[#This Row],[Billing Rate Charges]]-Table1[[#This Row],[ LORRY RATE ]] -> 110 | O96: 0 | P96: DONE | Q96: 105 | R96: PENDING | S96: 31-08-2024 | T96: 31-08-2024 | U96: closed | V96: BN
A97: 97 | B97: AUGUST | C97: 45533 | D97: BN | E97: JH01KM-8803 | F97: 9589264337 | G97: TIRUPUR | H97: ERODE | I97: RANCHI | J97: 32FEET SXL | K97: 53580 | L97: 102690 | M97: =Table1[[#This Row],[Billing Rate Charges]]-Table1[[#This Row],[ LORRY RATE ]] -> 49110 | O97: 0 | P97: DONE | Q97: 106 | R97: PENDING | S97: 02-09-2024 | T97: 02-09-2024 | U97: closed | V97: BN
A98: 98 | B98: AUGUST | C98: 45533 | D98: 3rd Party | E98: KA52K-0229 | F98: 9654538123 | G98: RANCHI | H98: N/A | I98: HOSUR,769145 | J98: 20FEET | K98: 27610 | L98: 41260 | M98: =Table1[[#This Row],[Billing Rate Charges]]-Table1[[#This Row],[ LORRY RATE ]] -> 13650 | N98: 27610 | O98: =Table1[[#This Row],[ LORRY RATE ]]-Table1[[#This Row],[Adance Paid (INR)]] -> 0 | P98: DONE | Q98: 107 | R98: PENDING | S98: 31-08-2024 | T98: 31-08-2024 | U98: closed | V98: Transporter 02 | W98: SPEED MODE MATERIAL EXTRA CHARGE
A99: 99 | B99: AUGUST | C99: 45533 | D99: 3rd Party | E99: NL01JH-8344 | F99: 9812468058 | G99: RANCHI | H99: HOSKOTE | I99: BOMMANSANDRA | J99: 32FEET SXL | K99: 34300 | L99: 46620 | M99: =Table1[[#This Row],[Billing Rate Charges]]-Table1[[#This Row],[ LORRY RATE ]] -> 12320 | N99: 34300 | O99: =Table1[[#This Row],[ LORRY RATE ]]-Table1[[#This Row],[Adance Paid (INR)]] -> 0 | P99: DONE | Q99: 108 | R99: PENDING | S99: 02-09-2024 | T99: 03-09-2024 | U99: closed | V99: Transporter 05
A100: 100 | B100: AUGUST | C100: 45533 | D100: 3rd Party | E100: KA51GM-6709 | F100: 9563961453 | G100: RANCHI | H100: HOSUR,186467 | I100: HASSAN | J100: 20FEET | K100: 30180 | L100: 44100 | M100: =Table1[[#This Row],[Billing Rate Charges]]-Table1[[#This Row],[ LORRY RATE ]] -> 13920 | N100: 30180 | O100: =Table1[[#This Row],[ LORRY RATE ]]-Table1[[#This Row],[Adance Paid (INR)]] -> 0 | P100: DONE | Q100: 109 | R100: PENDING | S100: 02-09-2024 | T100: 04-09-2024 | U100: closed | V100: Transporter 14
...

Sheet AUBURN LOAD CLEAN
A1: AUBURN LOAD REGISTER — BN LOGISTICS
A2: LOADS | B2: =SUMPRODUCT(--(AUBURN[LOADING DATE]<>"")) -> 1114 | D2: LORRY RATE PAID | E2: =SUM(AUBURN[LORRY RATE (₹)]) -> 45985070 | G2: MARGIN % | H2: =IFERROR($E$4/$E$3,"") -> 0.39240619 | J2: OWN FLEET (BN) LOADS | K2: =COUNTIF(AUBURN[PROVIDER],"BN") -> 684 | M2: Blue = you type it
A3: PERIOD | B3: =TEXT(MIN(AUBURN[LOADING DATE]),"mmm yyyy")&" to "&TEXT(MAX(AUBURN[LOADING DATE]),"mmm yyyy") -> May 2024 to Sep 2026 | D3: BILLED TO AUBURN | E3: =SUM(AUBURN[BILLING RATE (₹)]) -> 75694270 | G3: ADVANCE PAID | H3: =SUM(AUBURN[ADVANCE PAID (₹)]) -> 43905850 | J3: 3RD PARTY LOADS | K3: =COUNTIF(AUBURN[PROVIDER],"3rd Party") -> 430 | M3: Black = calculated, do not type
A4: AVG TRANSIT DAYS | B4: =IFERROR(AVERAGE(AUBURN[TRANSIT DAYS]),"") -> 3.8969754 | D4: NET SAVING | E4: =SUM(AUBURN[NET SAVING (₹)]) -> 29702900 | G4: BALANCE TO PAY | H4: =SUM(AUBURN[BALANCE TO PAY (₹)]) -> 118940 | J4: NO ADVANCE LOGGED | K4: =COUNTIF(AUBURN[LORRY RATE (₹)],">0")-SUMPRODUCT((AUBURN[LORRY RATE (₹)]>0)*(AUBURN[ADVANCE PAID (₹)]<>"")) -> 41 | M4: AA:AB (grouped) keep the original date text for traceability
A6: S.NO. | B6: LOADING DATE | C6: MONTH | D6: PROVIDER | E6: LORRY NO. | F6: MOBILE NO. | G6: FROM | H6: POINT GR NO. | I6: TO GR NO. | J6: LORRY MAKE | K6: LORRY RATE (₹) | L6: BILLING RATE (₹) | M6: NET SAVING (₹) | N6: MARGIN % | O6: ADVANCE PAID (₹) | P6: BALANCE TO PAY (₹) | Q6: BILL STATUS | R6: INVOICE NO. | S6: PAYMENT STATUS | T6: REACH DATE | U6: UNLOAD DATE | V6: UNLOAD END | W6: TRANSIT DAYS | X6: CURRENT STATUS | Y6: BROKER ADDRESS | Z6: REMARKS | AA6: REACH AS LOGGED | AB6: UNLOAD AS LOGGED
A7: =IF($B7="","",ROW()-6) -> 1 | B7: 45422 | C7: =IF($B7="","",EOMONTH($B7,-1)+1) -> 45413 | D7: 3rd Party | E7: TN52TM-7760 | F7: 9686844715 | G7: RANCHI | H7: HASSAN.176610,BOX 04 | I7: BOMMANSA.562608,BOX 578 | J7: 32FEET SXL | K7: 38590 | L7: 46620 | M7: =IF(OR($K7="",$L7=""),"",$L7-$K7) -> 8030 | N7: =IF(OR($L7="",$L7=0,$M7=""),"",$M7/$L7) -> 0.17224367 | O7: 38590 | P7: =IF(OR($K7="",$O7=""),"",$K7-$O7) -> 0 | Q7: DONE | R7: 1 | S7: RECEIPT | T7: 45422 | U7: 45427 | V7: 45430 | W7: =IF(OR($B7="",$U7=""),"",$U7-$B7) -> 5 | X7: Closed | Y7: Transporter 01 | AA7: SAME DAY | AB7: 15/05/2024./18/05/2024
A8: =IF($B8="","",ROW()-6) -> 2 | B8: 45427 | C8: =IF($B8="","",EOMONTH($B8,-1)+1) -> 45413 | D8: 3rd Party | E8: TN52TM-1398 | F8: 9941053951 | G8: RANCHI | H8: HOSKOTE.749378,BOX 983 | I8: HASSAN,772300,BOX 004 | J8: 32FEET SXL | K8: 36450 | L8: 46620 | M8: =IF(OR($K8="",$L8=""),"",$L8-$K8) -> 10170 | N8: =IF(OR($L8="",$L8=0,$M8=""),"",$M8/$L8) -> 0.21814672 | O8: 36450 | P8: =IF(OR($K8="",$O8=""),"",$K8-$O8) -> 0 | Q8: DONE | R8: 2 | S8: RECEIPT | T8: 45431 | U8: 45432 | V8: 45434 | W8: =IF(OR($B8="",$U8=""),"",$U8-$B8) -> 5 | X8: Closed | Y8: Transporter 02 | AB8: 20/05/2024./22/05/2024
A9: =IF($B9="","",ROW()-6) -> 3 | B9: 45431 | C9: =IF($B9="","",EOMONTH($B9,-1)+1) -> 45413 | D9: 3rd Party | E9: KA05TT-6944 | F9: 9295512602 | G9: RANCHI | H9: NARSAPUR.043922.BOX | I9: HASSAN,978172.BOX | J9: 24FEET | K9: 31930 | L9: 45040 | M9: =IF(OR($K9="",$L9=""),"",$L9-$K9) -> 13110 | N9: =IF(OR($L9="",$L9=0,$M9=""),"",$M9/$L9) -> 0.2910746 | O9: 31930 | P9: =IF(OR($K9="",$O9=""),"",$K9-$O9) -> 0 | Q9: DONE | R9: 3 | S9: RECEIPT | T9: 45433 | U9: 45433 | V9: 45434 | W9: =IF(OR($B9="",$U9=""),"",$U9-$B9) -> 2 | X9: Closed | Y9: Transporter 02 | AB9: 21/05/2024./22/05/2024
A10: =IF($B10="","",ROW()-6) -> 4 | B10: 45430 | C10: =IF($B10="","",EOMONTH($B10,-1)+1) -> 45413 | D10: 3rd Party | E10: KA02GM-9724 | F10: 9149905009 | G10: RANCHI | H10: N/A | I10: HASSAN.909686.BOX 312 | J10: 22FEET | K10: 28300 | L10: 38740 | M10: =IF(OR($K10="",$L10=""),"",$L10-$K10) -> 10440 | N10: =IF(OR($L10="",$L10=0,$M10=""),"",$M10/$L10) -> 0.2694889 | O10: 28300 | P10: =IF(OR($K10="",$O10=""),"",$K10-$O10) -> 0 | Q10: DONE | R10: 4 | S10: RECEIPT | T10: 45433 | U10: 45433 | W10: =IF(OR($B10="",$U10=""),"",$U10-$B10) -> 3 | X10: Closed | Y10: Transporter 02
A11: =IF($B11="","",ROW()-6) -> 5 | B11: 45431 | C11: =IF($B11="","",EOMONTH($B11,-1)+1) -> 45413 | D11: 3rd Party | E11: TN12RW-1972 | F11: 9678275995 | G11: RANCHI | H11: N/A | I11: HOSKOTE.125550.BOX 729 | J11: 20FEET | K11: 27830 | L11: 35600 | M11: =IF(OR($K11="",$L11=""),"",$L11-$K11) -> 7770 | N11: =IF(OR($L11="",$L11=0,$M11=""),"",$M11/$L11) -> 0.21825843 | O11: 27830 | P11: =IF(OR($K11="",$O11=""),"",$K11-$O11) -> 0 | Q11: DONE | R11: 5 | S11: RECEIPT | T11: 45433 | U11: 45433 | W11: =IF(OR($B11="",$U11=""),"",$U11-$B11) -> 2 | X11: Closed | Y11: Transporter 02
A12: =IF($B12="","",ROW()-6) -> 6 | B12: 45436 | C12: =IF($B12="","",EOMONTH($B12,-1)+1) -> 45413 | D12: 3rd Party | E12: KA51DJ-2589 | F12: 9087547668 | G12: RANCHI | H12: NARSAPUR,803363 | I12: HOSKOTE,467212 | J12: 20FEET | K12: 29850 | L12: 41900 | M12: =IF(OR($K12="",$L12=""),"",$L12-$K12) -> 12050 | N12: =IF(OR($L12="",$L12=0,$M12=""),"",$M12/$L12) -> 0.2875895 | O12: 29850 | P12: =IF(OR($K12="",$O12=""),"",$K12-$O12) -> 0 | Q12: DONE | R12: 6 | S12: RECEIPT | T12: 45440 | U12: 45440 | W12: =IF(OR($B12="",$U12=""),"",$U12-$B12) -> 4 | X12: Closed | Y12: Transporter 02
A13: =IF($B13="","",ROW()-6) -> 7 | B13: 45442 | C13: =IF($B13="","",EOMONTH($B13,-1)+1) -> 45413 | D13: 3rd Party | E13: PB13MM-3286 | F13: 9757815238 | G13: RANCHI | H13: N/A | I13: HOKOTE,579908 | J13: 32FEET SXL | K13: 32290 | L13: 40320 | M13: =IF(OR($K13="",$L13=""),"",$L13-$K13) -> 8030 | N13: =IF(OR($L13="",$L13=0,$M13=""),"",$M13/$L13) -> 0.19915675 | O13: 32290 | P13: =IF(OR($K13="",$O13=""),"",$K13-$O13) -> 0 | Q13: DONE | R13: 7 | S13: RECEIPT | T13: 45417 | U13: 45417 | W13: =IF(OR($B13="",$U13=""),"",$U13-$B13) -> -25 | X13: Closed | Y13: Transporter 01
A14: =IF($B14="","",ROW()-6) -> 8 | B14: 45436 | C14: =IF($B14="","",EOMONTH($B14,-1)+1) -> 45413 | D14: BN | E14: JH01KM-4371 | F14: 9025368773 | G14: RANCHI | H14: N/A | I14: HOSKOTE,749252 | J14: 24FEET SXL | K14: 43990 | L14: 38740 | M14: =IF(OR($K14="",$L14=""),"",$L14-$K14) -> -5250 | N14: =IF(OR($L14="",$L14=0,$M14=""),"",$M14/$L14) -> -0.13551884 | P14: =IF(OR($K14="",$O14=""),"",$K14-$O14) | Q14: DONE | R14: 8 | S14: RECEIPT | T14: 45439 | U14: 45440 | W14: =IF(OR($B14="",$U14=""),"",$U14-$B14) -> 4 | X14: Closed | Y14: BN
A15: =IF($B15="","",ROW()-6) -> 9 | B15: 45440 | C15: =IF($B15="","",EOMONTH($B15,-1)+1) -> 45413 | D15: BN | E15: JH01KM-4371 | F15: 9025368773 | G15: HOSKOTE | H15: BOMMANHALLI | I15: DODABALLAPUR | J15: 24FEET SXL | L15: 6300 | M15: =IF(OR($K15="",$L15=""),"",$L15-$K15) | N15: =IF(OR($L15="",$L15=0,$M15=""),"",$M15/$L15) | P15: =IF(OR($K15="",$O15=""),"",$K15-$O15) | Q15: DONE | R15: 9 | S15: RECEIPT | W15: =IF(OR($B15="",$U15=""),"",$U15-$B15) | X15: Closed | Y15: BN | AA15: LOADING
A16: =IF($B16="","",ROW()-6) -> 10 | B16: 45442 | C16: =IF($B16="","",EOMONTH($B16,-1)+1) -> 45413 | D16: BN | E16: JH01KM-4371 | F16: 9025368773 | G16: DODABALLAPUR | H16: N/A | I16: RANCHI ,872415/27 | J16: 24FEET SXL | K16: 48290 | L16: 67410 | M16: =IF(OR($K16="",$L16=""),"",$L16-$K16) -> 19120 | N16: =IF(OR($L16="",$L16=0,$M16=""),"",$M16/$L16) -> 0.28363744 | P16: =IF(OR($K16="",$O16=""),"",$K16-$O16) | Q16: DONE | R16: 9 | S16: RECEIPT | T16: 45445 | U16: 45446 | W16: =IF(OR($B16="",$U16=""),"",$U16-$B16) -> 4 | X16: Closed | Y16: BN
A17: =IF($B17="","",ROW()-6) -> 11 | B17: 45436 | C17: =IF($B17="","",EOMONTH($B17,-1)+1) -> 45413 | D17: BN | E17: JH01KM-8803 | F17: 9589264337 | G17: RANCHI | H17: N/A | I17: HOSKOTE ,140915 | J17: 32FEET SXL | K17: 44220 | L17: 40320 | M17: =IF(OR($K17="",$L17=""),"",$L17-$K17) -> -3900 | N17: =IF(OR($L17="",$L17=0,$M17=""),"",$M17/$L17) -> -0.09672619 | P17: =IF(OR($K17="",$O17=""),"",$K17-$O17) | Q17: DONE | R17: 10 | S17: RECEIPT | T17: 45439 | U17: 45439 | W17: =IF(OR($B17="",$U17=""),"",$U17-$B17) -> 3 | X17: Closed | Y17: BN
A18: =IF($B18="","",ROW()-6) -> 12 | B18: 45439 | C18: =IF($B18="","",EOMONTH($B18,-1)+1) -> 45413 | D18: BN | E18: JH01KM-8803 | F18: 9589264337 | G18: TIRUPUR | H18: N/A | I18: RANCHI,407449 | J18: 32FEET SXL | K18: 51030 | L18: 85680 | M18: =IF(OR($K18="",$L18=""),"",$L18-$K18) -> 34650 | N18: =IF(OR($L18="",$L18=0,$M18=""),"",$M18/$L18) -> 0.40441176 | P18: =IF(OR($K18="",$O18=""),"",$K18-$O18) | Q18: DONE | R18: 11 | S18: RECEIPT | T18: 45443 | U18: 45443 | W18: =IF(OR($B18="",$U18=""),"",$U18-$B18) -> 4 | X18: Closed | Y18: BN
A19: =IF($B19="","",ROW()-6) -> 13 | B19: 45444 | C19: =IF($B19="","",EOMONTH($B19,-1)+1) -> 45444 | D19: 3rd Party | E19: KA02YH-5646 | F19: 9198923795 | G19: RANCHI | H19: N/A | I19: HOSKOTE,264810 | J19: 20FEET | K19: 27290 | L19: 35600 | M19: =IF(OR($K19="",$L19=""),"",$L19-$K19) -> 8310 | N19: =IF(OR($L19="",$L19=0,$M19=""),"",$M19/$L19) -> 0.23342697 | O19: 27290 | P19: =IF(OR($K19="",$O19=""),"",$K19-$O19) -> 0 | Q19: DONE | R19: 12 | S19: RECEIPT | T19: 45447 | U19: 45447 | W19: =IF(OR($B19="",$U19=""),"",$U19-$B19) -> 3 | X19: Closed | Y19: Transporter 02
A20: =IF($B20="","",ROW()-6) -> 14 | B20: 45444 | C20: =IF($B20="","",EOMONTH($B20,-1)+1) -> 45444 | D20: 3rd Party | E20: KA05RX-6944 | F20: 9295512602 | G20: RANCHI | H20: N/A | I20: HASSAN,872860 | J20: 24FEET | K20: 29110 | L20: 38740 | M20: =IF(OR($K20="",$L20=""),"",$L20-$K20) -> 9630 | N20: =IF(OR($L20="",$L20=0,$M20=""),"",$M20/$L20) -> 0.24858028 | O20: 29110 | P20: =IF(OR($K20="",$O20=""),"",$K20-$O20) -> 0 | Q20: DONE | R20: 13 | S20: RECEIPT | T20: 45447 | U20: 45447 | W20: =IF(OR($B20="",$U20=""),"",$U20-$B20) -> 3 | X20: Closed | Y20: Transporter 02
A21: =IF($B21="","",ROW()-6) -> 15 | B21: 45444 | C21: =IF($B21="","",EOMONTH($B21,-1)+1) -> 45444 | D21: BN | E21: JH01KM-8803 | F21: 9589264337 | G21: RANCHI | H21: N/A | I21: HASSAN,913653 | J21: 32FEET SXL | K21: 44220 | L21: 40320 | M21: =IF(OR($K21="",$L21=""),"",$L21-$K21) -> -3900 | N21: =IF(OR($L21="",$L21=0,$M21=""),"",$M21/$L21) -> -0.09672619 | P21: =IF(OR($K21="",$O21=""),"",$K21-$O21) | Q21: DONE | R21: 14 | S21: RECEIPT | T21: 45448 | U21: 45448 | W21: =IF(OR($B21="",$U21=""),"",$U21-$B21) -> 4 | X21: Closed | Y21: BN
A22: =IF($B22="","",ROW()-6) -> 16 | B22: 45446 | C22: =IF($B22="","",EOMONTH($B22,-1)+1) -> 45444 | D22: BN | E22: JH01KM-4371 | F22: 9025368773 | G22: RANCHI | H22: NARSAPUR,970325+HOSKOTE,425534 | I22: BOMMANSANDRA ,890248 | J22: 24 FEET SXL | K22: 45880 | L22: 51340 | M22: =IF(OR($K22="",$L22=""),"",$L22-$K22) -> 5460 | N22: =IF(OR($L22="",$L22=0,$M22=""),"",$M22/$L22) -> 0.10634982 | P22: =IF(OR($K22="",$O22=""),"",$K22-$O22) | Q22: DONE | R22: 15 | S22: RECEIPT | T22: 45449 | U22: 45450 | W22: =IF(OR($B22="",$U22=""),"",$U22-$B22) -> 4 | X22: Closed | Y22: BN
A23: =IF($B23="","",ROW()-6) -> 17 | B23: 45449 | C23: =IF($B23="","",EOMONTH($B23,-1)+1) -> 45444 | D23: BN | E23: JH01KM8803 | F23: 9589264337 | G23: TIRUPUR | H23: N/A | I23: RANCHI,476477 | J23: 32 FEET SXL | K23: 51690 | L23: 90090 | M23: =IF(OR($K23="",$L23=""),"",$L23-$K23) -> 38400 | N23: =IF(OR($L23="",$L23=0,$M23=""),"",$M23/$L23) -> 0.42624043 | P23: =IF(OR($K23="",$O23=""),"",$K23-$O23) | Q23: DONE | R23: 16 | S23: RECEIPT | T23: 45452 | U23: 45453 | W23: =IF(OR($B23="",$U23=""),"",$U23-$B23) -> 4 | X23: Closed | Y23: BN
A24: =IF($B24="","",ROW()-6) -> 18 | B24: 45450 | C24: =IF($B24="","",EOMONTH($B24,-1)+1) -> 45444 | D24: 3rd Party | E24: KA02GM-9724 | F24: 9149905009 | G24: RANCHI | H24: BOMMANSANDRA,933942 | I24: HOSKOTE,387835 | J24: 22FEET | K24: 27640 | L24: 45040 | M24: =IF(OR($K24="",$L24=""),"",$L24-$K24) -> 17400 | N24: =IF(OR($L24="",$L24=0,$M24=""),"",$M24/$L24) -> 0.38632327 | O24: 27640 | P24: =IF(OR($K24="",$O24=""),"",$K24-$O24) -> 0 | Q24: DONE | R24: 17 | S24: RECEIPT | T24: 45454 | U24: 45454 | W24: =IF(OR($B24="",$U24=""),"",$U24-$B24) -> 4 | X24: Closed | Y24: Transporter 02
A25: =IF($B25="","",ROW()-6) -> 19 | B25: 45450 | C25: =IF($B25="","",EOMONTH($B25,-1)+1) -> 45444 | D25: BN | E25: JH01KM-4371 | F25: 9025368773 | G25: ERODE | H25: N/A | I25: RANCHI,187030 | J25: 24FEET | K25: 48290 | L25: 67410 | M25: =IF(OR($K25="",$L25=""),"",$L25-$K25) -> 19120 | N25: =IF(OR($L25="",$L25=0,$M25=""),"",$M25/$L25) -> 0.28363744 | P25: =IF(OR($K25="",$O25=""),"",$K25-$O25) | Q25: DONE | R25: 18 | S25: RECEIPT | T25: 45452 | U25: 45453 | W25: =IF(OR($B25="",$U25=""),"",$U25-$B25) -> 3 | X25: Closed | Y25: BN
A26: =IF($B26="","",ROW()-6) -> 20 | B26: 45455 | C26: =IF($B26="","",EOMONTH($B26,-1)+1) -> 45444 | D26: BN | E26: JH01KM-4371 | F26: 9025368773 | G26: RANCHI | H26: HOSKOTE,900316 | I26: BOMMANSA,863494 | J26: 24FEET | K26: 44930 | L26: 45040 | M26: =IF(OR($K26="",$L26=""),"",$L26-$K26) -> 110 | N26: =IF(OR($L26="",$L26=0,$M26=""),"",$M26/$L26) -> 0.0024422735 | P26: =IF(OR($K26="",$O26=""),"",$K26-$O26) | Q26: DONE | R26: 19 | S26: RECEIPT | T26: 45458 | U26: 45458 | W26: =IF(OR($B26="",$U26=""),"",$U26-$B26) -> 3 | X26: Closed | Y26: BN
A27: =IF($B27="","",ROW()-6) -> 21 | B27: 45456 | C27: =IF($B27="","",EOMONTH($B27,-1)+1) -> 45444 | D27: BN | E27: JH01KM-8803 | F27: 9589264337 | G27: RANCHI | H27: NARSAPUR,763576 | I27: BOMMANSANDRA,516517 | J27: 32FEET SXL | K27: 45170 | L27: 46620 | M27: =IF(OR($K27="",$L27=""),"",$L27-$K27) -> 1450 | N27: =IF(OR($L27="",$L27=0,$M27=""),"",$M27/$L27) -> 0.031102531 | P27: =IF(OR($K27="",$O27=""),"",$K27-$O27) | Q27: DONE | R27: 20 | S27: RECEIPT | T27: 45459 | U27: 45462 | W27: =IF(OR($B27="",$U27=""),"",$U27-$B27) -> 6 | X27: Closed | Y27: BN | Z27: LORRY HALTING - EXTRA CHARGE
A28: =IF($B28="","",ROW()-6) -> 22 | B28: 45457 | C28: =IF($B28="","",EOMONTH($B28,-1)+1) -> 45444 | D28: 3rd Party | E28: WB23J-3143 | F28: 9372267009 | G28: ERODE | H28: N/A | I28: RANCHI,241257 | J28: 32FEET MXL | K28: 75570 | L28: 93240 | M28: =IF(OR($K28="",$L28=""),"",$L28-$K28) -> 17670 | N28: =IF(OR($L28="",$L28=0,$M28=""),"",$M28/$L28) -> 0.18951094 | O28: 75570 | P28: =IF(OR($K28="",$O28=""),"",$K28-$O28) -> 0 | Q28: DONE | R28: 21 | S28: RECEIPT | T28: 45462 | U28: 45462 | W28: =IF(OR($B28="",$U28=""),"",$U28-$B28) -> 5 | X28: Closed | Y28: Transporter 03 | AA28: 19-06-2024 | AB28: 19-06-2024
A29: =IF($B29="","",ROW()-6) -> 23 | B29: 45458 | C29: =IF($B29="","",EOMONTH($B29,-1)+1) -> 45444 | D29: 3rd Party | E29: KA05TT-6944 | F29: 9295512602 | G29: RANCHI | H29: N/A | I29: HASSAN,857821 | J29: 24FEET | K29: 27770 | L29: 38740 | M29: =IF(OR($K29="",$L29=""),"",$L29-$K29) -> 10970 | N29: =IF(OR($L29="",$L29=0,$M29=""),"",$M29/$L29) -> 0.28316985 | O29: 27770 | P29: =IF(OR($K29="",$O29=""),"",$K29-$O29) -> 0 | Q29: DONE | R29: 22 | S29: RECEIPT | T29: 45462 | U29: 45462 | W29: =IF(OR($B29="",$U29=""),"",$U29-$B29) -> 4 | X29: Closed | Y29: Transporter 02 | AA29: 19-06-2024 | AB29: 19-06-2024
A30: =IF($B30="","",ROW()-6) -> 24 | B30: 45459 | C30: =IF($B30="","",EOMONTH($B30,-1)+1) -> 45444 | D30: BN | E30: JH01KM-4371 | F30: 9025368773 | G30: ERODE | H30: N/A | I30: RANCHI,454688 | J30: 24FEET | K30: 48290 | L30: 67410 | M30: =IF(OR($K30="",$L30=""),"",$L30-$K30) -> 19120 | N30: =IF(OR($L30="",$L30=0,$M30=""),"",$M30/$L30) -> 0.28363744 | P30: =IF(OR($K30="",$O30=""),"",$K30-$O30) | Q30: DONE | R30: 23 | S30: RECEIPT | T30: 45461 | U30: 45461 | W30: =IF(OR($B30="",$U30=""),"",$U30-$B30) -> 2 | X30: Closed | Y30: BN | Z30: OVERLOAD - EXTRA CHARGE | AA30: 18-06-2024 | AB30: 18-06-2024
A31: =IF($B31="","",ROW()-6) -> 25 | B31: 45460 | C31: =IF($B31="","",EOMONTH($B31,-1)+1) -> 45444 | D31: 3rd Party | E31: KA53T-7407 | F31: 9684865656 | G31: RANCHI | H31: NARSAPUR,795057 | I31: HASSAN,857821 | J31: 20FEET | K31: 26100 | L31: 41900 | M31: =IF(OR($K31="",$L31=""),"",$L31-$K31) -> 15800 | N31: =IF(OR($L31="",$L31=0,$M31=""),"",$M31/$L31) -> 0.37708831 | O31: 26100 | P31: =IF(OR($K31="",$O31=""),"",$K31-$O31) -> 0 | Q31: DONE | R31: 25 | S31: RECEIPT | T31: 45464 | U31: 45465 | W31: =IF(OR($B31="",$U31=""),"",$U31-$B31) -> 5 | X31: Closed | Y31: Transporter 02 | AA31: 21-06-2024 | AB31: 22-06-2024
A32: =IF($B32="","",ROW()-6) -> 26 | B32: 45462 | C32: =IF($B32="","",EOMONTH($B32,-1)+1) -> 45444 | D32: BN | E32: JH01KM-4371 | F32: 9025368773 | G32: RANCHI | H32: N/A | I32: HASSAN,493930 | J32: 24FEET | K32: 46520 | L32: 55600 | M32: =IF(OR($K32="",$L32=""),"",$L32-$K32) -> 9080 | N32: =IF(OR($L32="",$L32=0,$M32=""),"",$M32/$L32) -> 0.16330935 | P32: =IF(OR($K32="",$O32=""),"",$K32-$O32) | Q32: DONE | R32: 24 | S32: RECEIPT | T32: 45465 | U32: 45465 | W32: =IF(OR($B32="",$U32=""),"",$U32-$B32) -> 3 | X32: Closed | Y32: BN | AA32: 22-06-2024 | AB32: 22-06-2024
A33: =IF($B33="","",ROW()-6) -> 27 | B33: 45463 | C33: =IF($B33="","",EOMONTH($B33,-1)+1) -> 45444 | D33: BN | E33: JH01KM-8803 | F33: 9589264337 | G33: TIRUPUR,484647 | H33: ERODE,743866 | I33: RANCHI | J33: 32FEET SXL | K33: 52820 | L33: 97650 | M33: =IF(OR($K33="",$L33=""),"",$L33-$K33) -> 44830 | N33: =IF(OR($L33="",$L33=0,$M33=""),"",$M33/$L33) -> 0.45908858 | P33: =IF(OR($K33="",$O33=""),"",$K33-$O33) | Q33: DONE | R33: 26 | S33: RECEIPT | T33: 45466 | U33: 45466 | W33: =IF(OR($B33="",$U33=""),"",$U33-$B33) -> 3 | X33: Closed | Y33: BN | Z33: SPEED MODE MATERIAL EXTRA CHARGE | AA33: 23-06-2024 | AB33: 23-06-2024
A34: =IF($B34="","",ROW()-6) -> 28 | B34: 45464 | C34: =IF($B34="","",EOMONTH($B34,-1)+1) -> 45444 | D34: 3rd Party | E34: TN93L-8071 | F34: 9754088991 | G34: RANCHI | H34: NARSAPUR,912069+HOSKOTE,483982 | I34: BOMMANSANDRA,607558 | J34: 32FEET SXL | K34: 33110 | L34: 52920 | M34: =IF(OR($K34="",$L34=""),"",$L34-$K34) -> 19810 | N34: =IF(OR($L34="",$L34=0,$M34=""),"",$M34/$L34) -> 0.37433862 | O34: 33110 | P34: =IF(OR($K34="",$O34=""),"",$K34-$O34) -> 0 | Q34: DONE | R34: 27 | S34: RECEIPT | T34: 45468 | U34: 45469 | W34: =IF(OR($B34="",$U34=""),"",$U34-$B34) -> 5 | X34: Closed | Y34: Transporter 02 | Z34: MISC NOTE | AA34: 25-06-2024 | AB34: 26-06-2024
A35: =IF($B35="","",ROW()-6) -> 29 | B35: 45467 | C35: =IF($B35="","",EOMONTH($B35,-1)+1) -> 45444 | D35: BN | E35: JH01KM-8803 | F35: 9589264337 | G35: RANCHI | H35: HOSKOTE,742750 | I35: HASSAN ,377936 | J35: 32 FEET SXL | K35: 45170 | L35: 46620 | M35: =IF(OR($K35="",$L35=""),"",$L35-$K35) -> 1450 | N35: =IF(OR($L35="",$L35=0,$M35=""),"",$M35/$L35) -> 0.031102531 | P35: =IF(OR($K35="",$O35=""),"",$K35-$O35) | Q35: DONE | R35: 28 | S35: RECEIPT | T35: 45470 | U35: 45470 | W35: =IF(OR($B35="",$U35=""),"",$U35-$B35) -> 3 | X35: Closed | Y35: BN | AA35: 27-06-2024 | AB35: 27-06-2024
A36: =IF($B36="","",ROW()-6) -> 30 | B36: 45468 | C36: =IF($B36="","",EOMONTH($B36,-1)+1) -> 45444 | D36: BN | E36: JH01KM-4371 | F36: 9025368773 | G36: HOSUR | H36: N/A | I36: RANCHI,261832 | J36: 24FEET | K36: 48290 | L36: 67410 | M36: =IF(OR($K36="",$L36=""),"",$L36-$K36) -> 19120 | N36: =IF(OR($L36="",$L36=0,$M36=""),"",$M36/$L36) -> 0.28363744 | P36: =IF(OR($K36="",$O36=""),"",$K36-$O36) | Q36: DONE | R36: 29 | S36: RECEIPT | T36: 45471 | U36: 45471 | W36: =IF(OR($B36="",$U36=""),"",$U36-$B36) -> 3 | X36: Closed | Y36: BN | AA36: 28-06-2024 | AB36: 28-06-2024
A37: =IF($B37="","",ROW()-6) -> 31 | B37: 45469 | C37: =IF($B37="","",EOMONTH($B37,-1)+1) -> 45444 | D37: 3rd Party | E37: TN52TM-1398 | F37: 9941053951 | G37: RANCHI | H37: N/A | I37: HOSKOTE,491423 | J37: 32FEET SXL | K37: 33890 | L37: 40320 | M37: =IF(OR($K37="",$L37=""),"",$L37-$K37) -> 6430 | N37: =IF(OR($L37="",$L37=0,$M37=""),"",$M37/$L37) -> 0.15947421 | O37: 33890 | P37: =IF(OR($K37="",$O37=""),"",$K37-$O37) -> 0 | Q37: DONE | R37: 30 | S37: RECEIPT | T37: 45473 | U37: 45474 | W37: =IF(OR($B37="",$U37=""),"",$U37-$B37) -> 5 | X37: Closed | Y37: Transporter 02 | AA37: 30-06-2024 | AB37: 45298
A38: =IF($B38="","",ROW()-6) -> 32 | B38: 45470 | C38: =IF($B38="","",EOMONTH($B38,-1)+1) -> 45444 | D38: 3rd Party | E38: TN18GS-5854 | F38: 9834816284 | G38: RANCHI | H38: N/A | I38: NARSAPUR,366358 | J38: 32FEET SXL | K38: 34840 | L38: 46620 | M38: =IF(OR($K38="",$L38=""),"",$L38-$K38) -> 11780 | N38: =IF(OR($L38="",$L38=0,$M38=""),"",$M38/$L38) -> 0.25268125 | O38: 34840 | P38: =IF(OR($K38="",$O38=""),"",$K38-$O38) -> 0 | Q38: DONE | R38: 31 | S38: RECEIPT | T38: 45476 | U38: 45476 | W38: =IF(OR($B38="",$U38=""),"",$U38-$B38) -> 6 | X38: Closed | Y38: Transporter 02 | Z38: LORRY HALTING - EXTRA CHARGE | AA38: 45358 | AB38: 45358
A39: =IF($B39="","",ROW()-6) -> 33 | B39: 45474 | C39: =IF($B39="","",EOMONTH($B39,-1)+1) -> 45474 | D39: 3rd Party | E39: GJ27K-9382 | F39: 9660512245 | G39: AHM. | H39: N/A | I39: RANCHI,862761 | J39: 20FEET | K39: 44920 | L39: 56700 | M39: =IF(OR($K39="",$L39=""),"",$L39-$K39) -> 11780 | N39: =IF(OR($L39="",$L39=0,$M39=""),"",$M39/$L39) -> 0.20776014 | O39: 41620 | P39: =IF(OR($K39="",$O39=""),"",$K39-$O39) -> 3300 | Q39: DONE | R39: 37 | S39: PENDING | T39: 45478 | U39: 45478 | W39: =IF(OR($B39="",$U39=""),"",$U39-$B39) -> 4 | X39: Closed | Y39: Transporter 04 | Z39: MATERIAL SHIFTED TO ANOTHER VEHICLE | AA39: 45419 | AB39: 45419
A40: =IF($B40="","",ROW()-6) -> 34 | B40: 45474 | C40: =IF($B40="","",EOMONTH($B40,-1)+1) -> 45474 | D40: BN | E40: JH01KM-4371 | F40: 9025368773 | G40: RANCHI | H40: HOSKOTE,136530 | I40: HASSAN,323165 | J40: 24FEET | K40: 45740 | L40: 50400 | M40: =IF(OR($K40="",$L40=""),"",$L40-$K40) -> 4660 | N40: =IF(OR($L40="",$L40=0,$M40=""),"",$M40/$L40) -> 0.092460317 | P40: =IF(OR($K40="",$O40=""),"",$K40-$O40) | Q40: DONE | R40: 32 | S40: RECEIPT | T40: 45477 | U40: 45478 | W40: =IF(OR($B40="",$U40=""),"",$U40-$B40) -> 4 | X40: Closed | Y40: BN | AA40: 45389 | AB40: 45419
A41: =IF($B41="","",ROW()-6) -> 35 | B41: 45474 | C41: =IF($B41="","",EOMONTH($B41,-1)+1) -> 45474 | D41: BN | E41: JH01KM-8803 | F41: 9025368773 | G41: TIRUPUR,211792/56 | H41: ERODE,377051 | I41: RANCHI | J41: 32FEET | K41: 53580 | L41: 102690 | M41: =IF(OR($K41="",$L41=""),"",$L41-$K41) -> 49110 | N41: =IF(OR($L41="",$L41=0,$M41=""),"",$M41/$L41) -> 0.47823547 | P41: =IF(OR($K41="",$O41=""),"",$K41-$O41) | Q41: DONE | R41: 33 | S41: RECEIPT | T41: 45477 | U41: 45478 | W41: =IF(OR($B41="",$U41=""),"",$U41-$B41) -> 4 | X41: Closed | Y41: BN | AA41: 45389 | AB41: 45419
A42: =IF($B42="","",ROW()-6) -> 36 | B42: 45475 | C42: =IF($B42="","",EOMONTH($B42,-1)+1) -> 45474 | D42: 3rd Party | E42: KA52W-2643 | F42: 9578386887 | G42: RANCHI | H42: HOSKOTE,042648 | I42: BOMMANSANDRA,693938 | J42: 24FEET | K42: 29180 | L42: 48200 | M42: =IF(OR($K42="",$L42=""),"",$L42-$K42) -> 19020 | N42: =IF(OR($L42="",$L42=0,$M42=""),"",$M42/$L42) -> 0.39460581 | O42: 29180 | P42: =IF(OR($K42="",$O42=""),"",$K42-$O42) -> 0 | Q42: DONE | R42: 34 | S42: RECEIPT | T42: 45478 | U42: 45479 | W42: =IF(OR($B42="",$U42=""),"",$U42-$B42) -> 4 | X42: Closed | Y42: Transporter 02 | Z42: LORRY HALTING - EXTRA CHARGE | AA42: 45419 | AB42: 45450
A43: =IF($B43="","",ROW()-6) -> 37 | B43: 45475 | C43: =IF($B43="","",EOMONTH($B43,-1)+1) -> 45474 | D43: 3rd Party | E43: TN12XD-6346 | F43: 9678275995 | G43: RANCHI | H43: N/A | I43: NARSAPUR,362044 | J43: 20FEET | K43: 25150 | L43: 35600 | M43: =IF(OR($K43="",$L43=""),"",$L43-$K43) -> 10450 | N43: =IF(OR($L43="",$L43=0,$M43=""),"",$M43/$L43) -> 0.29353933 | O43: 25150 | P43: =IF(OR($K43="",$O43=""),"",$K43-$O43) -> 0 | Q43: DONE | R43: 35 | S43: RECEIPT | T43: 45482 | U43: 45482 | W43: =IF(OR($B43="",$U43=""),"",$U43-$B43) -> 7 | X43: Closed | Y43: Transporter 02 | AA43: 45542 | AB43: 45542
A44: =IF($B44="","",ROW()-6) -> 38 | B44: 45475 | C44: =IF($B44="","",EOMONTH($B44,-1)+1) -> 45474 | D44: 3rd Party | E44: TN12XD-6346 | F44: 9678275995 | G44: RANCHI | H44: PART LOAD | I44: HOSUR,398331 | J44: 20FEET | K44: 0 | L44: 11500 | M44: =IF(OR($K44="",$L44=""),"",$L44-$K44) -> 11500 | N44: =IF(OR($L44="",$L44=0,$M44=""),"",$M44/$L44) -> 1 | P44: =IF(OR($K44="",$O44=""),"",$K44-$O44) | Q44: DONE | R44: 36 | S44: RECEIPT | T44: 45482 | U44: 45482 | W44: =IF(OR($B44="",$U44=""),"",$U44-$B44) -> 7 | X44: Closed | Y44: Transporter 02 | Z44: WEIGHT-BASED BILLING (PART LOAD) | AA44: 45542 | AB44: 45542
A45: =IF($B45="","",ROW()-6) -> 39 | B45: 45476 | C45: =IF($B45="","",EOMONTH($B45,-1)+1) -> 45474 | D45: 3rd Party | E45: NL01N-2927 | F45: 9513184912 | G45: RANCHI | H45: NARSAPUR,199550 | I45: BOMMANSANDRA, 387363 | J45: 32 FEET SXL | K45: 35310 | L45: 49770 | M45: =IF(OR($K45="",$L45=""),"",$L45-$K45) -> 14460 | N45: =IF(OR($L45="",$L45=0,$M45=""),"",$M45/$L45) -> 0.29053647 | O45: 35310 | P45: =IF(OR($K45="",$O45=""),"",$K45-$O45) -> 0 | Q45: DONE | R45: 38 | S45: RECEIPT | T45: 45482 | U45: 45483 | W45: =IF(OR($B45="",$U45=""),"",$U45-$B45) -> 7 | X45: Closed | Y45: Transporter 05 | Z45: LORRY HALTING - EXTRA CHARGE | AA45: 45542 | AB45: 45572
A46: =IF($B46="","",ROW()-6) -> 40 | B46: 45477 | C46: =IF($B46="","",EOMONTH($B46,-1)+1) -> 45474 | D46: 3rd Party | E46: TN88W-4748 | F46: 9593083336 | G46: RANCHI | H46: NARSAPUR,590354 | I46: HASSAN, 125936 | J46: 32FEET SXL | K46: 34810 | L46: 53550 | M46: =IF(OR($K46="",$L46=""),"",$L46-$K46) -> 18740 | N46: =IF(OR($L46="",$L46=0,$M46=""),"",$M46/$L46) -> 0.34995331 | O46: 34810 | P46: =IF(OR($K46="",$O46=""),"",$K46-$O46) -> 0 | Q46: DONE | R46: 39 | S46: RECEIPT | T46: 45482 | U46: 45483 | W46: =IF(OR($B46="",$U46=""),"",$U46-$B46) -> 6 | X46: Closed | Y46: Transporter 02 | AA46: 45542 | AB46: 45572
A47: =IF($B47="","",ROW()-6) -> 41 | B47: 45478 | C47: =IF($B47="","",EOMONTH($B47,-1)+1) -> 45474 | D47: 3rd Party | E47: JH01DH-4340 | F47: 9137963915 | G47: RANCHI | H47: LOCAL | I47: RANCHI | J47: 10FEET | K47: 1870 | L47: 2840 | M47: =IF(OR($K47="",$L47=""),"",$L47-$K47) -> 970 | N47: =IF(OR($L47="",$L47=0,$M47=""),"",$M47/$L47) -> 0.3415493 | O47: 1870 | P47: =IF(OR($K47="",$O47=""),"",$K47-$O47) -> 0 | Q47: DONE | R47: 40 | S47: RECEIPT | T47: 45478 | U47: 45478 | W47: =IF(OR($B47="",$U47=""),"",$U47-$B47) -> 0 | X47: Closed | Y47: Transporter 06 | Z47: PICK-UP AND DELIVERY CHARGE ADDED | AA47: 45419 | AB47: 45419
A48: =IF($B48="","",ROW()-6) -> 42 | B48: 45478 | C48: =IF($B48="","",EOMONTH($B48,-1)+1) -> 45474 | D48: 3rd Party | E48: KA52K-7153 | F48: 9599281983 | G48: RANCHI | H48: N/A | I48: NARSAPUR,602705 | J48: 20FEET | K48: 25150 | L48: 35600 | M48: =IF(OR($K48="",$L48=""),"",$L48-$K48) -> 10450 | N48: =IF(OR($L48="",$L48=0,$M48=""),"",$M48/$L48) -> 0.29353933 | O48: 25150 | P48: =IF(OR($K48="",$O48=""),"",$K48-$O48) -> 0 | Q48: DONE | R48: 41 | S48: RECEIPT | T48: 45482 | U48: 45482 | W48: =IF(OR($B48="",$U48=""),"",$U48-$B48) -> 4 | X48: Closed | Y48: Transporter 02 | AA48: 45542 | AB48: 45542
A49: =IF($B49="","",ROW()-6) -> 43 | B49: 45479 | C49: =IF($B49="","",EOMONTH($B49,-1)+1) -> 45474 | D49: BN | E49: JH01KM-8803 | F49: 9589264337 | G49: RANCHI | H49: HOSKOTE+BMS,185224,176322 | I49: HASSAN,299082 | J49: 32FEET SXL | K49: 47150 | L49: 59850 | M49: =IF(OR($K49="",$L49=""),"",$L49-$K49) -> 12700 | N49: =IF(OR($L49="",$L49=0,$M49=""),"",$M49/$L49) -> 0.21219716 | P49: =IF(OR($K49="",$O49=""),"",$K49-$O49) | Q49: DONE | R49: 42 | S49: RECEIPT | T49: 45482 | U49: 45483 | W49: =IF(OR($B49="",$U49=""),"",$U49-$B49) -> 4 | X49: Closed | Y49: BN | AA49: 45542 | AB49: 45572
A50: =IF($B50="","",ROW()-6) -> 44 | B50: 45479 | C50: =IF($B50="","",EOMONTH($B50,-1)+1) -> 45474 | D50: 3rd Party | E50: TN18DH-3563 | F50: 9343626927 | G50: RANCHI | H50: NARSAPUR,309027 | I50: HOSKOTE,234717 | J50: 32FEET SXL | K50: 33770 | L50: 46620 | M50: =IF(OR($K50="",$L50=""),"",$L50-$K50) -> 12850 | N50: =IF(OR($L50="",$L50=0,$M50=""),"",$M50/$L50) -> 0.27563278 | O50: 33770 | P50: =IF(OR($K50="",$O50=""),"",$K50-$O50) -> 0 | Q50: DONE | R50: 43 | S50: RECEIPT | T50: 45484 | U50: 45485 | W50: =IF(OR($B50="",$U50=""),"",$U50-$B50) -> 6 | X50: Closed | Y50: Transporter 07 | Z50: LORRY DELAY | AA50: 45603 | AB50: 45633
A51: =IF($B51="","",ROW()-6) -> 45 | B51: 45481 | C51: =IF($B51="","",EOMONTH($B51,-1)+1) -> 45474 | D51: BN | E51: JH01KM-4371 | F51: 9097762415 | G51: ERODE | H51: N/A | I51: RANCHI | J51: 24FEET | K51: 49140 | L51: 73080 | M51: =IF(OR($K51="",$L51=""),"",$L51-$K51) -> 23940 | N51: =IF(OR($L51="",$L51=0,$M51=""),"",$M51/$L51) -> 0.32758621 | P51: =IF(OR($K51="",$O51=""),"",$K51-$O51) | Q51: DONE | R51: 44 | S51: RECEIPT | T51: 45483 | U51: 45484 | W51: =IF(OR($B51="",$U51=""),"",$U51-$B51) -> 3 | X51: Closed | Y51: BN | Z51: SPEED MODE MATERIAL EXTRA CHARGE | AA51: 45572 | AB51: 45603
A52: =IF($B52="","",ROW()-6) -> 46 | B52: 45482 | C52: =IF($B52="","",EOMONTH($B52,-1)+1) -> 45474 | D52: 3rd Party | E52: UP21LJ-1159 | F52: 9457796730 | G52: RANCHI | H52: N/A | I52: HASSAN,568746 | J52: 32FEET SXL | K52: 33860 | L52: 47250 | M52: =IF(OR($K52="",$L52=""),"",$L52-$K52) -> 13390 | N52: =IF(OR($L52="",$L52=0,$M52=""),"",$M52/$L52) -> 0.28338624 | O52: 33860 | P52: =IF(OR($K52="",$O52=""),"",$K52-$O52) -> 0 | Q52: DONE | R52: 45 | S52: RECEIPT | T52: 45485 | U52: 45485 | W52: =IF(OR($B52="",$U52=""),"",$U52-$B52) -> 3 | X52: Closed | Y52: Transporter 02 | AA52: 45633 | AB52: 45633
A53: =IF($B53="","",ROW()-6) -> 47 | B53: 45483 | C53: =IF($B53="","",EOMONTH($B53,-1)+1) -> 45474 | D53: 3rd Party | E53: KA52J-5960 | F53: 9291434058 | G53: RANCHI | H53: NARSAPUR,297445 | I53: HOSUR,469253 | J53: 24FEET | K53: 28710 | L53: 45040 | M53: =IF(OR($K53="",$L53=""),"",$L53-$K53) -> 16330 | N53: =IF(OR($L53="",$L53=0,$M53=""),"",$M53/$L53) -> 0.36256661 | O53: 28710 | P53: =IF(OR($K53="",$O53=""),"",$K53-$O53) -> 0 | Q53: DONE | R53: 46 | S53: RECEIPT | T53: 45488 | U53: 45488 | W53: =IF(OR($B53="",$U53=""),"",$U53-$B53) -> 5 | X53: Closed | Y53: Transporter 02 | AA53: 15-07-2024 | AB53: 15-07-2024
A54: =IF($B54="","",ROW()-6) -> 48 | B54: 45484 | C54: =IF($B54="","",EOMONTH($B54,-1)+1) -> 45474 | D54: BN | E54: JH01KM-4371 | F54: 9097762415 | G54: RANCHI | H54: NARSAPUR+HOSKOTE+BMS,862275,600470,484009 | I54: HASSAN,590477 | J54: 24FEET | K54: 47630 | L54: 63000 | M54: =IF(OR($K54="",$L54=""),"",$L54-$K54) -> 15370 | N54: =IF(OR($L54="",$L54=0,$M54=""),"",$M54/$L54) -> 0.24396825 | P54: =IF(OR($K54="",$O54=""),"",$K54-$O54) | Q54: DONE | R54: 47 | S54: RECEIPT | T54: 45489 | U54: 45489 | W54: =IF(OR($B54="",$U54=""),"",$U54-$B54) -> 5 | X54: Closed | Y54: BN | AA54: 16-07-2024 | AB54: 16-07-2024
A55: =IF($B55="","",ROW()-6) -> 49 | B55: 45486 | C55: =IF($B55="","",EOMONTH($B55,-1)+1) -> 45474 | D55: BN | E55: JH01KM8803 | F55: 9589264337 | G55: TIRUPUR | H55: ERODE,090919 | I55: RANCHI,612989 | J55: 32FEET SXL | K55: 53580 | L55: 102690 | M55: =IF(OR($K55="",$L55=""),"",$L55-$K55) -> 49110 | N55: =IF(OR($L55="",$L55=0,$M55=""),"",$M55/$L55) -> 0.47823547 | P55: =IF(OR($K55="",$O55=""),"",$K55-$O55) | Q55: DONE | R55: 48 | S55: RECEIPT | T55: 45489 | U55: 45489 | W55: =IF(OR($B55="",$U55=""),"",$U55-$B55) -> 3 | X55: Closed | Y55: BN | AA55: 16-07-2024 | AB55: 16-07-2024
A56: =IF($B56="","",ROW()-6) -> 50 | B56: 45486 | C56: =IF($B56="","",EOMONTH($B56,-1)+1) -> 45474 | D56: 3rd Party | E56: UP21SV-4401 | F56: 9057895037 | G56: LUDHIANA | H56: N/A | I56: RANCHI,473378 | J56: 32FEET SXL | K56: 63160 | L56: 81900 | M56: =IF(OR($K56="",$L56=""),"",$L56-$K56) -> 18740 | N56: =IF(OR($L56="",$L56=0,$M56=""),"",$M56/$L56) -> 0.22881563 | O56: 63160 | P56: =IF(OR($K56="",$O56=""),"",$K56-$O56) -> 0 | Q56: DONE | R56: 49 | S56: RECEIPT | T56: 45492 | U56: 45492 | W56: =IF(OR($B56="",$U56=""),"",$U56-$B56) -> 6 | X56: Closed | Y56: Transporter 08 | AA56: 19-07-2024 | AB56: 19-07-2024
A57: =IF($B57="","",ROW()-6) -> 51 | B57: 45486 | C57: =IF($B57="","",EOMONTH($B57,-1)+1) -> 45474 | D57: 3rd Party | E57: TN93L-3191 | F57: 9237773119 | G57: RANCHI | H57: NARSAPUR+BMS,932329,620472 | I57: HOSUR,412908 | J57: 32FEET SXL | K57: 33640 | L57: 52920 | M57: =IF(OR($K57="",$L57=""),"",$L57-$K57) -> 19280 | N57: =IF(OR($L57="",$L57=0,$M57=""),"",$M57/$L57) -> 0.36432351 | O57: 33640 | P57: =IF(OR($K57="",$O57=""),"",$K57-$O57) -> 0 | Q57: DONE | R57: 50 | S57: RECEIPT | T57: 45491 | U57: 45491 | W57: =IF(OR($B57="",$U57=""),"",$U57-$B57) -> 5 | X57: Closed | Y57: Transporter 02 | AA57: 18-07-2024 | AB57: 18-07-2024
A58: =IF($B58="","",ROW()-6) -> 52 | B58: 45489 | C58: =IF($B58="","",EOMONTH($B58,-1)+1) -> 45474 | D58: BN | E58: JH01KM-8803 | F58: 9589264337 | G58: RANCHI | H58: NARSAPUR,002622+BMS,068162 | I58: HOSKOTE,102073 | J58: 32FEET SXL | K58: 46960 | L58: 58590 | M58: =IF(OR($K58="",$L58=""),"",$L58-$K58) -> 11630 | N58: =IF(OR($L58="",$L58=0,$M58=""),"",$M58/$L58) -> 0.19849804 | P58: =IF(OR($K58="",$O58=""),"",$K58-$O58) | Q58: DONE | R58: 51 | S58: RECEIPT | T58: 45493 | U58: 45493 | W58: =IF(OR($B58="",$U58=""),"",$U58-$B58) -> 4 | X58: Closed | Y58: BN | Z58: SPEED MODE MATERIAL EXTRA CHARGE | AA58: 20-07-2024 | AB58: 20-07-2024
A59: =IF($B59="","",ROW()-6) -> 53 | B59: 45489 | C59: =IF($B59="","",EOMONTH($B59,-1)+1) -> 45474 | D59: 3rd Party | E59: NL01YH-1190 | F59: 9124137850 | G59: RANCHI | H59: N/A | I59: HASSAN,117872 | J59: 32FEET SXL | K59: 35740 | L59: 47250 | M59: =IF(OR($K59="",$L59=""),"",$L59-$K59) -> 11510 | N59: =IF(OR($L59="",$L59=0,$M59=""),"",$M59/$L59) -> 0.24359788 | O59: 35740 | P59: =IF(OR($K59="",$O59=""),"",$K59-$O59) -> 0 | Q59: DONE | R59: 52 | S59: RECEIPT | T59: 45493 | U59: 45493 | W59: =IF(OR($B59="",$U59=""),"",$U59-$B59) -> 4 | X59: Closed | Y59: Transporter 05 | AA59: 20-07-2024 | AB59: 20-07-2024
A60: =IF($B60="","",ROW()-6) -> 54 | B60: 45492 | C60: =IF($B60="","",EOMONTH($B60,-1)+1) -> 45474 | D60: BN | E60: JH01KM-4371 | F60: 9097762415 | G60: ERODE | H60: N/A | I60: RANCHI,448558 | J60: 24FEET | K60: 48290 | L60: 67410 | M60: =IF(OR($K60="",$L60=""),"",$L60-$K60) -> 19120 | N60: =IF(OR($L60="",$L60=0,$M60=""),"",$M60/$L60) -> 0.28363744 | P60: =IF(OR($K60="",$O60=""),"",$K60-$O60) | Q60: DONE | R60: 53 | S60: RECEIPT | T60: 45494 | U60: 45495 | W60: =IF(OR($B60="",$U60=""),"",$U60-$B60) -> 3 | X60: Closed | Y60: BN | AA60: 21-07-2024 | AB60: 22-07-2024
A61: =IF($B61="","",ROW()-6) -> 55 | B61: 45492 | C61: =IF($B61="","",EOMONTH($B61,-1)+1) -> 45474 | D61: 3rd Party | E61: TN52NV-3691 | F61: 9045944352 | G61: RANCHI | H61: NARSAPUR,220963 | I61: HOSKOTE,617581 | J61: 32FEET SXL | K61: 33230 | L61: 46620 | M61: =IF(OR($K61="",$L61=""),"",$L61-$K61) -> 13390 | N61: =IF(OR($L61="",$L61=0,$M61=""),"",$M61/$L61) -> 0.28721579 | O61: 33230 | P61: =IF(OR($K61="",$O61=""),"",$K61-$O61) -> 0 | Q61: DONE | R61: 54 | S61: RECEIPT | T61: 45498 | U61: 45498 | W61: =IF(OR($B61="",$U61=""),"",$U61-$B61) -> 6 | X61: Closed | Y61: Transporter 02 | Z61: LORRY BREAK DOWN | AA61: 25-07-2024 | AB61: 25-07-2024
A62: =IF($B62="","",ROW()-6) -> 56 | B62: 45494 | C62: =IF($B62="","",EOMONTH($B62,-1)+1) -> 45474 | D62: 3rd Party | E62: TN18DH-3563 | F62: 9343626927 | G62: RANCHI | H62: N/A | I62: HASSAN,241354 | J62: 32FEET SXL | K62: 34930 | L62: 47250 | M62: =IF(OR($K62="",$L62=""),"",$L62-$K62) -> 12320 | N62: =IF(OR($L62="",$L62=0,$M62=""),"",$M62/$L62) -> 0.26074074 | O62: 34930 | P62: =IF(OR($K62="",$O62=""),"",$K62-$O62) -> 0 | Q62: DONE | R62: 55 | S62: RECEIPT | T62: 45498 | U62: 45498 | W62: =IF(OR($B62="",$U62=""),"",$U62-$B62) -> 4 | X62: Closed | Y62: Transporter 07 | AA62: 25-07-2024 | AB62: 25-07-2024
A63: =IF($B63="","",ROW()-6) -> 57 | B63: 45495 | C63: =IF($B63="","",EOMONTH($B63,-1)+1) -> 45474 | D63: BN | E63: JH01KM-4371 | F63: 9097762415 | G63: RANCHI | H63: N/A | I63: HOSKOTE,471302 | J63: 24FEET | K63: 44930 | L63: 45040 | M63: =IF(OR($K63="",$L63=""),"",$L63-$K63) -> 110 | N63: =IF(OR($L63="",$L63=0,$M63=""),"",$M63/$L63) -> 0.0024422735 | P63: =IF(OR($K63="",$O63=""),"",$K63-$O63) | Q63: DONE | R63: 56 | S63: RECEIPT | T63: 45498 | U63: 45498 | W63: =IF(OR($B63="",$U63=""),"",$U63-$B63) -> 3 | X63: Closed | Y63: BN | Z63: SPEED MODE MATERIAL EXTRA CHARGE | AA63: 25-07-2024 | AB63: 25-07-2024
A64: =IF($B64="","",ROW()-6) -> 58 | B64: 45496 | C64: =IF($B64="","",EOMONTH($B64,-1)+1) -> 45474 | D64: 3rd Party | E64: NL01BJ-0985 | F64: 9062194812 | G64: RANCHI | H64: HOSKOTE,659144 | I64: HOSUR,535479 | J64: 32FEET SXL | K64: 31090 | L64: 46620 | M64: =IF(OR($K64="",$L64=""),"",$L64-$K64) -> 15530 | N64: =IF(OR($L64="",$L64=0,$M64=""),"",$M64/$L64) -> 0.33311883 | O64: 31090 | P64: =IF(OR($K64="",$O64=""),"",$K64-$O64) -> 0 | Q64: DONE | R64: 57 | S64: RECEIPT | T64: 45499 | U64: 45500 | W64: =IF(OR($B64="",$U64=""),"",$U64-$B64) -> 4 | X64: Closed | Y64: Transporter 02 | AA64: 26-07-2024 | AB64: 27-07-2024
A65: =IF($B65="","",ROW()-6) -> 59 | B65: 45496 | C65: =IF($B65="","",EOMONTH($B65,-1)+1) -> 45474 | D65: BN | E65: JH01KM-8803 | F65: 9589264337 | G65: TIRUPUR,700296 | H65: ERODE,39067 | I65: RANCHI | J65: 32FEET SXL | K65: 53580 | L65: 102690 | M65: =IF(OR($K65="",$L65=""),"",$L65-$K65) -> 49110 | N65: =IF(OR($L65="",$L65=0,$M65=""),"",$M65/$L65) -> 0.47823547 | P65: =IF(OR($K65="",$O65=""),"",$K65-$O65) | Q65: DONE | R65: 58 | S65: RECEIPT | T65: 45500 | U65: 45500 | W65: =IF(OR($B65="",$U65=""),"",$U65-$B65) -> 4 | X65: Closed | Y65: BN | AA65: 27-07-2024 | AB65: 27-07-2024
A66: =IF($B66="","",ROW()-6) -> 60 | B66: 45497 | C66: =IF($B66="","",EOMONTH($B66,-1)+1) -> 45474 | D66: 3rd Party | E66: KA52W-2384 | F66: 9564370374 | G66: RANCHI | H66: NARSAPUR,701529 | I66: HOSKOTE,550035 | J66: 24FEET | K66: 28710 | L66: 45040 | M66: =IF(OR($K66="",$L66=""),"",$L66-$K66) -> 16330 | N66: =IF(OR($L66="",$L66=0,$M66=""),"",$M66/$L66) -> 0.36256661 | O66: 28710 | P66: =IF(OR($K66="",$O66=""),"",$K66-$O66) -> 0 | Q66: DONE | R66: 59 | S66: RECEIPT | T66: 45501 | U66: 45502 | W66: =IF(OR($B66="",$U66=""),"",$U66-$B66) -> 5 | X66: Closed | Y66: Transporter 02 | AA66: 28-07-2024 | AB66: 29-07-2024
A67: =IF($B67="","",ROW()-6) -> 61 | B67: 45500 | C67: =IF($B67="","",EOMONTH($B67,-1)+1) -> 45474 | D67: 3rd Party | E67: NL01TM-4272 | F67: 9124747909 | G67: RANCHI | H67: NARSAPUR,118909 | I67: HASSAN,216580 | J67: 32FEET SXL | K67: 37220 | L67: 53550 | M67: =IF(OR($K67="",$L67=""),"",$L67-$K67) -> 16330 | N67: =IF(OR($L67="",$L67=0,$M67=""),"",$M67/$L67) -> 0.30494865 | O67: 37220 | P67: =IF(OR($K67="",$O67=""),"",$K67-$O67) -> 0 | Q67: DONE | R67: 60 | S67: RECEIPT | T67: 45503 | U67: 45504 | W67: =IF(OR($B67="",$U67=""),"",$U67-$B67) -> 4 | X67: Closed | Y67: Transporter 05 | AA67: 30-07-2024 | AB67: 31-07-2024
A68: =IF($B68="","",ROW()-6) -> 62 | B68: 45501 | C68: =IF($B68="","",EOMONTH($B68,-1)+1) -> 45474 | D68: 3rd Party | E68: JH01KM-8803 | F68: 9589264337 | G68: RANCHI | H68: NARSAPUR,362297+HOSKOTE,334147+HOSUR,693307 | I68: BMS,778726 | J68: 32FEET SXL | K68: 47910 | L68: 64890 | M68: =IF(OR($K68="",$L68=""),"",$L68-$K68) -> 16980 | N68: =IF(OR($L68="",$L68=0,$M68=""),"",$M68/$L68) -> 0.2616736 | P68: =IF(OR($K68="",$O68=""),"",$K68-$O68) | Q68: DONE | R68: 61 | S68: RECEIPT | T68: 45504 | U68: 45505 | W68: =IF(OR($B68="",$U68=""),"",$U68-$B68) -> 4 | X68: Closed | Y68: BN | Z68: SPEED MODE MATERIAL EXTRA CHARGE | AA68: 31-07-2024 | AB68: 45299
A69: =IF($B69="","",ROW()-6) -> 63 | B69: 45502 | C69: =IF($B69="","",EOMONTH($B69,-1)+1) -> 45474 | D69: 3rd Party | E69: JH01KM-4371 | F69: 9097762415 | G69: ERODE | H69: N/A | I69: RANCHI,858226 | J69: 24FEET | K69: 48290 | L69: 67410 | M69: =IF(OR($K69="",$L69=""),"",$L69-$K69) -> 19120 | N69: =IF(OR($L69="",$L69=0,$M69=""),"",$M69/$L69) -> 0.28363744 | P69: =IF(OR($K69="",$O69=""),"",$K69-$O69) | Q69: DONE | R69: 62 | S69: RECEIPT | T69: 45506 | U69: 45506 | W69: =IF(OR($B69="",$U69=""),"",$U69-$B69) -> 4 | X69: Closed | Y69: BN | AA69: 45330 | AB69: 45330
A70: =IF($B70="","",ROW()-6) -> 64 | B70: 45503 | C70: =IF($B70="","",EOMONTH($B70,-1)+1) -> 45474 | D70: 3rd Party | E70: TN05WJ-5569 | F70: 9021782276 | G70: RANCHI | H70: HOSKOTE,150285 | I70: HASSAN,436347 | J70: 20FEET | K70: 29110 | L70: 44100 | M70: =IF(OR($K70="",$L70=""),"",$L70-$K70) -> 14990 | N70: =IF(OR($L70="",$L70=0,$M70=""),"",$M70/$L70) -> 0.3399093 | O70: 29110 | P70: =IF(OR($K70="",$O70=""),"",$K70-$O70) -> 0 | Q70: DONE | R70: 63 | S70: RECEIPT | T70: 45512 | U70: 45512 | W70: =IF(OR($B70="",$U70=""),"",$U70-$B70) -> 9 | X70: Closed | Y70: Transporter 02 | AA70: 45512 | AB70: 45512
A71: =IF($B71="","",ROW()-6) -> 65 | B71: 45504 | C71: =IF($B71="","",EOMONTH($B71,-1)+1) -> 45474 | D71: 3rd Party | E71: KA52K-5945 | F71: 9926313971 | G71: RANCHI | H71: HOSKOTE,328759 | I71: HASSAN,562566 | J71: 22FEET | K71: 30180 | L71: 44100 | M71: =IF(OR($K71="",$L71=""),"",$L71-$K71) -> 13920 | N71: =IF(OR($L71="",$L71=0,$M71=""),"",$M71/$L71) -> 0.31564626 | O71: 30180 | P71: =IF(OR($K71="",$O71=""),"",$K71-$O71) -> 0 | Q71: DONE | R71: 64 | S71: RECEIPT | T71: 45509 | U71: 45510 | W71: =IF(OR($B71="",$U71=""),"",$U71-$B71) -> 6 | X71: Closed | Y71: Transporter 02 | AA71: 45420 | AB71: 45451
A72: =IF($B72="","",ROW()-6) -> 66 | B72: 45505 | C72: =IF($B72="","",EOMONTH($B72,-1)+1) -> 45505 | D72: 3rd Party | E72: WB17-0431 | F72: 9286629206 | G72: HOSUR | H72: N/A | I72: RANCHI,128779 | J72: 32FEET MXL | K72: 82150 | L72: 112140 | M72: =IF(OR($K72="",$L72=""),"",$L72-$K72) -> 29990 | N72: =IF(OR($L72="",$L72=0,$M72=""),"",$M72/$L72) -> 0.26743357 | O72: 82150 | P72: =IF(OR($K72="",$O72=""),"",$K72-$O72) -> 0 | Q72: DONE | R72: 65 | S72: RECEIPT | T72: 45509 | U72: 45509 | W72: =IF(OR($B72="",$U72=""),"",$U72-$B72) -> 4 | X72: Closed | Y72: Transporter 09 | Z72: OVERLOAD - EXTRA CHARGE | AA72: 45420 | AB72: 45420
A73: =IF($B73="","",ROW()-6) -> 67 | B73: 45506 | C73: =IF($B73="","",EOMONTH($B73,-1)+1) -> 45505 | D73: BN | E73: JH01KM-8803 | F73: 9589264337 | G73: TIRUPUR | H73: ERODE,156406 | I73: RANCHI,505803 | J73: 32FEET SXL | K73: 53580 | L73: 102690 | M73: =IF(OR($K73="",$L73=""),"",$L73-$K73) -> 49110 | N73: =IF(OR($L73="",$L73=0,$M73=""),"",$M73/$L73) -> 0.47823547 | P73: =IF(OR($K73="",$O73=""),"",$K73-$O73) | Q73: DONE | R73: 66 | S73: RECEIPT | T73: 45509 | U73: 45510 | W73: =IF(OR($B73="",$U73=""),"",$U73-$B73) -> 4 | X73: Closed | Y73: BN | AA73: 45420 | AB73: 45451
A74: =IF($B74="","",ROW()-6) -> 68 | B74: 45507 | C74: =IF($B74="","",EOMONTH($B74,-1)+1) -> 45505 | D74: 3rd Party | E74: PB10UW-4147 | F74: 9976081007 | G74: LUDHIANA | H74: N/A | I74: RANCHI,093231 | J74: 32FEET SXL | K74: 64230 | L74: 81900 | M74: =IF(OR($K74="",$L74=""),"",$L74-$K74) -> 17670 | N74: =IF(OR($L74="",$L74=0,$M74=""),"",$M74/$L74) -> 0.21575092 | O74: 64230 | P74: =IF(OR($K74="",$O74=""),"",$K74-$O74) -> 0 | Q74: DONE | R74: 67 | S74: RECEIPT | T74: 45513 | U74: 45513 | W74: =IF(OR($B74="",$U74=""),"",$U74-$B74) -> 6 | X74: Closed | Y74: Transporter 10 | AA74: 45543 | AB74: 45543
A75: =IF($B75="","",ROW()-6) -> 69 | B75: 45508 | C75: =IF($B75="","",EOMONTH($B75,-1)+1) -> 45505 | D75: BN | E75: JH01KM-4371 | F75: 9515412075 | G75: RANCHI | H75: HOSUR,044633+BMS,889749+WHITEFIELD,361169 | I75: HASSAN,149999 | J75: 24FEET SXL | K75: 47630 | L75: 63000 | M75: =IF(OR($K75="",$L75=""),"",$L75-$K75) -> 15370 | N75: =IF(OR($L75="",$L75=0,$M75=""),"",$M75/$L75) -> 0.24396825 | P75: =IF(OR($K75="",$O75=""),"",$K75-$O75) | Q75: DONE | R75: 68 | S75: RECEIPT | T75: 45512 | U75: 45512 | W75: =IF(OR($B75="",$U75=""),"",$U75-$B75) -> 4 | X75: Closed | Y75: BN | AA75: 45512 | AB75: 45512
A76: =IF($B76="","",ROW()-6) -> 70 | B76: 45510 | C76: =IF($B76="","",EOMONTH($B76,-1)+1) -> 45505 | D76: BN | E76: JH01KM-8803 | F76: 9589264337 | G76: RANCHI | H76: NARSAPUR,090549+HOSKOTE,595919+HOSUR,927 | I76: HASSAN,596476 | J76: 32FEETSXL | K76: 48100 | L76: 66150 | M76: =IF(OR($K76="",$L76=""),"",$L76-$K76) -> 18050 | N76: =IF(OR($L76="",$L76=0,$M76=""),"",$M76/$L76) -> 0.2728647 | P76: =IF(OR($K76="",$O76=""),"",$K76-$O76) | Q76: DONE | R76: 69 | S76: RECEIPT | T76: 45515 | U76: 45516 | W76: =IF(OR($B76="",$U76=""),"",$U76-$B76) -> 6 | X76: Closed | Y76: BN | AA76: 45604 | AB76: 45634
A77: =IF($B77="","",ROW()-6) -> 71 | B77: 45510 | C77: =IF($B77="","",EOMONTH($B77,-1)+1) -> 45505 | D77: 3rd Party | E77: TN25MM-5315 | F77: 9663777426 | G77: RANCHI | H77: HOSKOTE,613421 | I77: HOSUR,903559(AMOUNT 76215) | J77: 22FEET | K77: 29590 | L77: 54500 | M77: =IF(OR($K77="",$L77=""),"",$L77-$K77) -> 24910 | N77: =IF(OR($L77="",$L77=0,$M77=""),"",$M77/$L77) -> 0.45706422 | O77: 29590 | P77: =IF(OR($K77="",$O77=""),"",$K77-$O77) -> 0 | Q77: DONE | R77: 82 | S77: PENDING | T77: 45515 | U77: 45516 | W77: =IF(OR($B77="",$U77=""),"",$U77-$B77) -> 6 | X77: Closed | Y77: Transporter 02 | AA77: 45604 | AB77: 45634
A78: =IF($B78="","",ROW()-6) -> 72 | B78: 45513 | C78: =IF($B78="","",EOMONTH($B78,-1)+1) -> 45505 | D78: 3rd Party | E78: HR38K-4865 | F78: 9946150873 | G78: ERODE | H78: N/A | I78: RANCHI | J78: 32FEET SXL | K78: 69080 | L78: 96390 | M78: =IF(OR($K78="",$L78=""),"",$L78-$K78) -> 27310 | N78: =IF(OR($L78="",$L78=0,$M78=""),"",$M78/$L78) -> 0.28332815 | O78: 69080 | P78: =IF(OR($K78="",$O78=""),"",$K78-$O78) -> 0 | Q78: DONE | R78: 83 | S78: PENDING | T78: 45517 | U78: 45517 | W78: =IF(OR($B78="",$U78=""),"",$U78-$B78) -> 4 | X78: Closed | Y78: Transporter 11 | AA78: 13-08-2024 | AB78: 13-08-2024
A79: =IF($B79="","",ROW()-6) -> 73 | B79: 45513 | C79: =IF($B79="","",EOMONTH($B79,-1)+1) -> 45505 | D79: 3rd Party | E79: KA51DJ-7560 | F79: 9493729110 | G79: RANCHI | H79: BMS,415100+HSOKOTE,050034 | I79: HASSAN,969311 | J79: 22FEET | K79: 30590 | L79: 50400 | M79: =IF(OR($K79="",$L79=""),"",$L79-$K79) -> 19810 | N79: =IF(OR($L79="",$L79=0,$M79=""),"",$M79/$L79) -> 0.39305556 | O79: 30590 | P79: =IF(OR($K79="",$O79=""),"",$K79-$O79) -> 0 | Q79: DONE | R79: 84 | S79: PENDING | T79: 45518 | U79: 45518 | W79: =IF(OR($B79="",$U79=""),"",$U79-$B79) -> 5 | X79: Closed | Y79: Transporter 02 | AA79: 14-08-2024 | AB79: 14-08-2024
A80: =IF($B80="","",ROW()-6) -> 74 | B80: 45514 | C80: =IF($B80="","",EOMONTH($B80,-1)+1) -> 45505 | D80: 3rd Party | E80: TN02ZE-2186 | F80: 9065465756 | G80: RANCHI | H80: NARSAPUR,592+HOSKOTE,189304 | I80: BMS,864438 | J80: 32FEET SXL | K80: 32570 | L80: 52920 | M80: =IF(OR($K80="",$L80=""),"",$L80-$K80) -> 20350 | N80: =IF(OR($L80="",$L80=0,$M80=""),"",$M80/$L80) -> 0.38454271 | O80: 32570 | P80: =IF(OR($K80="",$O80=""),"",$K80-$O80) -> 0 | Q80: DONE | R80: 85 | S80: PENDING | T80: 45520 | U80: 45520 | W80: =IF(OR($B80="",$U80=""),"",$U80-$B80) -> 6 | X80: Closed | Y80: Transporter 12 | AA80: 16-08-2024 | AB80: 16-08-2024
A81: =IF($B81="","",ROW()-6) -> 75 | B81: 45515 | C81: =IF($B81="","",EOMONTH($B81,-1)+1) -> 45505 | D81: 3rd Party | E81: TN01FG-7374 | F81: 9892288874 | G81: RANCHI | H81: HOSKOTE,987663 | I81: BMS,789024 | J81: 32FEET SXL | K81: 31630 | L81: 46620 | M81: =IF(OR($K81="",$L81=""),"",$L81-$K81) -> 14990 | N81: =IF(OR($L81="",$L81=0,$M81=""),"",$M81/$L81) -> 0.32153582 | O81: 31630 | P81: =IF(OR($K81="",$O81=""),"",$K81-$O81) -> 0 | Q81: DONE | R81: 86 | S81: PENDING | T81: 45520 | U81: 45520 | W81: =IF(OR($B81="",$U81=""),"",$U81-$B81) -> 5 | X81: Closed | Y81: Transporter 12 | AA81: 16-08-2024 | AB81: 16-08-2024
A82: =IF($B82="","",ROW()-6) -> 76 | B82: 45515 | C82: =IF($B82="","",EOMONTH($B82,-1)+1) -> 45505 | D82: BN | E82: JH01KM-4371 | F82: 9515412075 | G82: ERODE | H82: N/A | I82: RANCHI,068347 | J82: 24FEET | K82: 49140 | L82: 73080 | M82: =IF(OR($K82="",$L82=""),"",$L82-$K82) -> 23940 | N82: =IF(OR($L82="",$L82=0,$M82=""),"",$M82/$L82) -> 0.32758621 | P82: =IF(OR($K82="",$O82=""),"",$K82-$O82) | Q82: DONE | R82: 87 | S82: PENDING | T82: 45520 | U82: 45520 | W82: =IF(OR($B82="",$U82=""),"",$U82-$B82) -> 5 | X82: Closed | Y82: BN | Z82: SPEED MODE MATERIAL EXTRA CHARGE | AA82: 16-08-2024 | AB82: 16-08-2024
A83: =IF($B83="","",ROW()-6) -> 77 | B83: 45517 | C83: =IF($B83="","",EOMONTH($B83,-1)+1) -> 45505 | D83: 3rd Party | E83: KA52K-1206 | F83: 9139770277 | G83: RANCHI | H83: HOSKOTE,781390 | I83: HASSAN,975201 | J83: 20FEET | K83: 29520 | L83: 50400 | M83: =IF(OR($K83="",$L83=""),"",$L83-$K83) -> 20880 | N83: =IF(OR($L83="",$L83=0,$M83=""),"",$M83/$L83) -> 0.41428571 | O83: 29520 | P83: =IF(OR($K83="",$O83=""),"",$K83-$O83) -> 0 | Q83: DONE | R83: 88 | S83: PENDING | T83: 45520 | U83: 45520 | W83: =IF(OR($B83="",$U83=""),"",$U83-$B83) -> 3 | X83: Closed | Y83: Transporter 02 | AA83: 16-08-2024 | AB83: 16-08-2024
A84: =IF($B84="","",ROW()-6) -> 78 | B84: 45518 | C84: =IF($B84="","",EOMONTH($B84,-1)+1) -> 45505 | D84: BN | E84: JH01KM-4371 | F84: 9515412075 | G84: RANCHI | H84: BMS,846401 | I84: HASSAN,928118 | J84: 24FEET | K84: 46590 | L84: 56070 | M84: =IF(OR($K84="",$L84=""),"",$L84-$K84) -> 9480 | N84: =IF(OR($L84="",$L84=0,$M84=""),"",$M84/$L84) -> 0.16907437 | O84: 46590 | P84: =IF(OR($K84="",$O84=""),"",$K84-$O84) -> 0 | Q84: DONE | R84: 89 | S84: PENDING | T84: 45520 | U84: 45520 | W84: =IF(OR($B84="",$U84=""),"",$U84-$B84) -> 2 | X84: Closed | Y84: BN | Z84: SPEED MODE MATERIAL EXTRA CHARGE | AA84: 16-08-2024 | AB84: 16-08-2024
A85: =IF($B85="","",ROW()-6) -> 79 | B85: 45518 | C85: =IF($B85="","",EOMONTH($B85,-1)+1) -> 45505 | D85: 3rd Party | E85: NL01JS-2253 | F85: 9577978275 | G85: RANCHI | H85: NARSAPUR,542310 | I85: HOSKOTE,530353 | J85: 32FEET SXL | K85: 31630 | L85: 46620 | M85: =IF(OR($K85="",$L85=""),"",$L85-$K85) -> 14990 | N85: =IF(OR($L85="",$L85=0,$M85=""),"",$M85/$L85) -> 0.32153582 | O85: 31630 | P85: =IF(OR($K85="",$O85=""),"",$K85-$O85) -> 0 | Q85: DONE | R85: 90 | S85: PENDING | T85: 45523 | U85: 45523 | W85: =IF(OR($B85="",$U85=""),"",$U85-$B85) -> 5 | X85: Closed | Y85: Transporter 02 | AA85: 19-08-2024 | AB85: 19-08-2024
A86: =IF($B86="","",ROW()-6) -> 80 | B86: 45518 | C86: =IF($B86="","",EOMONTH($B86,-1)+1) -> 45505 | D86: 3rd Party | E86: KA51YH-4062 | F86: 9573610475 | G86: RANCHI | H86: N/A | I86: HASSAN,421295 | J86: 32FEET SXL | K86: 36540 | L86: 47250 | M86: =IF(OR($K86="",$L86=""),"",$L86-$K86) -> 10710 | N86: =IF(OR($L86="",$L86=0,$M86=""),"",$M86/$L86) -> 0.22666667 | O86: 36540 | P86: =IF(OR($K86="",$O86=""),"",$K86-$O86) -> 0 | Q86: DONE | R86: 91 | S86: PENDING | T86: 45522 | U86: 45522 | W86: =IF(OR($B86="",$U86=""),"",$U86-$B86) -> 4 | X86: Closed | Y86: Transporter 02 | AA86: 18-08-2024 | AB86: 18-08-2024
A87: =IF($B87="","",ROW()-6) -> 81 | B87: 45518 | C87: =IF($B87="","",EOMONTH($B87,-1)+1) -> 45505 | D87: 3rd Party | E87: BY AIR | G87: RANCHI | H87: N/A | I87: BMS,334059 | J87: FLIGHT | K87: 209420 | L87: 264250 | M87: =IF(OR($K87="",$L87=""),"",$L87-$K87) -> 54830 | N87: =IF(OR($L87="",$L87=0,$M87=""),"",$M87/$L87) -> 0.2074929 | O87: 209420 | P87: =IF(OR($K87="",$O87=""),"",$K87-$O87) -> 0 | Q87: PENDING | S87: PENDING | T87: 45520 | U87: 45520 | W87: =IF(OR($B87="",$U87=""),"",$U87-$B87) -> 2 | X87: Closed | Y87: BY AIR | AA87: 16-08-2024 | AB87: 16-08-2024
A88: =IF($B88="","",ROW()-6) -> 82 | B88: 45519 | C88: =IF($B88="","",EOMONTH($B88,-1)+1) -> 45505 | D88: BN | E88: JH01KM-8803 | F88: 9589264337 | G88: ERODE | H88: N/A | I88: RANCHI,506848 | J88: 32FEET SXL | K88: 52630 | L88: 96390 | M88: =IF(OR($K88="",$L88=""),"",$L88-$K88) -> 43760 | N88: =IF(OR($L88="",$L88=0,$M88=""),"",$M88/$L88) -> 0.453989 | P88: =IF(OR($K88="",$O88=""),"",$K88-$O88) | Q88: DONE | R88: 92 | S88: PENDING | T88: 45522 | U88: 45522 | W88: =IF(OR($B88="",$U88=""),"",$U88-$B88) -> 3 | X88: Closed | Y88: BN | AA88: 18-08-2024 | AB88: 18-08-2024
A89: =IF($B89="","",ROW()-6) -> 83 | B89: 45520 | C89: =IF($B89="","",EOMONTH($B89,-1)+1) -> 45505 | D89: 3rd Party | E89: KL59NV-3787 | F89: 9316665035 | G89: RANCHI | H89: N/A | I89: HASSAN,820548 | J89: 25FEET | K89: 30710 | L89: 44100 | M89: =IF(OR($K89="",$L89=""),"",$L89-$K89) -> 13390 | N89: =IF(OR($L89="",$L89=0,$M89=""),"",$M89/$L89) -> 0.30362812 | O89: 30710 | P89: =IF(OR($K89="",$O89=""),"",$K89-$O89) -> 0 | Q89: DONE | R89: 93 | S89: PENDING | T89: 45524 | U89: 45524 | W89: =IF(OR($B89="",$U89=""),"",$U89-$B89) -> 4 | X89: Closed | Y89: Transporter 02 | AA89: 20-08-2024 | AB89: 20-08-2024
A90: =IF($B90="","",ROW()-6) -> 84 | B90: 45520 | C90: =IF($B90="","",EOMONTH($B90,-1)+1) -> 45505 | D90: 3rd Party | E90: KA13T-7124 | F90: 9742039597 | G90: RANCHI | H90: HOSKOTE,090684+HOSUR,678655 | I90: HASSAN,729295 | J90: 24FEET | K90: 33140 | L90: 56700 | M90: =IF(OR($K90="",$L90=""),"",$L90-$K90) -> 23560 | N90: =IF(OR($L90="",$L90=0,$M90=""),"",$M90/$L90) -> 0.41552028 | O90: 33140 | P90: =IF(OR($K90="",$O90=""),"",$K90-$O90) -> 0 | Q90: DONE | R90: 94 | S90: PENDING | T90: 45525 | U90: 45525 | W90: =IF(OR($B90="",$U90=""),"",$U90-$B90) -> 5 | X90: Closed | Y90: Transporter 02 | AA90: 21-08-2024 | AB90: 21-08-2024
A91: =IF($B91="","",ROW()-6) -> 85 | B91: 45524 | C91: =IF($B91="","",EOMONTH($B91,-1)+1) -> 45505 | D91: BN | E91: JH01KM-4371 | F91: 9515412075 | G91: RANCHI | H91: N/A | I91: HASSAN | J91: 24FEET | K91: 51880 | L91: 91350 | M91: =IF(OR($K91="",$L91=""),"",$L91-$K91) -> 39470 | N91: =IF(OR($L91="",$L91=0,$M91=""),"",$M91/$L91) -> 0.43207444 | P91: =IF(OR($K91="",$O91=""),"",$K91-$O91) | Q91: DONE | R91: 95 | S91: PENDING | T91: 45527 | U91: 45528 | W91: =IF(OR($B91="",$U91=""),"",$U91-$B91) -> 4 | X91: Closed | Y91: BN | AA91: 23-08-2024 | AB91: 24-08-2024
A92: =IF($B92="","",ROW()-6) -> 86 | B92: 45525 | C92: =IF($B92="","",EOMONTH($B92,-1)+1) -> 45505 | D92: BN | E92: JH01KM-8803 | F92: 9589264337 | G92: RANCHI | H92: BOMMANSANDRA,467189 | I92: HOSUR,630362 (76215) | J92: 32FEET SXL | K92: 45170 | L92: 46620 | M92: =IF(OR($K92="",$L92=""),"",$L92-$K92) -> 1450 | N92: =IF(OR($L92="",$L92=0,$M92=""),"",$M92/$L92) -> 0.031102531 | P92: =IF(OR($K92="",$O92=""),"",$K92-$O92) | Q92: DONE | R92: 96 | S92: PENDING | T92: 45529 | U92: 45530 | W92: =IF(OR($B92="",$U92=""),"",$U92-$B92) -> 5 | X92: Closed | Y92: BN | AA92: 25-08-2024 | AB92: 26-08-2024
A93: =IF($B93="","",ROW()-6) -> 87 | B93: 45528 | C93: =IF($B93="","",EOMONTH($B93,-1)+1) -> 45505 | D93: 3rd Party | E93: TN02EV-8853 | F93: 9772336065 | G93: RANCHI | H93: NARSAPUR,219420 | I93: BOMMANSANDRA,071351 | J93: 32FEET SXL | K93: 33770 | L93: 46620 | M93: =IF(OR($K93="",$L93=""),"",$L93-$K93) -> 12850 | N93: =IF(OR($L93="",$L93=0,$M93=""),"",$M93/$L93) -> 0.27563278 | O93: 33770 | P93: =IF(OR($K93="",$O93=""),"",$K93-$O93) -> 0 | Q93: DONE | R93: 97 | S93: PENDING | T93: 45532 | U93: 45532 | W93: =IF(OR($B93="",$U93=""),"",$U93-$B93) -> 4 | X93: Closed | Y93: Transporter 02 | AA93: 28-08-2024 | AB93: 28-08-2024
A94: =IF($B94="","",ROW()-6) -> 88 | B94: 45528 | C94: =IF($B94="","",EOMONTH($B94,-1)+1) -> 45505 | D94: 3rd Party | E94: MH14CY-6391 | F94: 9788395365 | G94: ERODE | H94: N/A | I94: RANCHI | J94: 32FEET SXL | K94: 67210 | L94: 96390 | M94: =IF(OR($K94="",$L94=""),"",$L94-$K94) -> 29180 | N94: =IF(OR($L94="",$L94=0,$M94=""),"",$M94/$L94) -> 0.3027285 | O94: 67210 | P94: =IF(OR($K94="",$O94=""),"",$K94-$O94) -> 0 | Q94: DONE | R94: 98 | S94: PENDING | T94: 45533 | U94: 45533 | W94: =IF(OR($B94="",$U94=""),"",$U94-$B94) -> 5 | X94: Closed | Y94: Transporter 13 | AA94: 29-08-2024 | AB94: 29-08-2024
A95: =IF($B95="","",ROW()-6) -> 89 | B95: 45528 | C95: =IF($B95="","",EOMONTH($B95,-1)+1) -> 45505 | D95: 3rd Party | E95: TN02ZE-2186 | F95: 9065465756 | G95: RANCHI | H95: N/A | I95: HASSAN,452608 | J95: 32FEET SXL | K95: 40160 | L95: 53550 | M95: =IF(OR($K95="",$L95=""),"",$L95-$K95) -> 13390 | N95: =IF(OR($L95="",$L95=0,$M95=""),"",$M95/$L95) -> 0.25004669 | O95: 40160 | P95: =IF(OR($K95="",$O95=""),"",$K95-$O95) -> 0 | Q95: DONE | R95: 99 | S95: PENDING | T95: 45533 | U95: 45533 | W95: =IF(OR($B95="",$U95=""),"",$U95-$B95) -> 5 | X95: Closed | Y95: Transporter 12 | Z95: OVERLOAD - EXTRA CHARGE | AA95: 29-08-2024 | AB95: 29-08-2024
A96: =IF($B96="","",ROW()-6) -> 90 | B96: 45528 | C96: =IF($B96="","",EOMONTH($B96,-1)+1) -> 45505 | D96: 3rd Party | E96: KA05GM-9110 | F96: 9748894966 | G96: RANCHI | H96: N/A | I96: HOSUR,731673(78679) | J96: 20FEET | K96: 25690 | L96: 35600 | M96: =IF(OR($K96="",$L96=""),"",$L96-$K96) -> 9910 | N96: =IF(OR($L96="",$L96=0,$M96=""),"",$M96/$L96) -> 0.27837079 | O96: 25690 | P96: =IF(OR($K96="",$O96=""),"",$K96-$O96) -> 0 | Q96: DONE | R96: 100 | S96: PENDING | T96: 45532 | U96: 45532 | W96: =IF(OR($B96="",$U96=""),"",$U96-$B96) -> 4 | X96: Closed | Y96: Transporter 02 | AA96: 28-08-2024 | AB96: 28-08-2024
A97: =IF($B97="","",ROW()-6) -> 91 | B97: 45528 | C97: =IF($B97="","",EOMONTH($B97,-1)+1) -> 45505 | D97: 3rd Party | E97: TN93L-8071 | F97: 9950818773 | G97: RANCHI | H97: NARSAPUR,415768 +HOSKOTE,364185 | I97: BOMMANSANDRA,901796 | J97: 32FEET SXL | K97: 33640 | L97: 52920 | M97: =IF(OR($K97="",$L97=""),"",$L97-$K97) -> 19280 | N97: =IF(OR($L97="",$L97=0,$M97=""),"",$M97/$L97) -> 0.36432351 | O97: 33640 | P97: =IF(OR($K97="",$O97=""),"",$K97-$O97) -> 0 | Q97: DONE | R97: 101 | S97: PENDING | T97: 45532 | U97: 45532 | W97: =IF(OR($B97="",$U97=""),"",$U97-$B97) -> 4 | X97: Closed | Y97: Transporter 02 | AA97: 28-08-2024 | AB97: 28-08-2024
A98: =IF($B98="","",ROW()-6) -> 92 | B98: 45531 | C98: =IF($B98="","",EOMONTH($B98,-1)+1) -> 45505 | D98: 3rd Party | E98: KA52K-7446 | F98: 9923171297 | G98: RANCHI | H98: N/A | I98: HOSUR,556621 (89221) | J98: 22FEET | K98: 25690 | L98: 35600 | M98: =IF(OR($K98="",$L98=""),"",$L98-$K98) -> 9910 | N98: =IF(OR($L98="",$L98=0,$M98=""),"",$M98/$L98) -> 0.27837079 | O98: 25690 | P98: =IF(OR($K98="",$O98=""),"",$K98-$O98) -> 0 | Q98: DONE | R98: 102 | S98: PENDING | T98: 45534 | U98: 45534 | W98: =IF(OR($B98="",$U98=""),"",$U98-$B98) -> 3 | X98: Closed | Y98: Transporter 02 | AA98: 30-08-2024 | AB98: 30-08-2024
A99: =IF($B99="","",ROW()-6) -> 93 | B99: 45531 | C99: =IF($B99="","",EOMONTH($B99,-1)+1) -> 45505 | D99: 3rd Party | E99: TN18DH-3563 | F99: 9358929187 | G99: RANCHI | H99: N/A | I99: HOSUR,450806 (86986) | J99: 32FEET SXL | K99: 34300 | L99: 46620 | M99: =IF(OR($K99="",$L99=""),"",$L99-$K99) -> 12320 | N99: =IF(OR($L99="",$L99=0,$M99=""),"",$M99/$L99) -> 0.26426426 | O99: 34300 | P99: =IF(OR($K99="",$O99=""),"",$K99-$O99) -> 0 | Q99: DONE | R99: 103 | S99: PENDING | T99: 45535 | U99: 45535 | W99: =IF(OR($B99="",$U99=""),"",$U99-$B99) -> 4 | X99: Closed | Y99: Transporter 07 | Z99: OVERLOAD - EXTRA CHARGE | AA99: 31-08-2024 | AB99: 31-08-2024
A100: =IF($B100="","",ROW()-6) -> 94 | B100: 45531 | C100: =IF($B100="","",EOMONTH($B100,-1)+1) -> 45505 | D100: 3rd Party | E100: KA53NV-5673 | F100: 9165942602 | G100: RANCHI | H100: BMS | I100: HASSAN | J100: 22FEET | K100: 29550 | L100: 43470 | M100: =IF(OR($K100="",$L100=""),"",$L100-$K100) -> 13920 | N100: =IF(OR($L100="",$L100=0,$M100=""),"",$M100/$L100) -> 0.32022084 | O100: 29550 | P100: =IF(OR($K100="",$O100=""),"",$K100-$O100) -> 0 | Q100: DONE | R100: 104 | S100: PENDING | T100: 45535 | U100: 45535 | W100: =IF(OR($B100="",$U100=""),"",$U100-$B100) -> 4 | X100: Closed | Y100: Transporter 02 | Z100: SPEED MODE MATERIAL EXTRA CHARGE | AA100: 31-08-2024 | AB100: 31-08-2024
A101: =IF($B101="","",ROW()-6) -> 95 | B101: 45531 | C101: =IF($B101="","",EOMONTH($B101,-1)+1) -> 45505 | D101: BN | E101: JH01KM-4371 | F101: 9515412075 | G101: RANCHI | H101: HOSKOTE | I101: BOMMANSANDRA | J101: 24FEET | K101: 44930 | L101: 45040 | M101: =IF(OR($K101="",$L101=""),"",$L101-$K101) -> 110 | N101: =IF(OR($L101="",$L101=0,$M101=""),"",$M101/$L101) -> 0.0024422735 | P101: =IF(OR($K101="",$O101=""),"",$K101-$O101) | Q101: DONE | R101: 105 | S101: PENDING | T101: 45535 | U101: 45535 | W101: =IF(OR($B101="",$U101=""),"",$U101-$B101) -> 4 | X101: Closed | Y101: BN | AA101: 31-08-2024 | AB101: 31-08-2024
...

Sheet Market Load
A1: S.NO. | B1: LOAD DATE | C1: LORRY NO. | D1: CUSTOMER NAME | E1: LOAD FROM | F1: DELIVERY POINT | G1: RATE | H1: ADVANCE | I1: BALANCE | J1: ADVANCE RECEIVED DATE | K1: REMARKS | L1: POD STATUS
A2: 1 | B2: 45756 | C2: JH01KD-6142 | D2: Customer 01 | E2: KRISHNAGIRI | F2: RANCHI | G2: 54450 | H2: 54450 | J2: 45761 | K2: ALL FREIGHT CLEAR NO DUES | L2: DONE
A3: 2 | B3: 45765 | C3: JH01KD-0526 | D3: Customer 02 | E3: HOSKOTE | F3: KOLKATA | G3: 49500 | H3: 49500 | J3: 45768 | K3: ALL FREIGHT CLEAR NO DUES | L3: DONE
A4: 3 | B4: 45768 | C4: JH01KD-2417 | D4: Customer 02 | E4: MALUR | F4: BIHAR SHARIF | G4: 57420 | H4: 57420 | J4: 45772 | K4: ALL FREIGHT CLEAR NO DUES | L4: DONE
A5: 4 | B5: 45772 | C5: JH01KD-6142 | D5: Customer 01 | E5: KRISHNAGIRI | F5: DHULAGARH | G5: 49500 | H5: 49500 | J5: 45776 | K5: ALL FREIGHT CLEAR NO DUES | L5: DONE
A6: 5 | B6: 45772 | C6: JH01KD-0526 | D6: Customer 01 | E6: HOSKOTE | F6: DHULAGARH | G6: 49830 | H6: 49830 | J6: 45778 | K6: ALL FREIGHT CLEAR NO DUES | L6: DONE
A7: 6 | B7: 45773 | C7: JH01KM-8803 | D7: Customer 02 | E7: ATIBALLI+NEELMANGLA | F7: ANGUL ODISSA | G7: 54580 | H7: 54580 | J7: 45775 | K7: ALL FREIGHT CLEAR NO DUES | L7: DONE
A8: 7 | B8: 45782 | C8: JH01KD-0526 | D8: Customer 01 | E8: KRISHNAGIRI | F8: DHULAGARH | G8: 50490 | H8: 50490 | J8: 45792 | K8: ALL FREIGHT CLEAR NO DUES | L8: DONE
A9: 8 | B9: 45782 | C9: JH01KD-6142 | D9: Customer 02 | E9: ATIBALLI+NEELMANGLA | F9: BURGED ODISSA | G9: 56100 | H9: 56100 | J9: 45783 | K9: ALL FREIGHT CLEAR NO DUES | L9: DONE
A10: 9 | B10: 45784 | C10: JH01KD-2417 | D10: Customer 01 | E10: KRISHNAGIRI | F10: RANCHI | G10: 54450 | H10: 54450 | J10: 45784 | K10: ALL FREIGHT CLEAR NO DUES | L10: DONE
A11: 10 | B11: 45793 | C11: JH01KD-2417 | D11: Transporter 29 | E11: NARSAPUR | F11: TIRUPPUR | G11: 9900 | H11: 9900 | I11: - | J11: 45840 | K11: ALL FREIGHT CLEAR NO DUES | L11: DONE
A12: 11 | B12: 45796 | C12: JH01KD-6142 | D12: Customer 02 | E12: ATIBALLI+JIGNI | F12: SAMBALPUR ODISSA | G12: 56100 | H12: 56100 | J12: 45798 | K12: ALL FREIGHT CLEAR NO DUES | L12: DONE
A13: 12 | B13: 45813 | C13: JH01KD-0526 | D13: Transporter 33 | E13: NARSAPUR | F13: TIRCHY | G13: 14520 | H13: 14520 | J13: 45819 | K13: ALL FREIGHT CLEAR NO DUES | L13: DONE
A14: 13 | B14: 45814 | C14: JH01KD-6142 | D14: Customer 02 | E14: JIGNI+NEELMANGLA | F14: DHULAGARH | G14: 54780 | H14: 54780 | J14: 45814 | K14: ALL FREIGHT CLEAR NO DUES | L14: DONE
A15: 14 | B15: 45817 | C15: JH01KD-6142 | D15: Customer 05 | E15: HOWRAH | F15: RANCHI | G15: 16500 | H15: 16500 | J15: 45819 | K15: ALL FREIGHT CLEAR NO DUES | L15: DONE
A16: 15 | B16: 45836 | C16: JH01KD-0526 | D16: Transporter 33 | E16: NARSAPUR | F16: DURGAPUR | G16: 56100 | H16: 56100 | I16: - | J16: 45884 | K16: ALL FREIGHT CLEAR NO DUES | L16: DONE
A17: 16 | B17: 45841 | C17: JH01KM-8803 | D17: Customer 02 | E17: K.R.PURAM BANGLORE | F17: BRAHMAPUR,ODISSA | G17: 49500 | H17: 49500 | J17: 45843 | K17: ALL FREIGHT CLEAR NO DUES | L17: DONE
A18: 17 | B18: 45844 | C18: JH01KM-8803 | D18: Customer 06 | E18: BRAHMAPUR | F18: KEONJHAR | G18: 6600 | H18: 6600 | I18: - | J18: 45844 | K18: ALL FREIGHT CLEAR NO DUES | L18: DONE
A19: 17 | B19: 45841 | C19: JH01KD-3958 | D19: Customer 02 | E19: JIGNI,BNG | F19: PATNA | G19: 58080 | H19: 58080 | J19: 45843 | K19: ALL FREIGHT CLEAR NO DUES | L19: DONE
A20: 18 | B20: 45843 | C20: JH01KD-6142 | D20: Customer 01 | E20: KRISHNAGIRI | F20: RANCHI | G20: 52470 | H20: 52470 | J20: 45846 | K20: ALL FREIGHT CLEAR NO DUES | L20: DONE
A21: 19 | B21: 45851 | C21: JH01KD-2417 | D21: Customer 07 | E21: NEELMANGLA | F21: RANCHI | G21: 59400 | H21: 59400 | I21: - | J21: 45930 | K21: ALL FREIGHT CLEAR NO DUES | L21: DONE
A22: 20 | B22: 45860 | C22: JH01KD-2417 | D22: Customer 01 | E22: KRISHNAGIRI | F22: DHULAGARH | G22: 48840 | H22: 48840 | I22: - | J22: 45863 | K22: ALL FREIGHT CLEAR NO DUES | L22: DONE
A23: 21 | B23: 45876 | C23: JH01KD-6142 | D23: Customer 01 | E23: KRISHNAGIRI | F23: RANCHI | G23: 49500 | H23: 49500 | I23: - | J23: - | K23: ALL FREIGHT CLEAR NO DUES | L23: DONE
A24: 22 | B24: 45883 | C24: JH01KM-8803 | D24: Customer 02 | E24: JIGNI | F24: PATNA | G24: 52800 | H24: 52800 | I24: - | J24: 45885 | K24: ALL FREIGHT CLEAR NO DUES | L24: DONE
A25: 23 | B25: 45886 | C25: JH01KD-3958 | D25: Customer 02 | E25: JIGNI | F25: PATNA | G25: 52800 | H25: 52800 | I25: - | J25: 45890 | K25: ALL FREIGHT CLEAR NO DUES | L25: DONE
A26: 24 | B26: 45887 | C26: JH01KD-6142 | D26: Customer 02 | E26: JIGNI | F26: PATNA | G26: 52800 | H26: 5280 | I26: - | J26: 45890 | K26: ALL FREIGHT CLEAR NO DUES | L26: DONE
A27: 25 | B27: 45891 | C27: JH01KD-0526 | D27: Customer 02 | E27: DODABALLAPUR | F27: KOLKATA | G27: 48180 | H27: 48180 | I27: - | J27: - | K27: ALL FREIGHT CLEAR NO DUES | L27: DONE
A28: 26 | B28: 45892 | C28: JH01KD2417 | D28: Customer 01 | E28: KRISHNAGIRI | F28: RANCHI | G28: 49170 | H28: 49170 | I28: - | J28: - | K28: ALL FREIGHT CLEAR NO DUES | L28: DONE
A29: 57 | B29: 45894 | C29: BR24XY-8129 | D29: Customer 01 | E29: CHENNAI | F29: KOLKATA | G29: 46860 | H29: 46860 | I29: - | J29: 26-08-205 | K29: ALL FREIGHT CLEAR NO DUES | L29: DONE
A30: 58 | B30: 45904 | C30: JH01KD-3958 | D30: Customer 02 | E30: JIGNI | F30: PATNA | G30: 54120 | H30: 54120 | I30: - | J30: 46000 | K30: ALL FREIGHT CLEAR NO DUES | L30: DONE
A31: 59 | B31: 45910 | C31: JH01KD-0526 | D31: Customer 02 | E31: JIGNI | F31: PATNA | G31: 54120 | H31: 54120 | I31: - | J31: - | K31: ALL FREIGHT CLEAR NO DUES | L31: DONE
A32: 60 | B32: 45915 | C32: JH01KD-6142 | D32: Customer 01 | E32: NEELMANGLA | F32: KOLKATA | G32: 47520 | H32: 47520 | I32: - | J32: - | K32: ALL FREIGHT CLEAR NO DUES | L32: DONE
A33: 61 | B33: 45917 | C33: JH01KD-3958 | D33: Customer 02 | E33: JIGNI | F33: PATNA | G33: 54120 | H33: 54120 | I33: - | J33: - | K33: ALL FREIGHT CLEAR NO DUES | L33: DONE
A34: 62 | B34: 45920 | C34: BR24XY-8129 | D34: Customer 01 | E34: KRISHNAGIRI | F34: DHULAGARH | G34: 48510 | H34: 48510 | I34: - | J34: - | K34: ALL FREIGHT CLEAR NO DUES | L34: DONE
A35: 63 | B35: 45926 | C35: BR24XY-8129 | D35: BN | E35: KOLKATA | F35: RANCHI | G35: 16500 | H35: 16500 | I35: - | J35: 45940 | K35: ALL FREIGHT CLEAR NO DUES | L35: DONE
A36: 64 | B36: 45954 | C36: JH01KD-6142 | D36: Customer 02 | E36: JIGNI | F36: BALASORE | G36: 50160 | H36: 50160 | I36: - | J36: - | K36: ALL FREIGHT CLEAR NO DUES | L36: DONE
A37: 65 | B37: 45958 | C37: JH01KD-0526 | D37: Customer 02 | E37: JIGNI | F37: BALASORE | G37: 47520 | H37: 47520 | I37: - | J37: - | K37: ALL FREIGHT CLEAR NO DUES | L37: DONE
A38: 66 | B38: 45965 | C38: JH01KD-2417 | D38: Customer 01 | E38: KRISHNAGIRI | F38: RANCHI | G38: 50160 | H38: 50160 | I38: - | J38: 45967 | K38: ALL FREIGHT CLEAR NO DUES | L38: DONE
A39: 67 | B39: 45965 | C39: JH01KD-6142 | D39: Customer 01 | E39: KRISHNAGIRI | F39: DHULAGARH | G39: 48840 | H39: 48840 | I39: - | J39: 45979 | K39: ALL FREIGHT CLEAR NO DUES | L39: DONE
A40: 68 | B40: 45968 | C40: JH01KD-0526 | D40: Customer 02 | E40: HOSUR | F40: KOLKATA | G40: 49500 | H40: 49500 | I40: - | J40: - | K40: ALL FREIGHT CLEAR NO DUES | L40: DONE
A41: 69 | B41: 45968 | C41: JH01KD-3958 | D41: Customer 02 | E41: KR PURAM BNG | F41: DHULAGARH | G41: 49500 | H41: 49500 | I41: - | J41: - | K41: ALL FREIGHT CLEAR NO DUES | L41: DONE
A42: 70 | B42: 45977 | C42: JH01KD-0526 | D42: Customer 08 | E42: BOMMANSANDRA | F42: KOLKATA | G42: 51500 | H42: 51500 | I42: - | J42: 45979 | K42: ALL FREIGHT CLEAR NO DUES | L42: DONE
A43: 71 | B43: 45979 | C43: JH01KD-3958 | D43: Customer 08 | E43: NEELMANGLA | F43: RANCHI | G43: 55620 | H43: 55620 | I43: - | J43: 45979 | K43: ALL FREIGHT CLEAR NO DUES | L43: DONE
A44: 72 | B44: 45979 | C44: JH01KM-8803 | D44: Customer 08 | E44: NEELMANGLA | F44: RANCHI | G44: 55620 | H44: 55620 | I44: - | J44: 45979 | K44: ALL FREIGHT CLEAR NO DUES | L44: DONE
A45: 73 | B45: 45989 | C45: JH01KD-0526 | D45: Customer 08 | E45: HOSKOTE | F45: KOLKATA | G45: 54780 | H45: 54780 | J45: - | K45: ALL FREIGHT CLEAR NO DUES | L45: DONE
A46: 74 | B46: 45991 | C46: JH01KD-3958 | D46: Customer 08 | E46: HOSKOTE | F46: KOLKATA | G46: 54780 | H46: 54780 | I46: - | J46: - | K46: ALL FREIGHT CLEAR NO DUES | L46: DONE
A47: 75 | B47: 45991 | C47: JH01KD-2417 | D47: Customer 08 | E47: NEELMANGLA | F47: DHULAGARH | G47: 51480 | H47: 51480 | J47: - | K47: ALL FREIGHT CLEAR NO DUES | L47: DONE
A48: 76 | B48: 46001 | C48: JH01KD-2417 | D48: Customer 08 | E48: BMS | F48: RANCHI | G48: 52600 | H48: 52600 | I48: - | J48: - | K48: ALL FREIGHT CLEAR NO DUES | L48: DONE
A49: 77 | B49: 46024 | C49: JH01KD-6142 | D49: Customer 09 | E49: TUMKUR BNG | F49: ODISSA+KOLKATA | G49: 52000 | H49: 44320 | I49: - | J49: - | K49: ALL FREIGHT CLEAR NO DUES | L49: DONE ,V6903129326
A50: 78 | B50: 46028 | C50: JH01KD-6142 | D50: BN | E50: KOLKATA | F50: RANCHI | G50: 16500 | H50: 16500 | I50: - | J50: 46042 | K50: ALL FREIGHT CLEAR NO DUES | L50: BILL NO.234
A51: 79 | B51: 46039 | C51: JH01KM-8803 | D51: Customer 09 | E51: ATIBALLI+JIGNI | F51: DARBHANGA BIHAR | G51: 51480 | H51: 51480 | I51: - | J51: 46039 | K51: ALL FREIGHT CLEAR NO DUES | L51: DONE,V1662352462
A52: 80 | B52: 46041 | C52: JH01KD-0526 | D52: Customer 09 | E52: ATIBALLI | F52: PURNIA BIHAR | G52: 51480 | H52: 51480 | I52: - | J52: 46041 | K52: ALL FREIGHT CLEAR NO DUES | L52: DONE,V1662352462
A53: 81 | B53: 46041 | C53: JH01KD-3958 | D53: Customer 09 | E53: JIGNI | F53: PURNIA BIHAR | G53: 50820 | H53: 50820 | I53: - | J53: 46041 | K53: ALL FREIGHT CLEAR NO DUES | L53: DONE,V1662352462
A54: 82 | B54: 46041 | C54: JH01KD-2417 | D54: Customer 09 | E54: ATIBALLI+JIGNI | F54: BHAGALPUR | G54: 51480 | H54: 51480 | I54: - | J54: 46041 | K54: ALL FREIGHT CLEAR NO DUES | L54: DONE,V1662352462
A55: 83 | B55: 46068 | C55: JH01KD-6142 | D55: Customer 09 | E55: ATIBALLI,BNG | F55: MUJAFFARPUR | G55: 51680 | H55: 51680 | I55: - | J55: 46071 | K55: ALL FREIGHT CLEAR NO DUES | L55: DONE
A56: 84 | B56: 46041 | C56: JH01KD-0526 | D56: Customer 09 | E56: JIGNI | F56: PATNA | G56: 51410 | H56: 51410 | I56: - | J56: 46073 | K56: ALL FREIGHT CLEAR NO DUES | L56: DONE
A57: 85 | B57: 46079 | C57: JH01KD-6142 | D57: Customer 09 | E57: JIGNI BNG | F57: KOLKATA | G57: 53920 | H57: 53920 | I57: - | J57: 46079 | K57: ALL FREIGHT CLEAR NO DUES | L57: DONE
A58: 86 | B58: 46084 | C58: JH01KD-6142 | D58: BN | E58: KOLKATA | F58: RANCHI | G58: 9900 | H58: 9900 | I58: - | J58: 46097 | K58: ALL FREIGHT CLEAR NO DUES | L58: BILLNO.316
A59: 87 | B59: 46092 | C59: JH01KD-6142 | D59: Customer 09 | E59: SOUKIYA BNG | F59: KOLKATA | G59: 50490 | H59: 50490 | I59: - | J59: 46094 | K59: ALL FREIGHT CLEAR NO DUES | L59: DONE
A60: 88 | B60: 46096 | C60: JH01KD-3958 | D60: Customer 09 | E60: JIGNI BNG | F60: SAMBALPUR ODISSA | G60: 46200 | H60: 46200 | I60: - | J60: 46099 | K60: ALL FREIGHT CLEAR NO DUES | L60: DONE | M60: HALTING CHARGE PENDING
A61: 89 | B61: 46101 | C61: JH01KD-2417 | D61: Customer 10 | E61: JIGNI BNG | F61: KOLKATA | G61: 50120 | H61: 50120 | I61: - | J61: 46102 | K61: ALL FREIGHT CLEAR NO DUES | L61: DONE
A62: 90 | B62: 46102 | C62: JH01KD-0526 | D62: Customer 09 | E62: JIGNI BNG | F62: PATNA | G62: 54780 | H62: 54780 | I62: - | J62: 46103 | K62: ALL FREIGHT CLEAR NO DUES | L62: DONE
A63: 91 | B63: 46102 | C63: JH01KD-6142 | D63: Customer 10 | E63: NEELMANGLA | F63: BHUBNESHWAR | G63: 43760 | H63: 43760 | I63: - | J63: 46103 | K63: ALL FREIGHT CLEAR NO DUES | L63: DONE
A64: 92 | B64: 46104 | C64: JH01KD-6142 | D64: Customer 10 | E64: PURI ODISSA | F64: RANCHI | G64: 13980 | H64: 13980 | I64: - | K64: ALL FREIGHT CLEAR NO DUES | L64: DONE
A65: 93 | B65: 46105 | C65: JH01KD-2417 | D65: Customer 10 | E65: KOLKATA,2 | F65: RANCHI | G65: 13970 | H65: 13970 | I65: - | J65: 46105 | K65: ALL FREIGHT CLEAR NO DUES | L65: DONE
A66: 94 | B66: 46107 | C66: JH01KD-0526 | D66: Customer 10 | E66: PATNA,3 | F66: KOLKATA | G66: 13970 | H66: 13970 | I66: - | J66: 46107 | K66: ALL FREIGHT CLEAR NO DUES | L66: DONE
A67: 95 | B67: 46107 | C67: JH01KD-6142 | D67: Customer 10 | E67: RANCHI | F67: SAMBALPUR ODISSA | G67: 12340 | H67: 12340 | I67: - | K67: ALL FREIGHT CLEAR NO DUES | L67: DONE
A68: 96 | B68: 46108 | C68: JH01KM-8803 | D68: Customer 09 | E68: JIGNI BNG | F68: PATNA | G68: 54780 | H68: 54780 | I68: - | J68: 46108 | K68: ALL FREIGHT CLEAR NO DUES | L68: DONE
A69: 97 | B69: 46114 | C69: JH01KM-8803 | D69: Customer 10 | E69: HAZIPUR BIHAR | F69: RAMGARH RANCHI | G69: 11150 | H69: 11150 | I69: - | J69: - | K69: ALL FREIGHT CLEAR NO DUES | L69: DONE
A70: 98 | B70: 46115 | C70: JH01KR-1695 | D70: Customer 10 | E70: NAGRI RANCHI | F70: KHARAGPUR | G70: 9510 | H70: 9510 | I70: - | J70: 46115 | K70: ALL FREIGHT CLEAR NO DUES | L70: DONE
A71: 99 | B71: 46115 | C71: JH01KD-0526 | D71: Customer 09 | E71: JIGNI+ATIBALLI BNG | F71: BHAGALPUR | G71: 56100 | H71: 56100 | I71: - | J71: - | K71: ALL FREIGHT CLEAR NO DUES | L71: DONE
A72: 100 | B72: 46116 | C72: JH01KR-1695 | D72: BN | E72: KOLKATA | F72: RANCHI | G72: 16500 | H72: 16500 | I72: - | J72: - | K72: ALL FREIGHT CLEAR NO DUES | L72: DONE
A73: 101 | B73: 46117 | C73: JH01KD-6142 | D73: Customer 10 | E73: RANCHI | F73: PATNA | G73: 11220 | H73: 11220 | I73: - | J73: 46118 | K73: ALL FREIGHT CLEAR NO DUES | L73: DONE
A74: 102 | B74: 46118 | C74: JH01KM-8803 | D74: Customer 10 | E74: RANCHI | F74: SALAP KOLKATA | G74: 9900 | H74: 9900 | I74: - | J74: 46118 | K74: ALL FREIGHT CLEAR NO DUES | L74: DONE
A75: 103 | B75: 46119 | C75: JH01KD-0526 | D75: Customer 10 | E75: PATNA HAZIPUR | F75: SIMDEGA | G75: 10560 | H75: 10560 | I75: - | J75: 46121 | K75: ALL FREIGHT CLEAR NO DUES | L75: DONE
A76: 104 | B76: 46120 | C76: JH01KD-2417 | D76: Customer 10 | E76: RANCHI | F76: CUTTACK | G76: 13660 | H76: 13660 | I76: - | J76: 46121 | K76: ALL FREIGHT CLEAR NO DUES | L76: DONE
A77: 105 | B77: 46121 | C77: JH01KD-3958 | D77: Customer 10 | E77: RANCHI | F77: KOLKATA | G77: 10690 | H77: 10690 | I77: - | J77: 46121 | K77: ALL FREIGHT CLEAR NO DUES | L77: DONE
A78: 106 | B78: 46121 | C78: JH01KM-8803 | D78: Customer 10+ 05DAYS HALTING 7518 | E78: KOLKATA | F78: ODISSA | G78: 18760 | H78: 18760 | I78: - | J78: 46123 | K78: ALL FREIGHT CLEAR NO DUES | L78: DONE
A79: 107 | B79: 46122 | C79: JH01KD-2417 | D79: Customer 10 | E79: CUTTACK | F79: BANGLORE | G79: 18150 | H79: 20200 | I79: - | J79: 46123 | K79: ALL FREIGHT CLEAR NO DUES | L79: DONE
A80: 108 | B80: 46122 | C80: JH01KD-6142 | D80: Customer 10 | E80: PATNA | F80: CUTTACK | G80: 17160 | H80: 17160 | I80: - | J80: 46122 | K80: ALL FREIGHT CLEAR NO DUES | L80: DONE
A81: 109 | B81: 46123 | C81: JH01KD-0526 | D81: Customer 11 | E81: JAMSHEDPUR | F81: CHENNAI | G81: 24140 | H81: 24140 | I81: - | J81: 46126 | K81: ALL FREIGHT CLEAR NO DUES | L81: DONE
A82: 110 | B82: 46125 | C82: JH01KD-7230 | D82: Customer 11 | E82: JAMSHEDPUR | F82: CHENNAI | G82: 25180 | H82: 25180 | I82: - | J82: 46126 | K82: ALL FREIGHT CLEAR NO DUES | L82: DONE
A83: 111 | B83: 46125 | C83: JH01KD-3958 | D83: Customer 12 | E83: KOLKATA | F83: BANGLORE | G83: 28380 | H83: 28380 | I83: - | J83: - | K83: ALL FREIGHT CLEAR NO DUES | L83: DONE
A84: 112 | B84: 46125 | C84: JH01KD-6142 | D84: Customer 10 | E84: ODISSA | F84: HOSUR | G84: 25090 | H84: 25090 | I84: - | J84: - | K84: ALL FREIGHT CLEAR NO DUES | L84: DONE
A85: 113 | B85: 46126 | C85: JH01KR-9064 | D85: Customer 10 | E85: JAMSHEDPUR | F85: ANGUL ODISSA | G85: 13330 | H85: 13330 | I85: - | J85: - | K85: ALL FREIGHT CLEAR NO DUES | L85: DONE
A86: 114 | B86: 46128 | C86: JH01KD-0526 | D86: Customer 09 | E86: CHENNAI | F86: PATNA | G86: 58340 | H86: 58340 | I86: - | J86: - | K86: ALL FREIGHT CLEAR NO DUES | L86: DONE
A87: 115 | B87: 46129 | C87: JH01KR-5582 | D87: Customer 09 | E87: JIGNI BNG | F87: PATNA | G87: 59530 | H87: 59530 | I87: - | J87: - | K87: ALL FREIGHT CLEAR NO DUES | L87: DONE
A88: 116 | B88: 46129 | C88: JH01KR-7230 | D88: Customer 10 | E88: CHENNAI | F88: PATNA | G88: 64020 | H88: 64020 | I88: - | J88: - | K88: ALL FREIGHT CLEAR NO DUES | L88: DONE
A89: 117 | B89: 46131 | C89: JH01KM-8803 | D89: Customer 10 | E89: ODISSA | F89: HOSUR | G89: 26910 | H89: 26910 | I89: - | J89: - | K89: ALL FREIGHT CLEAR NO DUES | L89: DONE
A90: 118 | B90: 46132 | C90: JH01KR-9064 | D90: Customer 13 | E90: BALASORE | F90: NAMAKKAL ,TN. | G90: 29700 | H90: 29700 | I90: - | J90: - | K90: ALL FREIGHT CLEAR NO DUES | L90: DONE
A91: 119 | B91: 46132 | C91: JH01KD-3958 | D91: Customer 10 | E91: BANGLORE | F91: DANKUNI | G91: 50160 | H91: 50160 | I91: - | J91: - | K91: ALL FREIGHT CLEAR NO DUES | L91: DONE
A92: 120 | B92: 46133 | C92: JH01KD-0526 | D92: Customer 14 | E92: PATNA | F92: BOKARO | G92: 9240 | H92: 8380 | I92: 860 | J92: - | K92: BALANCE PENDING | L92: DONE
A93: 121 | B93: 46134 | C93: JH01KR-5582 | D93: Customer 14 | E93: PATNA | F93: JAMSHEDPUR | G93: 10560 | H93: 9700 | I93: 860 | J93: - | K93: BALANCE PENDING | L93: DONE
A94: 122 | B94: 46136 | C94: JH01KD-2417 | D94: Customer 10 | E94: HOSUR | F94: BAGNAN KOLKATA | G94: 51810 | H94: 51810 | I94: - | J94: - | K94: ALL FREIGHT CLEAR NO DUES | L94: DONE
A95: 123 | B95: 46137 | C95: JH01KD-6142 | D95: Customer 10 | E95: HOSKOTE | F95: BAGNAN KOLKATA | G95: 51810 | H95: 51810 | I95: - | J95: - | K95: ALL FREIGHT CLEAR NO DUES | L95: DONE
A96: 124 | B96: 46140 | C96: JH01KR-7230 | D96: Customer 10 | E96: BANGLORE | F96: GUWAHATI | G96: 73290 | H96: 73290 | I96: - | J96: 46141 | K96: ALL FREIGHT CLEAR NO DUES | L96: DONE
A97: 125 | B97: 46141 | C97: JH01KR-5582 | D97: Customer 10 | E97: BANGLORE | F97: BALASORE | G97: 50890 | H97: 50890 | I97: - | J97: 46142 | K97: ALL FREIGHT CLEAR NO DUES | L97: DONE
A98: 126 | B98: 46141 | C98: JH01KR-1695 | D98: Customer 11 | E98: JAMSHEDPUR | F98: DHARWAD | G98: 34980 | H98: 34980 | I98: - | J98: - | K98: ALL FREIGHT CLEAR NO DUES | L98: DONE
A99: 127 | B99: 46147 | C99: JH01KR-5582 | D99: Customer 10 | E99: JAJPUR ODISSA | F99: HYDERABAD | G99: 16500 | H99: 16500 | I99: - | J99: 46148 | K99: ALL FREIGHT CLEAR NO DUES | L99: DONE
A100: 128 | B100: 46147 | C100: JH01KR-7230 | D100: Customer 10 | E100: GUWAHATI | F100: PAKUR JHARKHAND | G100: 14520 | H100: 14520 | I100: - | J100: 46148 | K100: ALL FREIGHT CLEAR NO DUES | L100: DONE
...

Sheet MARKET LOAD CLEAN
A1: MARKET LOAD REGISTER — BN LOGISTICS (own trucks sold outside Auburn)
A2: LOADS | B2: =SUMPRODUCT(--(MARKET[LOAD DATE]<>"")) -> 171 | D2: REVENUE | E2: =SUM(MARKET[RATE (₹)]) -> 6780690 | G2: AVG LOAD VALUE | H2: =IFERROR(AVERAGE(MARKET[RATE (₹)]),"") -> 39653.158 | J2: Blue = you type it
A3: PERIOD | B3: =TEXT(MIN(MARKET[LOAD DATE]),"mmm yyyy")&" to "&TEXT(MAX(MARKET[LOAD DATE]),"mmm yyyy") -> Apr 2025 to Sep 2026 | D3: RECEIVED | E3: =SUM(MARKET[ADVANCE RECEIVED (₹)]) -> 6558710 | G3: AVG DAYS TO RECEIVE | H3: =IFERROR(AVERAGE(MARKET[DAYS TO RECEIVE]),"") -> 7.0625 | J3: Black = calculated, do not type
A4: CUSTOMERS | B4: =SUMPRODUCT((MARKET[CUSTOMER NAME]<>"")/COUNTIF(MARKET[CUSTOMER NAME],MARKET[CUSTOMER NAME]&"")) -> 24 | D4: BALANCE DUE | E4: =SUM(MARKET[BALANCE DUE (₹)]) -> 192280 | G4: POD NOT DONE | H4: =COUNTIF(MARKET[LOAD DATE],">0")-COUNTIF(MARKET[POD STATUS],"DONE") -> 27 | J4: BALANCE DUE = RATE − ADVANCE RECEIVED
A6: S.NO. | B6: LOAD DATE | C6: MONTH | D6: LORRY NO. | E6: CUSTOMER NAME | F6: LOAD FROM | G6: DELIVERY POINT | H6: RATE (₹) | I6: ADVANCE RECEIVED (₹) | J6: BALANCE DUE (₹) | K6: ADVANCE RECEIVED DATE | L6: DAYS TO RECEIVE | M6: POD STATUS | N6: POD REF | O6: REMARKS | P6: POD AS LOGGED
A7: =IF($B7="","",ROW()-6) -> 1 | B7: 45756 | C7: =IF($B7="","",EOMONTH($B7,-1)+1) -> 45748 | D7: JH01KD-6142 | E7: Customer 01 | F7: KRISHNAGIRI | G7: RANCHI | H7: 54450 | I7: 54450 | J7: =IF(OR($H7="",$I7=""),"",$H7-$I7) -> 0 | K7: 45761 | L7: =IF(OR($B7="",$K7=""),"",$K7-$B7) -> 5 | M7: DONE | O7: ALL FREIGHT CLEAR NO DUES | P7: DONE
A8: =IF($B8="","",ROW()-6) -> 2 | B8: 45765 | C8: =IF($B8="","",EOMONTH($B8,-1)+1) -> 45748 | D8: JH01KD-0526 | E8: Customer 02 | F8: HOSKOTE | G8: KOLKATA | H8: 49500 | I8: 49500 | J8: =IF(OR($H8="",$I8=""),"",$H8-$I8) -> 0 | K8: 45768 | L8: =IF(OR($B8="",$K8=""),"",$K8-$B8) -> 3 | M8: DONE | O8: ALL FREIGHT CLEAR NO DUES | P8: DONE
A9: =IF($B9="","",ROW()-6) -> 3 | B9: 45768 | C9: =IF($B9="","",EOMONTH($B9,-1)+1) -> 45748 | D9: JH01KD-2417 | E9: Customer 02 | F9: MALUR | G9: BIHAR SHARIF | H9: 57420 | I9: 57420 | J9: =IF(OR($H9="",$I9=""),"",$H9-$I9) -> 0 | K9: 45772 | L9: =IF(OR($B9="",$K9=""),"",$K9-$B9) -> 4 | M9: DONE | O9: ALL FREIGHT CLEAR NO DUES | P9: DONE
A10: =IF($B10="","",ROW()-6) -> 4 | B10: 45772 | C10: =IF($B10="","",EOMONTH($B10,-1)+1) -> 45748 | D10: JH01KD-6142 | E10: Customer 01 | F10: KRISHNAGIRI | G10: DHULAGARH | H10: 49500 | I10: 49500 | J10: =IF(OR($H10="",$I10=""),"",$H10-$I10) -> 0 | K10: 45776 | L10: =IF(OR($B10="",$K10=""),"",$K10-$B10) -> 4 | M10: DONE | O10: ALL FREIGHT CLEAR NO DUES | P10: DONE
A11: =IF($B11="","",ROW()-6) -> 5 | B11: 45772 | C11: =IF($B11="","",EOMONTH($B11,-1)+1) -> 45748 | D11: JH01KD-0526 | E11: Customer 01 | F11: HOSKOTE | G11: DHULAGARH | H11: 49830 | I11: 49830 | J11: =IF(OR($H11="",$I11=""),"",$H11-$I11) -> 0 | K11: 45778 | L11: =IF(OR($B11="",$K11=""),"",$K11-$B11) -> 6 | M11: DONE | O11: ALL FREIGHT CLEAR NO DUES | P11: DONE
A12: =IF($B12="","",ROW()-6) -> 6 | B12: 45773 | C12: =IF($B12="","",EOMONTH($B12,-1)+1) -> 45748 | D12: JH01KM-8803 | E12: Customer 02 | F12: ATIBALLI+NEELMANGLA | G12: ANGUL ODISSA | H12: 54580 | I12: 54580 | J12: =IF(OR($H12="",$I12=""),"",$H12-$I12) -> 0 | K12: 45775 | L12: =IF(OR($B12="",$K12=""),"",$K12-$B12) -> 2 | M12: DONE | O12: ALL FREIGHT CLEAR NO DUES | P12: DONE
A13: =IF($B13="","",ROW()-6) -> 7 | B13: 45782 | C13: =IF($B13="","",EOMONTH($B13,-1)+1) -> 45778 | D13: JH01KD-0526 | E13: Customer 01 | F13: KRISHNAGIRI | G13: DHULAGARH | H13: 50490 | I13: 50490 | J13: =IF(OR($H13="",$I13=""),"",$H13-$I13) -> 0 | K13: 45792 | L13: =IF(OR($B13="",$K13=""),"",$K13-$B13) -> 10 | M13: DONE | O13: ALL FREIGHT CLEAR NO DUES | P13: DONE
A14: =IF($B14="","",ROW()-6) -> 8 | B14: 45782 | C14: =IF($B14="","",EOMONTH($B14,-1)+1) -> 45778 | D14: JH01KD-6142 | E14: Customer 02 | F14: ATIBALLI+NEELMANGLA | G14: BURGED ODISSA | H14: 56100 | I14: 56100 | J14: =IF(OR($H14="",$I14=""),"",$H14-$I14) -> 0 | K14: 45783 | L14: =IF(OR($B14="",$K14=""),"",$K14-$B14) -> 1 | M14: DONE | O14: ALL FREIGHT CLEAR NO DUES | P14: DONE
A15: =IF($B15="","",ROW()-6) -> 9 | B15: 45784 | C15: =IF($B15="","",EOMONTH($B15,-1)+1) -> 45778 | D15: JH01KD-2417 | E15: Customer 01 | F15: KRISHNAGIRI | G15: RANCHI | H15: 54450 | I15: 54450 | J15: =IF(OR($H15="",$I15=""),"",$H15-$I15) -> 0 | K15: 45784 | L15: =IF(OR($B15="",$K15=""),"",$K15-$B15) -> 0 | M15: DONE | O15: ALL FREIGHT CLEAR NO DUES | P15: DONE
A16: =IF($B16="","",ROW()-6) -> 10 | B16: 45793 | C16: =IF($B16="","",EOMONTH($B16,-1)+1) -> 45778 | D16: JH01KD-2417 | E16: Transporter 29 | F16: NARSAPUR | G16: TIRUPPUR | H16: 9900 | I16: 9900 | J16: =IF(OR($H16="",$I16=""),"",$H16-$I16) -> 0 | K16: 45840 | L16: =IF(OR($B16="",$K16=""),"",$K16-$B16) -> 47 | M16: DONE | O16: ALL FREIGHT CLEAR NO DUES | P16: DONE
A17: =IF($B17="","",ROW()-6) -> 11 | B17: 45796 | C17: =IF($B17="","",EOMONTH($B17,-1)+1) -> 45778 | D17: JH01KD-6142 | E17: Customer 02 | F17: ATIBALLI+JIGNI | G17: SAMBALPUR ODISSA | H17: 56100 | I17: 56100 | J17: =IF(OR($H17="",$I17=""),"",$H17-$I17) -> 0 | K17: 45798 | L17: =IF(OR($B17="",$K17=""),"",$K17-$B17) -> 2 | M17: DONE | O17: ALL FREIGHT CLEAR NO DUES | P17: DONE
A18: =IF($B18="","",ROW()-6) -> 12 | B18: 45813 | C18: =IF($B18="","",EOMONTH($B18,-1)+1) -> 45809 | D18: JH01KD-0526 | E18: Transporter 33 | F18: NARSAPUR | G18: TIRCHY | H18: 14520 | I18: 14520 | J18: =IF(OR($H18="",$I18=""),"",$H18-$I18) -> 0 | K18: 45819 | L18: =IF(OR($B18="",$K18=""),"",$K18-$B18) -> 6 | M18: DONE | O18: ALL FREIGHT CLEAR NO DUES | P18: DONE
... A27: =IF($B27="","",ROW()-6) -> 21 | B27: 45860 | C27: =IF($B27="","",EOMONTH($B27,-1)+1) -> 45839 | D27: JH01KD-2417 | E27: Customer 01 | F27: KRISHNAGIRI | G27: DHULAGARH | H27: 48840 | I27: 48840 | J27: =IF(OR($H27="",$I27=""),"",$H27-$I27) -> 0 | K27: 45863 | L27: =IF(OR($B27="",$K27=""),"",$K27-$B27) -> 3 | M27: DONE | O27: ALL FREIGHT CLEAR NO DUES | P27: DONE
A28: =IF($B28="","",ROW()-6) -> 22 | B28: 45876 | C28: =IF($B28="","",EOMONTH($B28,-1)+1) -> 45870 | D28: JH01KD-6142 | E28: Customer 01 | F28: KRISHNAGIRI | G28: RANCHI | H28: 49500 | I28: 49500 | J28: =IF(OR($H28="",$I28=""),"",$H28-$I28) -> 0 | L28: =IF(OR($B28="",$K28=""),"",$K28-$B28) | M28: DONE | O28: ALL FREIGHT CLEAR NO DUES | P28: DONE
A29: =IF($B29="","",ROW()-6) -> 23 | B29: 45883 | C29: =IF($B29="","",EOMONTH($B29,-1)+1) -> 45870 | D29: JH01KM-8803 | E29: Customer 02 | F29: JIGNI | G29: PATNA | H29: 52800 | I29: 52800 | J29: =IF(OR($H29="",$I29=""),"",$H29-$I29) -> 0 | K29: 45885 | L29: =IF(OR($B29="",$K29=""),"",$K29-$B29) -> 2 | M29: DONE | O29: ALL FREIGHT CLEAR NO DUES | P29: DONE
A30: =IF($B30="","",ROW()-6) -> 24 | B30: 45886 | C30: =IF($B30="","",EOMONTH($B30,-1)+1) -> 45870 | D30: JH01KD-3958 | E30: Customer 02 | F30: JIGNI | G30: PATNA | H30: 52800 | I30: 52800 | J30: =IF(OR($H30="",$I30=""),"",$H30-$I30) -> 0 | K30: 45890 | L30: =IF(OR($B30="",$K30=""),"",$K30-$B30) -> 4 | M30: DONE | O30: ALL FREIGHT CLEAR NO DUES | P30: DONE
A31: =IF($B31="","",ROW()-6) -> 25 | B31: 45887 | C31: =IF($B31="","",EOMONTH($B31,-1)+1) -> 45870 | D31: JH01KD-6142 | E31: Customer 02 | F31: JIGNI | G31: PATNA | H31: 52800 | I31: 5280 | J31: =IF(OR($H31="",$I31=""),"",$H31-$I31) -> 47520 | K31: 45890 | L31: =IF(OR($B31="",$K31=""),"",$K31-$B31) -> 3 | M31: DONE | O31: ALL FREIGHT CLEAR NO DUES | P31: DONE
A32: =IF($B32="","",ROW()-6) -> 26 | B32: 45891 | C32: =IF($B32="","",EOMONTH($B32,-1)+1) -> 45870 | D32: JH01KD-0526 | E32: Customer 02 | F32: DODABALLAPUR | G32: KOLKATA | H32: 48180 | I32: 48180 | J32: =IF(OR($H32="",$I32=""),"",$H32-$I32) -> 0 | L32: =IF(OR($B32="",$K32=""),"",$K32-$B32) | M32: DONE | O32: ALL FREIGHT CLEAR NO DUES | P32: DONE
A33: =IF($B33="","",ROW()-6) -> 27 | B33: 45892 | C33: =IF($B33="","",EOMONTH($B33,-1)+1) -> 45870 | D33: JH01KD2417 | E33: Customer 01 | F33: KRISHNAGIRI | G33: RANCHI | H33: 49170 | I33: 49170 | J33: =IF(OR($H33="",$I33=""),"",$H33-$I33) -> 0 | L33: =IF(OR($B33="",$K33=""),"",$K33-$B33) | M33: DONE | O33: ALL FREIGHT CLEAR NO DUES | P33: DONE
A34: =IF($B34="","",ROW()-6) -> 28 | B34: 45894 | C34: =IF($B34="","",EOMONTH($B34,-1)+1) -> 45870 | D34: BR24XY-8129 | E34: Customer 01 | F34: CHENNAI | G34: KOLKATA | H34: 46860 | I34: 46860 | J34: =IF(OR($H34="",$I34=""),"",$H34-$I34) -> 0 | L34: =IF(OR($B34="",$K34=""),"",$K34-$B34) | M34: DONE | O34: ALL FREIGHT CLEAR NO DUES | P34: DONE
A35: =IF($B35="","",ROW()-6) -> 29 | B35: 45904 | C35: =IF($B35="","",EOMONTH($B35,-1)+1) -> 45901 | D35: JH01KD-3958 | E35: Customer 02 | F35: JIGNI | G35: PATNA | H35: 54120 | I35: 54120 | J35: =IF(OR($H35="",$I35=""),"",$H35-$I35) -> 0 | K35: 46000 | L35: =IF(OR($B35="",$K35=""),"",$K35-$B35) -> 96 | M35: DONE | O35: ALL FREIGHT CLEAR NO DUES | P35: DONE
A36: =IF($B36="","",ROW()-6) -> 30 | B36: 45910 | C36: =IF($B36="","",EOMONTH($B36,-1)+1) -> 45901 | D36: JH01KD-0526 | E36: Customer 02 | F36: JIGNI | G36: PATNA | H36: 54120 | I36: 54120 | J36: =IF(OR($H36="",$I36=""),"",$H36-$I36) -> 0 | L36: =IF(OR($B36="",$K36=""),"",$K36-$B36) | M36: DONE | O36: ALL FREIGHT CLEAR NO DUES | P36: DONE
A37: =IF($B37="","",ROW()-6) -> 31 | B37: 45915 | C37: =IF($B37="","",EOMONTH($B37,-1)+1) -> 45901 | D37: JH01KD-6142 | E37: Customer 01 | F37: NEELMANGLA | G37: KOLKATA | H37: 47520 | I37: 47520 | J37: =IF(OR($H37="",$I37=""),"",$H37-$I37) -> 0 | L37: =IF(OR($B37="",$K37=""),"",$K37-$B37) | M37: DONE | O37: ALL FREIGHT CLEAR NO DUES | P37: DONE
A38: =IF($B38="","",ROW()-6) -> 32 | B38: 45917 | C38: =IF($B38="","",EOMONTH($B38,-1)+1) -> 45901 | D38: JH01KD-3958 | E38: Customer 02 | F38: JIGNI | G38: PATNA | H38: 54120 | I38: 54120 | J38: =IF(OR($H38="",$I38=""),"",$H38-$I38) -> 0 | L38: =IF(OR($B38="",$K38=""),"",$K38-$B38) | M38: DONE | O38: ALL FREIGHT CLEAR NO DUES | P38: DONE
A39: =IF($B39="","",ROW()-6) -> 33 | B39: 45920 | C39: =IF($B39="","",EOMONTH($B39,-1)+1) -> 45901 | D39: BR24XY-8129 | E39: Customer 01 | F39: KRISHNAGIRI | G39: DHULAGARH | H39: 48510 | I39: 48510 | J39: =IF(OR($H39="",$I39=""),"",$H39-$I39) -> 0 | L39: =IF(OR($B39="",$K39=""),"",$K39-$B39) | M39: DONE | O39: ALL FREIGHT CLEAR NO DUES | P39: DONE
A40: =IF($B40="","",ROW()-6) -> 34 | B40: 45926 | C40: =IF($B40="","",EOMONTH($B40,-1)+1) -> 45901 | D40: BR24XY-8129 | E40: BN | F40: KOLKATA | G40: RANCHI | H40: 16500 | I40: 16500 | J40: =IF(OR($H40="",$I40=""),"",$H40-$I40) -> 0 | K40: 45940 | L40: =IF(OR($B40="",$K40=""),"",$K40-$B40) -> 14 | M40: DONE | O40: ALL FREIGHT CLEAR NO DUES | P40: DONE
A41: =IF($B41="","",ROW()-6) -> 35 | B41: 45954 | C41: =IF($B41="","",EOMONTH($B41,-1)+1) -> 45931 | D41: JH01KD-6142 | E41: Customer 02 | F41: JIGNI | G41: BALASORE | H41: 50160 | I41: 50160 | J41: =IF(OR($H41="",$I41=""),"",$H41-$I41) -> 0 | L41: =IF(OR($B41="",$K41=""),"",$K41-$B41) | M41: DONE | O41: ALL FREIGHT CLEAR NO DUES | P41: DONE
A42: =IF($B42="","",ROW()-6) -> 36 | B42: 45958 | C42: =IF($B42="","",EOMONTH($B42,-1)+1) -> 45931 | D42: JH01KD-0526 | E42: Customer 02 | F42: JIGNI | G42: BALASORE | H42: 47520 | I42: 47520 | J42: =IF(OR($H42="",$I42=""),"",$H42-$I42) -> 0 | L42: =IF(OR($B42="",$K42=""),"",$K42-$B42) | M42: DONE | O42: ALL FREIGHT CLEAR NO DUES | P42: DONE
A43: =IF($B43="","",ROW()-6) -> 37 | B43: 45965 | C43: =IF($B43="","",EOMONTH($B43,-1)+1) -> 45962 | D43: JH01KD-2417 | E43: Customer 01 | F43: KRISHNAGIRI | G43: RANCHI | H43: 50160 | I43: 50160 | J43: =IF(OR($H43="",$I43=""),"",$H43-$I43) -> 0 | K43: 45967 | L43: =IF(OR($B43="",$K43=""),"",$K43-$B43) -> 2 | M43: DONE | O43: ALL FREIGHT CLEAR NO DUES | P43: DONE
A44: =IF($B44="","",ROW()-6) -> 38 | B44: 45965 | C44: =IF($B44="","",EOMONTH($B44,-1)+1) -> 45962 | D44: JH01KD-6142 | E44: Customer 01 | F44: KRISHNAGIRI | G44: DHULAGARH | H44: 48840 | I44: 48840 | J44: =IF(OR($H44="",$I44=""),"",$H44-$I44) -> 0 | K44: 45979 | L44: =IF(OR($B44="",$K44=""),"",$K44-$B44) -> 14 | M44: DONE | O44: ALL FREIGHT CLEAR NO DUES | P44: DONE
A45: =IF($B45="","",ROW()-6) -> 39 | B45: 45968 | C45: =IF($B45="","",EOMONTH($B45,-1)+1) -> 45962 | D45: JH01KD-0526 | E45: Customer 02 | F45: HOSUR | G45: KOLKATA | H45: 49500 | I45: 49500 | J45: =IF(OR($H45="",$I45=""),"",$H45-$I45) -> 0 | L45: =IF(OR($B45="",$K45=""),"",$K45-$B45) | M45: DONE | O45: ALL FREIGHT CLEAR NO DUES | P45: DONE
A46: =IF($B46="","",ROW()-6) -> 40 | B46: 45968 | C46: =IF($B46="","",EOMONTH($B46,-1)+1) -> 45962 | D46: JH01KD-3958 | E46: Customer 02 | F46: KR PURAM BNG | G46: DHULAGARH | H46: 49500 | I46: 49500 | J46: =IF(OR($H46="",$I46=""),"",$H46-$I46) -> 0 | L46: =IF(OR($B46="",$K46=""),"",$K46-$B46) | M46: DONE | O46: ALL FREIGHT CLEAR NO DUES | P46: DONE
A47: =IF($B47="","",ROW()-6) -> 41 | B47: 45977 | C47: =IF($B47="","",EOMONTH($B47,-1)+1) -> 45962 | D47: JH01KD-0526 | E47: Customer 08 | F47: BOMMANSANDRA | G47: KOLKATA | H47: 51500 | I47: 51500 | J47: =IF(OR($H47="",$I47=""),"",$H47-$I47) -> 0 | K47: 45979 | L47: =IF(OR($B47="",$K47=""),"",$K47-$B47) -> 2 | M47: DONE | O47: ALL FREIGHT CLEAR NO DUES | P47: DONE
A48: =IF($B48="","",ROW()-6) -> 42 | B48: 45979 | C48: =IF($B48="","",EOMONTH($B48,-1)+1) -> 45962 | D48: JH01KD-3958 | E48: Customer 08 | F48: NEELMANGLA | G48: RANCHI | H48: 55620 | I48: 55620 | J48: =IF(OR($H48="",$I48=""),"",$H48-$I48) -> 0 | K48: 45979 | L48: =IF(OR($B48="",$K48=""),"",$K48-$B48) -> 0 | M48: DONE | O48: ALL FREIGHT CLEAR NO DUES | P48: DONE
A49: =IF($B49="","",ROW()-6) -> 43 | B49: 45979 | C49: =IF($B49="","",EOMONTH($B49,-1)+1) -> 45962 | D49: JH01KM-8803 | E49: Customer 08 | F49: NEELMANGLA | G49: RANCHI | H49: 55620 | I49: 55620 | J49: =IF(OR($H49="",$I49=""),"",$H49-$I49) -> 0 | K49: 45979 | L49: =IF(OR($B49="",$K49=""),"",$K49-$B49) -> 0 | M49: DONE | O49: ALL FREIGHT CLEAR NO DUES | P49: DONE
A50: =IF($B50="","",ROW()-6) -> 44 | B50: 45989 | C50: =IF($B50="","",EOMONTH($B50,-1)+1) -> 45962 | D50: JH01KD-0526 | E50: Customer 08 | F50: HOSKOTE | G50: KOLKATA | H50: 54780 | I50: 54780 | J50: =IF(OR($H50="",$I50=""),"",$H50-$I50) -> 0 | L50: =IF(OR($B50="",$K50=""),"",$K50-$B50) | M50: DONE | O50: ALL FREIGHT CLEAR NO DUES | P50: DONE
A51: =IF($B51="","",ROW()-6) -> 45 | B51: 45991 | C51: =IF($B51="","",EOMONTH($B51,-1)+1) -> 45962 | D51: JH01KD-3958 | E51: Customer 08 | F51: HOSKOTE | G51: KOLKATA | H51: 54780 | I51: 54780 | J51: =IF(OR($H51="",$I51=""),"",$H51-$I51) -> 0 | L51: =IF(OR($B51="",$K51=""),"",$K51-$B51) | M51: DONE | O51: ALL FREIGHT CLEAR NO DUES | P51: DONE
A52: =IF($B52="","",ROW()-6) -> 46 | B52: 45991 | C52: =IF($B52="","",EOMONTH($B52,-1)+1) -> 45962 | D52: JH01KD-2417 | E52: Customer 08 | F52: NEELMANGLA | G52: DHULAGARH | H52: 51480 | I52: 51480 | J52: =IF(OR($H52="",$I52=""),"",$H52-$I52) -> 0 | L52: =IF(OR($B52="",$K52=""),"",$K52-$B52) | M52: DONE | O52: ALL FREIGHT CLEAR NO DUES | P52: DONE
A53: =IF($B53="","",ROW()-6) -> 47 | B53: 46001 | C53: =IF($B53="","",EOMONTH($B53,-1)+1) -> 45992 | D53: JH01KD-2417 | E53: Customer 08 | F53: BMS | G53: RANCHI | H53: 52600 | I53: 52600 | J53: =IF(OR($H53="",$I53=""),"",$H53-$I53) -> 0 | L53: =IF(OR($B53="",$K53=""),"",$K53-$B53) | M53: DONE | O53: ALL FREIGHT CLEAR NO DUES | P53: DONE
A54: =IF($B54="","",ROW()-6) -> 48 | B54: 46024 | C54: =IF($B54="","",EOMONTH($B54,-1)+1) -> 46023 | D54: JH01KD-6142 | E54: Customer 09 | F54: TUMKUR BNG | G54: ODISSA+KOLKATA | H54: 52000 | I54: 44320 | J54: =IF(OR($H54="",$I54=""),"",$H54-$I54) -> 7680 | L54: =IF(OR($B54="",$K54=""),"",$K54-$B54) | M54: DONE | N54: V6903129326 | O54: ALL FREIGHT CLEAR NO DUES | P54: DONE ,V6903129326 | U54: CONDITIONAL FORMATTING
A55: =IF($B55="","",ROW()-6) -> 49 | B55: 46028 | C55: =IF($B55="","",EOMONTH($B55,-1)+1) -> 46023 | D55: JH01KD-6142 | E55: BN | F55: KOLKATA | G55: RANCHI | H55: 16500 | I55: 16500 | J55: =IF(OR($H55="",$I55=""),"",$H55-$I55) -> 0 | K55: 46042 | L55: =IF(OR($B55="",$K55=""),"",$K55-$B55) -> 14 | M55: DONE | N55: BILLNO.234 | O55: ALL FREIGHT CLEAR NO DUES | P55: BILL NO.234
A56: =IF($B56="","",ROW()-6) -> 50 | B56: 46039 | C56: =IF($B56="","",EOMONTH($B56,-1)+1) -> 46023 | D56: JH01KM-8803 | E56: Customer 09 | F56: ATIBALLI+JIGNI | G56: DARBHANGA BIHAR | H56: 51480 | I56: 51480 | J56: =IF(OR($H56="",$I56=""),"",$H56-$I56) -> 0 | K56: 46039 | L56: =IF(OR($B56="",$K56=""),"",$K56-$B56) -> 0 | M56: DONE | N56: V1662352462 | O56: ALL FREIGHT CLEAR NO DUES | P56: DONE,V1662352462
A57: =IF($B57="","",ROW()-6) -> 51 | B57: 46041 | C57: =IF($B57="","",EOMONTH($B57,-1)+1) -> 46023 | D57: JH01KD-0526 | E57: Customer 09 | F57: ATIBALLI | G57: PURNIA BIHAR | H57: 51480 | I57: 51480 | J57: =IF(OR($H57="",$I57=""),"",$H57-$I57) -> 0 | K57: 46041 | L57: =IF(OR($B57="",$K57=""),"",$K57-$B57) -> 0 | M57: DONE | N57: V1662352462 | O57: ALL FREIGHT CLEAR NO DUES | P57: DONE,V1662352462
A58: =IF($B58="","",ROW()-6) -> 52 | B58: 46041 | C58: =IF($B58="","",EOMONTH($B58,-1)+1) -> 46023 | D58: JH01KD-3958 | E58: Customer 09 | F58: JIGNI | G58: PURNIA BIHAR | H58: 50820 | I58: 50820 | J58: =IF(OR($H58="",$I58=""),"",$H58-$I58) -> 0 | K58: 46041 | L58: =IF(OR($B58="",$K58=""),"",$K58-$B58) -> 0 | M58: DONE | N58: V1662352462 | O58: ALL FREIGHT CLEAR NO DUES | P58: DONE,V1662352462
A59: =IF($B59="","",ROW()-6) -> 53 | B59: 46041 | C59: =IF($B59="","",EOMONTH($B59,-1)+1) -> 46023 | D59: JH01KD-2417 | E59: Customer 09 | F59: ATIBALLI+JIGNI | G59: BHAGALPUR | H59: 51480 | I59: 51480 | J59: =IF(OR($H59="",$I59=""),"",$H59-$I59) -> 0 | K59: 46041 | L59: =IF(OR($B59="",$K59=""),"",$K59-$B59) -> 0 | M59: DONE | N59: V1662352462 | O59: ALL FREIGHT CLEAR NO DUES | P59: DONE,V1662352462
A60: =IF($B60="","",ROW()-6) -> 54 | B60: 46068 | C60: =IF($B60="","",EOMONTH($B60,-1)+1) -> 46054 | D60: JH01KD-6142 | E60: Customer 09 | F60: ATIBALLI,BNG | G60: MUJAFFARPUR | H60: 51680 | I60: 51680 | J60: =IF(OR($H60="",$I60=""),"",$H60-$I60) -> 0 | K60: 46071 | L60: =IF(OR($B60="",$K60=""),"",$K60-$B60) -> 3 | M60: DONE | O60: ALL FREIGHT CLEAR NO DUES | P60: DONE
A61: =IF($B61="","",ROW()-6) -> 55 | B61: 46041 | C61: =IF($B61="","",EOMONTH($B61,-1)+1) -> 46023 | D61: JH01KD-0526 | E61: Customer 09 | F61: JIGNI | G61: PATNA | H61: 51410 | I61: 51410 | J61: =IF(OR($H61="",$I61=""),"",$H61-$I61) -> 0 | K61: 46073 | L61: =IF(OR($B61="",$K61=""),"",$K61-$B61) -> 32 | M61: DONE | O61: ALL FREIGHT CLEAR NO DUES | P61: DONE
A62: =IF($B62="","",ROW()-6) -> 56 | B62: 46079 | C62: =IF($B62="","",EOMONTH($B62,-1)+1) -> 46054 | D62: JH01KD-6142 | E62: Customer 09 | F62: JIGNI BNG | G62: KOLKATA | H62: 53920 | I62: 53920 | J62: =IF(OR($H62="",$I62=""),"",$H62-$I62) -> 0 | K62: 46079 | L62: =IF(OR($B62="",$K62=""),"",$K62-$B62) -> 0 | M62: DONE | O62: ALL FREIGHT CLEAR NO DUES | P62: DONE
A63: =IF($B63="","",ROW()-6) -> 57 | B63: 46084 | C63: =IF($B63="","",EOMONTH($B63,-1)+1) -> 46082 | D63: JH01KD-6142 | E63: BN | F63: KOLKATA | G63: RANCHI | H63: 9900 | I63: 9900 | J63: =IF(OR($H63="",$I63=""),"",$H63-$I63) -> 0 | K63: 46097 | L63: =IF(OR($B63="",$K63=""),"",$K63-$B63) -> 13 | M63: DONE | N63: BILLNO.316 | O63: ALL FREIGHT CLEAR NO DUES | P63: BILLNO.316
A64: =IF($B64="","",ROW()-6) -> 58 | B64: 46092 | C64: =IF($B64="","",EOMONTH($B64,-1)+1) -> 46082 | D64: JH01KD-6142 | E64: Customer 09 | F64: SOUKIYA BNG | G64: KOLKATA | H64: 50490 | I64: 50490 | J64: =IF(OR($H64="",$I64=""),"",$H64-$I64) -> 0 | K64: 46094 | L64: =IF(OR($B64="",$K64=""),"",$K64-$B64) -> 2 | M64: DONE | O64: ALL FREIGHT CLEAR NO DUES | P64: DONE
A65: =IF($B65="","",ROW()-6) -> 59 | B65: 46096 | C65: =IF($B65="","",EOMONTH($B65,-1)+1) -> 46082 | D65: JH01KD-3958 | E65: Customer 09 | F65: JIGNI BNG | G65: SAMBALPUR ODISSA | H65: 46200 | I65: 46200 | J65: =IF(OR($H65="",$I65=""),"",$H65-$I65) -> 0 | K65: 46099 | L65: =IF(OR($B65="",$K65=""),"",$K65-$B65) -> 3 | M65: DONE | O65: ALL FREIGHT CLEAR NO DUES | P65: DONE
A66: =IF($B66="","",ROW()-6) -> 60 | B66: 46101 | C66: =IF($B66="","",EOMONTH($B66,-1)+1) -> 46082 | D66: JH01KD-2417 | E66: Customer 10 | F66: JIGNI BNG | G66: KOLKATA | H66: 50120 | I66: 50120 | J66: =IF(OR($H66="",$I66=""),"",$H66-$I66) -> 0 | K66: 46102 | L66: =IF(OR($B66="",$K66=""),"",$K66-$B66) -> 1 | M66: DONE | O66: ALL FREIGHT CLEAR NO DUES | P66: DONE
A67: =IF($B67="","",ROW()-6) -> 61 | B67: 46102 | C67: =IF($B67="","",EOMONTH($B67,-1)+1) -> 46082 | D67: JH01KD-0526 | E67: Customer 09 | F67: JIGNI BNG | G67: PATNA | H67: 54780 | I67: 54780 | J67: =IF(OR($H67="",$I67=""),"",$H67-$I67) -> 0 | K67: 46103 | L67: =IF(OR($B67="",$K67=""),"",$K67-$B67) -> 1 | M67: DONE | O67: ALL FREIGHT CLEAR NO DUES | P67: DONE
A68: =IF($B68="","",ROW()-6) -> 62 | B68: 46102 | C68: =IF($B68="","",EOMONTH($B68,-1)+1) -> 46082 | D68: JH01KD-6142 | E68: Customer 10 | F68: NEELMANGLA | G68: BHUBNESHWAR | H68: 43760 | I68: 43760 | J68: =IF(OR($H68="",$I68=""),"",$H68-$I68) -> 0 | K68: 46103 | L68: =IF(OR($B68="",$K68=""),"",$K68-$B68) -> 1 | M68: DONE | O68: ALL FREIGHT CLEAR NO DUES | P68: DONE
A69: =IF($B69="","",ROW()-6) -> 63 | B69: 46104 | C69: =IF($B69="","",EOMONTH($B69,-1)+1) -> 46082 | D69: JH01KD-6142 | E69: Customer 10 | F69: PURI ODISSA | G69: RANCHI | H69: 13980 | I69: 13980 | J69: =IF(OR($H69="",$I69=""),"",$H69-$I69) -> 0 | L69: =IF(OR($B69="",$K69=""),"",$K69-$B69) | M69: DONE | O69: ALL FREIGHT CLEAR NO DUES | P69: DONE
A70: =IF($B70="","",ROW()-6) -> 64 | B70: 46105 | C70: =IF($B70="","",EOMONTH($B70,-1)+1) -> 46082 | D70: JH01KD-2417 | E70: Customer 10 | F70: KOLKATA,2 | G70: RANCHI | H70: 13970 | I70: 13970 | J70: =IF(OR($H70="",$I70=""),"",$H70-$I70) -> 0 | K70: 46105 | L70: =IF(OR($B70="",$K70=""),"",$K70-$B70) -> 0 | M70: DONE | O70: ALL FREIGHT CLEAR NO DUES | P70: DONE
A71: =IF($B71="","",ROW()-6) -> 65 | B71: 46107 | C71: =IF($B71="","",EOMONTH($B71,-1)+1) -> 46082 | D71: JH01KD-0526 | E71: Customer 10 | F71: PATNA,3 | G71: KOLKATA | H71: 13970 | I71: 13970 | J71: =IF(OR($H71="",$I71=""),"",$H71-$I71) -> 0 | K71: 46107 | L71: =IF(OR($B71="",$K71=""),"",$K71-$B71) -> 0 | M71: DONE | O71: ALL FREIGHT CLEAR NO DUES | P71: DONE
A72: =IF($B72="","",ROW()-6) -> 66 | B72: 46107 | C72: =IF($B72="","",EOMONTH($B72,-1)+1) -> 46082 | D72: JH01KD-6142 | E72: Customer 10 | F72: RANCHI | G72: SAMBALPUR ODISSA | H72: 12340 | I72: 12340 | J72: =IF(OR($H72="",$I72=""),"",$H72-$I72) -> 0 | L72: =IF(OR($B72="",$K72=""),"",$K72-$B72) | M72: DONE | O72: ALL FREIGHT CLEAR NO DUES | P72: DONE
A73: =IF($B73="","",ROW()-6) -> 67 | B73: 46108 | C73: =IF($B73="","",EOMONTH($B73,-1)+1) -> 46082 | D73: JH01KM-8803 | E73: Customer 09 | F73: JIGNI BNG | G73: PATNA | H73: 54780 | I73: 54780 | J73: =IF(OR($H73="",$I73=""),"",$H73-$I73) -> 0 | K73: 46108 | L73: =IF(OR($B73="",$K73=""),"",$K73-$B73) -> 0 | M73: DONE | O73: ALL FREIGHT CLEAR NO DUES | P73: DONE
A74: =IF($B74="","",ROW()-6) -> 68 | B74: 46114 | C74: =IF($B74="","",EOMONTH($B74,-1)+1) -> 46113 | D74: JH01KM-8803 | E74: Customer 10 | F74: HAZIPUR BIHAR | G74: RAMGARH RANCHI | H74: 11150 | I74: 11150 | J74: =IF(OR($H74="",$I74=""),"",$H74-$I74) -> 0 | L74: =IF(OR($B74="",$K74=""),"",$K74-$B74) | M74: DONE | O74: ALL FREIGHT CLEAR NO DUES | P74: DONE
A75: =IF($B75="","",ROW()-6) -> 69 | B75: 46115 | C75: =IF($B75="","",EOMONTH($B75,-1)+1) -> 46113 | D75: JH01KR-1695 | E75: Customer 10 | F75: NAGRI RANCHI | G75: KHARAGPUR | H75: 9510 | I75: 9510 | J75: =IF(OR($H75="",$I75=""),"",$H75-$I75) -> 0 | K75: 46115 | L75: =IF(OR($B75="",$K75=""),"",$K75-$B75) -> 0 | M75: DONE | O75: ALL FREIGHT CLEAR NO DUES | P75: DONE
A76: =IF($B76="","",ROW()-6) -> 70 | B76: 46115 | C76: =IF($B76="","",EOMONTH($B76,-1)+1) -> 46113 | D76: JH01KD-0526 | E76: Customer 09 | F76: JIGNI+ATIBALLI BNG | G76: BHAGALPUR | H76: 56100 | I76: 56100 | J76: =IF(OR($H76="",$I76=""),"",$H76-$I76) -> 0 | L76: =IF(OR($B76="",$K76=""),"",$K76-$B76) | M76: DONE | O76: ALL FREIGHT CLEAR NO DUES | P76: DONE
A77: =IF($B77="","",ROW()-6) -> 71 | B77: 46116 | C77: =IF($B77="","",EOMONTH($B77,-1)+1) -> 46113 | D77: JH01KR-1695 | E77: BN | F77: KOLKATA | G77: RANCHI | H77: 16500 | I77: 16500 | J77: =IF(OR($H77="",$I77=""),"",$H77-$I77) -> 0 | L77: =IF(OR($B77="",$K77=""),"",$K77-$B77) | M77: DONE | O77: ALL FREIGHT CLEAR NO DUES | P77: DONE
A78: =IF($B78="","",ROW()-6) -> 72 | B78: 46117 | C78: =IF($B78="","",EOMONTH($B78,-1)+1) -> 46113 | D78: JH01KD-6142 | E78: Customer 10 | F78: RANCHI | G78: PATNA | H78: 11220 | I78: 11220 | J78: =IF(OR($H78="",$I78=""),"",$H78-$I78) -> 0 | K78: 46118 | L78: =IF(OR($B78="",$K78=""),"",$K78-$B78) -> 1 | M78: DONE | O78: ALL FREIGHT CLEAR NO DUES | P78: DONE
A79: =IF($B79="","",ROW()-6) -> 73 | B79: 46118 | C79: =IF($B79="","",EOMONTH($B79,-1)+1) -> 46113 | D79: JH01KM-8803 | E79: Customer 10 | F79: RANCHI | G79: SALAP KOLKATA | H79: 9900 | I79: 9900 | J79: =IF(OR($H79="",$I79=""),"",$H79-$I79) -> 0 | K79: 46118 | L79: =IF(OR($B79="",$K79=""),"",$K79-$B79) -> 0 | M79: DONE | O79: ALL FREIGHT CLEAR NO DUES | P79: DONE
A80: =IF($B80="","",ROW()-6) -> 74 | B80: 46119 | C80: =IF($B80="","",EOMONTH($B80,-1)+1) -> 46113 | D80: JH01KD-0526 | E80: Customer 10 | F80: PATNA HAZIPUR | G80: SIMDEGA | H80: 10560 | I80: 10560 | J80: =IF(OR($H80="",$I80=""),"",$H80-$I80) -> 0 | K80: 46121 | L80: =IF(OR($B80="",$K80=""),"",$K80-$B80) -> 2 | M80: DONE | O80: ALL FREIGHT CLEAR NO DUES | P80: DONE
A81: =IF($B81="","",ROW()-6) -> 75 | B81: 46120 | C81: =IF($B81="","",EOMONTH($B81,-1)+1) -> 46113 | D81: JH01KD-2417 | E81: Customer 10 | F81: RANCHI | G81: CUTTACK | H81: 13660 | I81: 13660 | J81: =IF(OR($H81="",$I81=""),"",$H81-$I81) -> 0 | K81: 46121 | L81: =IF(OR($B81="",$K81=""),"",$K81-$B81) -> 1 | M81: DONE | O81: ALL FREIGHT CLEAR NO DUES | P81: DONE
A82: =IF($B82="","",ROW()-6) -> 76 | B82: 46121 | C82: =IF($B82="","",EOMONTH($B82,-1)+1) -> 46113 | D82: JH01KD-3958 | E82: Customer 10 | F82: RANCHI | G82: KOLKATA | H82: 10690 | I82: 10690 | J82: =IF(OR($H82="",$I82=""),"",$H82-$I82) -> 0 | K82: 46121 | L82: =IF(OR($B82="",$K82=""),"",$K82-$B82) -> 0 | M82: DONE | O82: ALL FREIGHT CLEAR NO DUES | P82: DONE
A83: =IF($B83="","",ROW()-6) -> 77 | B83: 46121 | C83: =IF($B83="","",EOMONTH($B83,-1)+1) -> 46113 | D83: JH01KM-8803 | E83: Customer 10+ 05DAYS HALTING 7518 | F83: KOLKATA | G83: ODISSA | H83: 18760 | I83: 18760 | J83: =IF(OR($H83="",$I83=""),"",$H83-$I83) -> 0 | K83: 46123 | L83: =IF(OR($B83="",$K83=""),"",$K83-$B83) -> 2 | M83: DONE | O83: ALL FREIGHT CLEAR NO DUES | P83: DONE
A84: =IF($B84="","",ROW()-6) -> 78 | B84: 46122 | C84: =IF($B84="","",EOMONTH($B84,-1)+1) -> 46113 | D84: JH01KD-2417 | E84: Customer 10 | F84: CUTTACK | G84: BANGLORE | H84: 18150 | I84: 20200 | J84: =IF(OR($H84="",$I84=""),"",$H84-$I84) -> -2050 | K84: 46123 | L84: =IF(OR($B84="",$K84=""),"",$K84-$B84) -> 1 | M84: DONE | O84: ALL FREIGHT CLEAR NO DUES | P84: DONE
A85: =IF($B85="","",ROW()-6) -> 79 | B85: 46122 | C85: =IF($B85="","",EOMONTH($B85,-1)+1) -> 46113 | D85: JH01KD-6142 | E85: Customer 10 | F85: PATNA | G85: CUTTACK | H85: 17160 | I85: 17160 | J85: =IF(OR($H85="",$I85=""),"",$H85-$I85) -> 0 | K85: 46122 | L85: =IF(OR($B85="",$K85=""),"",$K85-$B85) -> 0 | M85: DONE | O85: ALL FREIGHT CLEAR NO DUES | P85: DONE
A86: =IF($B86="","",ROW()-6) -> 80 | B86: 46123 | C86: =IF($B86="","",EOMONTH($B86,-1)+1) -> 46113 | D86: JH01KD-0526 | E86: Transporter 41 | F86: JAMSHEDPUR | G86: CHENNAI | H86: 24140 | I86: 24140 | J86: =IF(OR($H86="",$I86=""),"",$H86-$I86) -> 0 | K86: 46126 | L86: =IF(OR($B86="",$K86=""),"",$K86-$B86) -> 3 | M86: DONE | O86: ALL FREIGHT CLEAR NO DUES | P86: DONE
A87: =IF($B87="","",ROW()-6) -> 81 | B87: 46125 | C87: =IF($B87="","",EOMONTH($B87,-1)+1) -> 46113 | D87: JH01KD-7230 | E87: Transporter 41 | F87: JAMSHEDPUR | G87: CHENNAI | H87: 25180 | I87: 25180 | J87: =IF(OR($H87="",$I87=""),"",$H87-$I87) -> 0 | K87: 46126 | L87: =IF(OR($B87="",$K87=""),"",$K87-$B87) -> 1 | M87: DONE | O87: ALL FREIGHT CLEAR NO DUES | P87: DONE
A88: =IF($B88="","",ROW()-6) -> 82 | B88: 46125 | C88: =IF($B88="","",EOMONTH($B88,-1)+1) -> 46113 | D88: JH01KD-3958 | E88: Customer 12 | F88: KOLKATA | G88: BANGLORE | H88: 28380 | I88: 28380 | J88: =IF(OR($H88="",$I88=""),"",$H88-$I88) -> 0 | L88: =IF(OR($B88="",$K88=""),"",$K88-$B88) | M88: DONE | O88: ALL FREIGHT CLEAR NO DUES | P88: DONE
A89: =IF($B89="","",ROW()-6) -> 83 | B89: 46125 | C89: =IF($B89="","",EOMONTH($B89,-1)+1) -> 46113 | D89: JH01KD-6142 | E89: Customer 10 | F89: ODISSA | G89: HOSUR | H89: 25090 | I89: 25090 | J89: =IF(OR($H89="",$I89=""),"",$H89-$I89) -> 0 | L89: =IF(OR($B89="",$K89=""),"",$K89-$B89) | M89: DONE | O89: ALL FREIGHT CLEAR NO DUES | P89: DONE
A90: =IF($B90="","",ROW()-6) -> 84 | B90: 46126 | C90: =IF($B90="","",EOMONTH($B90,-1)+1) -> 46113 | D90: JH01KR-9064 | E90: Customer 10 | F90: JAMSHEDPUR | G90: ANGUL ODISSA | H90: 13330 | I90: 13330 | J90: =IF(OR($H90="",$I90=""),"",$H90-$I90) -> 0 | L90: =IF(OR($B90="",$K90=""),"",$K90-$B90) | M90: DONE | O90: ALL FREIGHT CLEAR NO DUES | P90: DONE
A91: =IF($B91="","",ROW()-6) -> 85 | B91: 46128 | C91: =IF($B91="","",EOMONTH($B91,-1)+1) -> 46113 | D91: JH01KD-0526 | E91: Customer 09 | F91: CHENNAI | G91: PATNA | H91: 58340 | I91: 58340 | J91: =IF(OR($H91="",$I91=""),"",$H91-$I91) -> 0 | L91: =IF(OR($B91="",$K91=""),"",$K91-$B91) | M91: DONE | O91: ALL FREIGHT CLEAR NO DUES | P91: DONE
A92: =IF($B92="","",ROW()-6) -> 86 | B92: 46129 | C92: =IF($B92="","",EOMONTH($B92,-1)+1) -> 46113 | D92: JH01KR-5582 | E92: Customer 09 | F92: JIGNI BNG | G92: PATNA | H92: 59530 | I92: 59530 | J92: =IF(OR($H92="",$I92=""),"",$H92-$I92) -> 0 | L92: =IF(OR($B92="",$K92=""),"",$K92-$B92) | M92: DONE | O92: ALL FREIGHT CLEAR NO DUES | P92: DONE
A93: =IF($B93="","",ROW()-6) -> 87 | B93: 46129 | C93: =IF($B93="","",EOMONTH($B93,-1)+1) -> 46113 | D93: JH01KR-7230 | E93: Customer 10 | F93: CHENNAI | G93: PATNA | H93: 64020 | I93: 64020 | J93: =IF(OR($H93="",$I93=""),"",$H93-$I93) -> 0 | L93: =IF(OR($B93="",$K93=""),"",$K93-$B93) | M93: DONE | O93: ALL FREIGHT CLEAR NO DUES | P93: DONE
A94: =IF($B94="","",ROW()-6) -> 88 | B94: 46131 | C94: =IF($B94="","",EOMONTH($B94,-1)+1) -> 46113 | D94: JH01KM-8803 | E94: Customer 10 | F94: ODISSA | G94: HOSUR | H94: 26910 | I94: 26910 | J94: =IF(OR($H94="",$I94=""),"",$H94-$I94) -> 0 | L94: =IF(OR($B94="",$K94=""),"",$K94-$B94) | M94: DONE | O94: ALL FREIGHT CLEAR NO DUES | P94: DONE
A95: =IF($B95="","",ROW()-6) -> 89 | B95: 46132 | C95: =IF($B95="","",EOMONTH($B95,-1)+1) -> 46113 | D95: JH01KR-9064 | E95: Customer 13 | F95: BALASORE | G95: NAMAKKAL ,TN. | H95: 29700 | I95: 29700 | J95: =IF(OR($H95="",$I95=""),"",$H95-$I95) -> 0 | L95: =IF(OR($B95="",$K95=""),"",$K95-$B95) | M95: DONE | O95: ALL FREIGHT CLEAR NO DUES | P95: DONE
A96: =IF($B96="","",ROW()-6) -> 90 | B96: 46132 | C96: =IF($B96="","",EOMONTH($B96,-1)+1) -> 46113 | D96: JH01KD-3958 | E96: Customer 10 | F96: BANGLORE | G96: DANKUNI | H96: 50160 | I96: 50160 | J96: =IF(OR($H96="",$I96=""),"",$H96-$I96) -> 0 | L96: =IF(OR($B96="",$K96=""),"",$K96-$B96) | M96: DONE | O96: ALL FREIGHT CLEAR NO DUES | P96: DONE
A97: =IF($B97="","",ROW()-6) -> 91 | B97: 46133 | C97: =IF($B97="","",EOMONTH($B97,-1)+1) -> 46113 | D97: JH01KD-0526 | E97: Customer 14 | F97: PATNA | G97: BOKARO | H97: 9240 | I97: 8380 | J97: =IF(OR($H97="",$I97=""),"",$H97-$I97) -> 860 | L97: =IF(OR($B97="",$K97=""),"",$K97-$B97) | M97: DONE | O97: BALANCE PENDING | P97: DONE
A98: =IF($B98="","",ROW()-6) -> 92 | B98: 46134 | C98: =IF($B98="","",EOMONTH($B98,-1)+1) -> 46113 | D98: JH01KR-5582 | E98: Customer 14 | F98: PATNA | G98: JAMSHEDPUR | H98: 10560 | I98: 9700 | J98: =IF(OR($H98="",$I98=""),"",$H98-$I98) -> 860 | L98: =IF(OR($B98="",$K98=""),"",$K98-$B98) | M98: DONE | O98: BALANCE PENDING | P98: DONE
A99: =IF($B99="","",ROW()-6) -> 93 | B99: 46136 | C99: =IF($B99="","",EOMONTH($B99,-1)+1) -> 46113 | D99: JH01KD-2417 | E99: Customer 10 | F99: HOSUR | G99: BAGNAN KOLKATA | H99: 51810 | I99: 51810 | J99: =IF(OR($H99="",$I99=""),"",$H99-$I99) -> 0 | L99: =IF(OR($B99="",$K99=""),"",$K99-$B99) | M99: DONE | O99: ALL FREIGHT CLEAR NO DUES | P99: DONE
A100: =IF($B100="","",ROW()-6) -> 94 | B100: 46137 | C100: =IF($B100="","",EOMONTH($B100,-1)+1) -> 46113 | D100: JH01KD-6142 | E100: Customer 10 | F100: HOSKOTE | G100: BAGNAN KOLKATA | H100: 51810 | I100: 51810 | J100: =IF(OR($H100="",$I100=""),"",$H100-$I100) -> 0 | L100: =IF(OR($B100="",$K100=""),"",$K100-$B100) | M100: DONE | O100: ALL FREIGHT CLEAR NO DUES | P100: DONE
A101: =IF($B101="","",ROW()-6) -> 95 | B101: 46140 | C101: =IF($B101="","",EOMONTH($B101,-1)+1) -> 46113 | D101: JH01KR-7230 | E101: Customer 10 | F101: BANGLORE | G101: GUWAHATI | H101: 73290 | I101: 73290 | J101: =IF(OR($H101="",$I101=""),"",$H101-$I101) -> 0 | K101: 46141 | L101: =IF(OR($B101="",$K101=""),"",$K101-$B101) -> 1 | M101: DONE | O101: ALL FREIGHT CLEAR NO DUES | P101: DONE
A102: =IF($B102="","",ROW()-6) -> 96 | B102: 46141 | C102: =IF($B102="","",EOMONTH($B102,-1)+1) -> 46113 | D102: JH01KR-5582 | E102: Customer 10 | F102: BANGLORE | G102: BALASORE | H102: 50890 | I102: 50890 | J102: =IF(OR($H102="",$I102=""),"",$H102-$I102) -> 0 | K102: 46142 | L102: =IF(OR($B102="",$K102=""),"",$K102-$B102) -> 1 | M102: DONE | O102: ALL FREIGHT CLEAR NO DUES | P102: DONE
A103: =IF($B103="","",ROW()-6) -> 97 | B103: 46141 | C103: =IF($B103="","",EOMONTH($B103,-1)+1) -> 46113 | D103: JH01KR-1695 | E103: Transporter 41 | F103: JAMSHEDPUR | G103: DHARWAD | H103: 34980 | I103: 34980 | J103: =IF(OR($H103="",$I103=""),"",$H103-$I103) -> 0 | L103: =IF(OR($B103="",$K103=""),"",$K103-$B103) | M103: DONE | O103: ALL FREIGHT CLEAR NO DUES | P103: DONE
A104: =IF($B104="","",ROW()-6) -> 98 | B104: 46147 | C104: =IF($B104="","",EOMONTH($B104,-1)+1) -> 46143 | D104: JH01KR-5582 | E104: Customer 10 | F104: JAJPUR ODISSA | G104: HYDERABAD | H104: 16500 | I104: 16500 | J104: =IF(OR($H104="",$I104=""),"",$H104-$I104) -> 0 | K104: 46148 | L104: =IF(OR($B104="",$K104=""),"",$K104-$B104) -> 1 | M104: DONE | O104: ALL FREIGHT CLEAR NO DUES | P104: DONE
A105: =IF($B105="","",ROW()-6) -> 99 | B105: 46147 | C105: =IF($B105="","",EOMONTH($B105,-1)+1) -> 46143 | D105: JH01KR-7230 | E105: Customer 10 | F105: GUWAHATI | G105: PAKUR JHARKHAND | H105: 14520 | I105: 14520 | J105: =IF(OR($H105="",$I105=""),"",$H105-$I105) -> 0 | K105: 46148 | L105: =IF(OR($B105="",$K105=""),"",$K105-$B105) -> 1 | M105: DONE | O105: ALL FREIGHT CLEAR NO DUES | P105: DONE
A106: =IF($B106="","",ROW()-6) -> 100 | B106: 46147 | C106: =IF($B106="","",EOMONTH($B106,-1)+1) -> 46143 | D106: JH01KR-1695 | E106: Customer 09 | F106: DHARWAD GOA | G106: BANGLORE | H106: 21450 | I106: 21450 | J106: =IF(OR($H106="",$I106=""),"",$H106-$I106) -> 0 | K106: 46148 | L106: =IF(OR($B106="",$K106=""),"",$K106-$B106) -> 1 | M106: DONE | O106: ALL FREIGHT CLEAR NO DUES | P106: DONE
A107: =IF($B107="","",ROW()-6) -> 101 | B107: 46147 | C107: =IF($B107="","",EOMONTH($B107,-1)+1) -> 46143 | D107: JH01KD-0526 | E107: Transporter 41 | F107: JAMSHEDPUR | G107: MYSORE | H107: 29240 | I107: 29240 | J107: =IF(OR($H107="",$I107=""),"",$H107-$I107) -> 0 | L107: =IF(OR($B107="",$K107=""),"",$K107-$B107) | M107: DONE | O107: ALL FREIGHT CLEAR NO DUES | P107: DONE
A108: =IF($B108="","",ROW()-6) -> 102 | B108: 46150 | C108: =IF($B108="","",EOMONTH($B108,-1)+1) -> 46143 | D108: JH01KR-7230 | E108: Customer 10 | F108: KHARAGPUR | G108: BANGLORE | H108: 27520 | I108: 27520 | J108: =IF(OR($H108="",$I108=""),"",$H108-$I108) -> 0 | L108: =IF(OR($B108="",$K108=""),"",$K108-$B108) | M108: DONE | O108: ALL FREIGHT CLEAR NO DUES | P108: DONE
A109: =IF($B109="","",ROW()-6) -> 103 | B109: 46150 | C109: =IF($B109="","",EOMONTH($B109,-1)+1) -> 46143 | D109: JH01KR-5582 | E109: Customer 10 | F109: HYDERABAD | G109: BANGLORE | H109: 17400 | I109: 17400 | J109: =IF(OR($H109="",$I109=""),"",$H109-$I109) -> 0 | L109: =IF(OR($B109="",$K109=""),"",$K109-$B109) | M109: DONE | O109: ALL FREIGHT CLEAR NO DUES | P109: DONE
...

Sheet Monthly Sale
A1: Year | B1: Month | C1: Auburn Sale | D1: Market Sale | E1: Total Sale
A2: 2024 | B2: May | C2: 533290 | D2: - | E2: 533290
A3: 2024 | B3: June | C3: 1108630 | D3: - | E3: 1108630
A4: 2024 | B4: July | C4: 1799760 | D4: - | E4: 1799760 | I4: =C13+D13 -> 3179890
A5: 2024 | B5: August | C5: 2398070 | D5: - | E5: 2398070
A6: 2024 | B6: September | C6: 2439320 | D6: - | E6: 2439320
A7: 2024 | B7: October | C7: 2415418 | D7: - | E7: 2415418
A8: 2024 | B8: November | C8: 2566952 | D8: - | E8: 2566952
A9: 2024 | B9: December | C9: 3341365 | D9: - | E9: 3341365
A10: 2025 | B10: January | C10: 3913110 | D10: - | E10: 3913110
A11: 2025 | B11: February | C11: 3083750 | D11: - | E11: 3083750
A12: 2025 | B12: March | C12: 2744440 | D12: - | E12: 2744440
A13: 2025 | B13: April | C13: 2864610 | D13: 315280 | E13: 2611317
A14: 2025 | B14: May | C14: 2298580 | D14: 227040 | E14: 2525620
A15: 2025 | B15: June | C15: 2801910 | D15: 141900 | E15: 2943810
A16: 2025 | B16: July | C16: 2780820 | D16: 274890 | E16: 3055710
A17: 2025 | B17: August | C17: 2169720 | D17: 352110 | E17: 2521830
A18: 2025 | B18: September | C18: 2798000 | D18: 274890 | E18: 3072863
A19: 2025 | B19: October | C19: 2172550 | D19: 97680 | E19: 2270230
A20: 2025 | B20: November | C20: 2473630 | D20: 521780 | E20: 2995410
A21: 2025 | B21: December | C21: 2612615 | D21: 52600 | E21: 2665215
A22: 2026 | B22: January | C22: 2164039 | D22: 376848 | E22: 2540887
A23: 2026 | B23: February | C23: 2255700 | D23: 53922 | E23: 2309622
A24: 2026 | B24: March | C24: 1857550 | D24: 364290 | E24: 2221840
... A29: 2026 | B29: August | C29: 4109890 | D29: 497880 | E29: 4595108

Sheet MONTHLY SALE CLEAN
A1: MONTHLY SALE — BN LOGISTICS
A2: Auburn figures come from AUBURN LOAD CLEAN, market figures from MARKET LOAD CLEAN — all SUMIFS by month.
A3: MONTH | B3: AUBURN LOADS | C3: AUBURN BILLED (₹) | D3: AUBURN LORRY COST (₹) | E3: AUBURN MARGIN (₹) | F3: AUBURN MARGIN % | G3: MARKET LOADS | H3: MARKET SALE (₹) | I3: TOTAL SALE (₹)
A4: =DATE(2024,5,1) -> 45413 | B4: =COUNTIFS(AUBURN[MONTH],$A4) -> 12 | C4: =SUMIFS(AUBURN[BILLING RATE (₹)],AUBURN[MONTH],$A4) -> 533290 | D4: =SUMIFS(AUBURN[LORRY RATE (₹)],AUBURN[MONTH],$A4) -> 412770 | E4: =$C4-$D4 -> 120520 | F4: =IFERROR($E4/$C4,"") -> 0.22599336 | G4: =COUNTIFS(MARKET[MONTH],$A4) -> 0 | H4: =SUMIFS(MARKET[RATE (₹)],MARKET[MONTH],$A4) -> 0 | I4: =$C4+$H4 -> 533290
A5: =EOMONTH(A4,0)+1 -> 45444 | B5: =COUNTIFS(AUBURN[MONTH],$A5) -> 20 | C5: =SUMIFS(AUBURN[BILLING RATE (₹)],AUBURN[MONTH],$A5) -> 1108630 | D5: =SUMIFS(AUBURN[LORRY RATE (₹)],AUBURN[MONTH],$A5) -> 836590 | E5: =$C5-$D5 -> 272040 | F5: =IFERROR($E5/$C5,"") -> 0.24538394 | G5: =COUNTIFS(MARKET[MONTH],$A5) -> 0 | H5: =SUMIFS(MARKET[RATE (₹)],MARKET[MONTH],$A5) -> 0 | I5: =$C5+$H5 -> 1108630
A6: =EOMONTH(A5,0)+1 -> 45474 | B6: =COUNTIFS(AUBURN[MONTH],$A6) -> 33 | C6: =SUMIFS(AUBURN[BILLING RATE (₹)],AUBURN[MONTH],$A6) -> 1799760 | D6: =SUMIFS(AUBURN[LORRY RATE (₹)],AUBURN[MONTH],$A6) -> 1236520 | E6: =$C6-$D6 -> 563240 | F6: =IFERROR($E6/$C6,"") -> 0.31295284 | G6: =COUNTIFS(MARKET[MONTH],$A6) -> 0 | H6: =SUMIFS(MARKET[RATE (₹)],MARKET[MONTH],$A6) -> 0 | I6: =$C6+$H6 -> 1799760
A7: =EOMONTH(A6,0)+1 -> 45505 | B7: =COUNTIFS(AUBURN[MONTH],$A7) -> 36 | C7: =SUMIFS(AUBURN[BILLING RATE (₹)],AUBURN[MONTH],$A7) -> 2398070 | D7: =SUMIFS(AUBURN[LORRY RATE (₹)],AUBURN[MONTH],$A7) -> 1653210 | E7: =$C7-$D7 -> 744860 | F7: =IFERROR($E7/$C7,"") -> 0.31060811 | G7: =COUNTIFS(MARKET[MONTH],$A7) -> 0 | H7: =SUMIFS(MARKET[RATE (₹)],MARKET[MONTH],$A7) -> 0 | I7: =$C7+$H7 -> 2398070
A8: =EOMONTH(A7,0)+1 -> 45536 | B8: =COUNTIFS(AUBURN[MONTH],$A8) -> 42 | C8: =SUMIFS(AUBURN[BILLING RATE (₹)],AUBURN[MONTH],$A8) -> 2439320 | D8: =SUMIFS(AUBURN[LORRY RATE (₹)],AUBURN[MONTH],$A8) -> 1656270 | E8: =$C8-$D8 -> 783050 | F8: =IFERROR($E8/$C8,"") -> 0.32101159 | G8: =COUNTIFS(MARKET[MONTH],$A8) -> 0 | H8: =SUMIFS(MARKET[RATE (₹)],MARKET[MONTH],$A8) -> 0 | I8: =$C8+$H8 -> 2439320
A9: =EOMONTH(A8,0)+1 -> 45566 | B9: =COUNTIFS(AUBURN[MONTH],$A9) -> 46 | C9: =SUMIFS(AUBURN[BILLING RATE (₹)],AUBURN[MONTH],$A9) -> 2489130 | D9: =SUMIFS(AUBURN[LORRY RATE (₹)],AUBURN[MONTH],$A9) -> 1719650 | E9: =$C9-$D9 -> 769480 | F9: =IFERROR($E9/$C9,"") -> 0.30913612 | G9: =COUNTIFS(MARKET[MONTH],$A9) -> 0 | H9: =SUMIFS(MARKET[RATE (₹)],MARKET[MONTH],$A9) -> 0 | I9: =$C9+$H9 -> 2489130
A10: =EOMONTH(A9,0)+1 -> 45597 | B10: =COUNTIFS(AUBURN[MONTH],$A10) -> 45 | C10: =SUMIFS(AUBURN[BILLING RATE (₹)],AUBURN[MONTH],$A10) -> 2493240 | D10: =SUMIFS(AUBURN[LORRY RATE (₹)],AUBURN[MONTH],$A10) -> 1732700 | E10: =$C10-$D10 -> 760540 | F10: =IFERROR($E10/$C10,"") -> 0.30504083 | G10: =COUNTIFS(MARKET[MONTH],$A10) -> 0 | H10: =SUMIFS(MARKET[RATE (₹)],MARKET[MONTH],$A10) -> 0 | I10: =$C10+$H10 -> 2493240
A11: =EOMONTH(A10,0)+1 -> 45627 | B11: =COUNTIFS(AUBURN[MONTH],$A11) -> 54 | C11: =SUMIFS(AUBURN[BILLING RATE (₹)],AUBURN[MONTH],$A11) -> 3305770 | D11: =SUMIFS(AUBURN[LORRY RATE (₹)],AUBURN[MONTH],$A11) -> 2390200 | E11: =$C11-$D11 -> 915570 | F11: =IFERROR($E11/$C11,"") -> 0.27696119 | G11: =COUNTIFS(MARKET[MONTH],$A11) -> 0 | H11: =SUMIFS(MARKET[RATE (₹)],MARKET[MONTH],$A11) -> 0 | I11: =$C11+$H11 -> 3305770
A12: =EOMONTH(A11,0)+1 -> 45658 | B12: =COUNTIFS(AUBURN[MONTH],$A12) -> 58 | C12: =SUMIFS(AUBURN[BILLING RATE (₹)],AUBURN[MONTH],$A12) -> 3913110 | D12: =SUMIFS(AUBURN[LORRY RATE (₹)],AUBURN[MONTH],$A12) -> 2949440 | E12: =$C12-$D12 -> 963670 | F12: =IFERROR($E12/$C12,"") -> 0.24626704 | G12: =COUNTIFS(MARKET[MONTH],$A12) -> 0 | H12: =SUMIFS(MARKET[RATE (₹)],MARKET[MONTH],$A12) -> 0 | I12: =$C12+$H12 -> 3913110
A13: =EOMONTH(A12,0)+1 -> 45689 | B13: =COUNTIFS(AUBURN[MONTH],$A13) -> 55 | C13: =SUMIFS(AUBURN[BILLING RATE (₹)],AUBURN[MONTH],$A13) -> 3083750 | D13: =SUMIFS(AUBURN[LORRY RATE (₹)],AUBURN[MONTH],$A13) -> 2187260 | E13: =$C13-$D13 -> 896490 | F13: =IFERROR($E13/$C13,"") -> 0.29071423 | G13: =COUNTIFS(MARKET[MONTH],$A13) -> 0 | H13: =SUMIFS(MARKET[RATE (₹)],MARKET[MONTH],$A13) -> 0 | I13: =$C13+$H13 -> 3083750
A14: =EOMONTH(A13,0)+1 -> 45717 | B14: =COUNTIFS(AUBURN[MONTH],$A14) -> 46 | C14: =SUMIFS(AUBURN[BILLING RATE (₹)],AUBURN[MONTH],$A14) -> 2744440 | D14: =SUMIFS(AUBURN[LORRY RATE (₹)],AUBURN[MONTH],$A14) -> 1867850 | E14: =$C14-$D14 -> 876590 | F14: =IFERROR($E14/$C14,"") -> 0.31940578 | G14: =COUNTIFS(MARKET[MONTH],$A14) -> 0 | H14: =SUMIFS(MARKET[RATE (₹)],MARKET[MONTH],$A14) -> 0 | I14: =$C14+$H14 -> 2744440
A15: =EOMONTH(A14,0)+1 -> 45748 | B15: =COUNTIFS(AUBURN[MONTH],$A15) -> 46 | C15: =SUMIFS(AUBURN[BILLING RATE (₹)],AUBURN[MONTH],$A15) -> 2852010 | D15: =SUMIFS(AUBURN[LORRY RATE (₹)],AUBURN[MONTH],$A15) -> 1876090 | E15: =$C15-$D15 -> 975920 | F15: =IFERROR($E15/$C15,"") -> 0.34218674 | G15: =COUNTIFS(MARKET[MONTH],$A15) -> 6 | H15: =SUMIFS(MARKET[RATE (₹)],MARKET[MONTH],$A15) -> 315280 | I15: =$C15+$H15 -> 3167290
A16: =EOMONTH(A15,0)+1 -> 45778 | B16: =COUNTIFS(AUBURN[MONTH],$A16) -> 40 | C16: =SUMIFS(AUBURN[BILLING RATE (₹)],AUBURN[MONTH],$A16) -> 2298580 | D16: =SUMIFS(AUBURN[LORRY RATE (₹)],AUBURN[MONTH],$A16) -> 1429090 | E16: =$C16-$D16 -> 869490 | F16: =IFERROR($E16/$C16,"") -> 0.37827267 | G16: =COUNTIFS(MARKET[MONTH],$A16) -> 5 | H16: =SUMIFS(MARKET[RATE (₹)],MARKET[MONTH],$A16) -> 227040 | I16: =$C16+$H16 -> 2525620
... A59: =EOMONTH(A58,0)+1 -> 47088 | B59: =COUNTIFS(AUBURN[MONTH],$A59) -> 0 | C59: =SUMIFS(AUBURN[BILLING RATE (₹)],AUBURN[MONTH],$A59) -> 0 | D59: =SUMIFS(AUBURN[LORRY RATE (₹)],AUBURN[MONTH],$A59) -> 0 | E59: =$C59-$D59 -> 0 | F59: =IFERROR($E59/$C59,"") | G59: =COUNTIFS(MARKET[MONTH],$A59) -> 0 | H59: =SUMIFS(MARKET[RATE (₹)],MARKET[MONTH],$A59) -> 0 | I59: =$C59+$H59 -> 0
A60: TOTAL | B60: =SUM(B4:B59) -> 1114 | C60: =SUM(C4:C59) -> 75694270 | D60: =SUM(D4:D59) -> 45985070 | E60: =SUM(E4:E59) -> 29709200 | F60: =IFERROR($E$60/$C$60,"") -> 0.39248942 | G60: =SUM(G4:G59) -> 171 | H60: =SUM(H4:H59) -> 6780690 | I60: =SUM(I4:I59) -> 82474960

Sheet Monthly KM Run
A1: Truck No | B1: On Road Date | C1: Make | D1: Capacity | E1: Driver | F1: Year | G1: Month | H1: Actual Total KM Run | I1: Target KM / Month | J1: Veriation | K1: Incentive
A2: 2417 | C2: Tata | D2: 32 Feet | E2: Driver A | F2: 2026 | G2: March | H2: 12830 | I2: 15000 | J2: =H2-I2 -> -2170 | K2: =IF(J2<0,0,J2*1) -> 0
A3: 0526 | C3: Tata | D3: 32 Feet | E3: Driver B | F3: 2026 | G3: March | H3: 13420 | I3: 15000 | J3: =H3-I3 -> -1580 | K3: =IF(J3<0,0,J3*1) -> 0
A4: 3958 | C4: Tata | D4: 32 Feet | E4: Driver C | F4: 2026 | G4: March | H4: 12150 | I4: 15000 | J4: =H4-I4 -> -2850 | K4: =IF(J4<0,0,J4*1) -> 0
A5: 6142 | C5: Tata | D5: 32 Feet | E5: Driver D | F5: 2026 | G5: March | H5: 9950 | I5: 15000 | J5: =H5-I5 -> -5050 | K5: =IF(J5<0,0,J5*1) -> 0
A6: 8803 | C6: Ashok | D6: 32 Feet | E6: Driver E | F6: 2026 | G6: March | H6: 12500 | I6: 15000 | J6: =H6-I6 -> -2500 | K6: =IF(J6<0,0,J6*1) -> 0
A7: 4371 | C7: Ashok | D7: 24 Feet | E7: Driver F | F7: 2026 | G7: March | H7: 6500 | I7: 15000 | J7: =H7-I7 -> -8500 | K7: =IF(J7<0,0,J7*1) -> 0
A8: 1695 | C8: Tata | D8: 32 Feet | E8: Driver G | F8: 2026 | G8: March | I8: 15000 | J8: =H8-I8 -> -15000 | K8: =IF(J8<0,0,J8*1) -> 0
A9: 7230 | C9: Tata | D9: 32 Feet | E9: Driver H | F9: 2026 | G9: March | H9: 0 | I9: 15000 | J9: =H9-I9 -> -15000 | K9: =IF(J9<0,0,J9*1) -> 0
A10: 9064 | C10: Tata | D10: 32 Feet | E10: Driver I | F10: 2026 | G10: March | H10: 0 | I10: 15000 | J10: =H10-I10 -> -15000 | K10: =IF(J10<0,0,J10*1) -> 0
A11: 5582 | C11: Tata | D11: 32 Feet | E11: Driver J | F11: 2026 | G11: March | H11: 0 | I11: 15000 | J11: =H11-I11 -> -15000 | K11: =IF(J11<0,0,J11*1) -> 0
A13: Truck No | B13: On Road Date | C13: Make | D13: Capacity | E13: Driver | F13: Year | G13: Month | H13: Actual Total KM Run | I13: Target KM / Month | J13: Veriation | K13: Incentive
A14: 2417 | C14: Tata | D14: 32 Feet | E14: Driver A | F14: 2026 | G14: April | H14: 10600 | I14: 15000 | J14: -4400 | K14: 0
A15: 0526 | C15: Tata | D15: 32 Feet | E15: Driver B | F15: 2026 | G15: April | H15: 10880 | I15: 15000 | J15: -4120 | K15: 0
A16: 3958 | C16: Tata | D16: 32 Feet | E16: Driver K | F16: 2026 | G16: April | H16: 11250 | I16: 15000 | J16: -3750 | K16: 0
A17: 6142 | C17: Tata | D17: 32 Feet | E17: Driver D | F17: 2026 | G17: April | H17: 12970 | I17: 15000 | J17: -2030 | K17: 0
A18: 8803 | C18: Ashok | D18: 32 Feet | E18: Driver E | F18: 2026 | G18: April | H18: 6500 | I18: 15000 | J18: -8500 | K18: 0
A19: 4371 | C19: Ashok | D19: 24 Feet | E19: Driver L | F19: 2026 | G19: April | H19: 8250 | I19: 15000 | J19: -6750 | K19: 0
A20: 1695 | C20: Tata | D20: 32 Feet | E20: Driver G | F20: 2026 | G20: April | H20: 11550 | I20: 15000 | J20: -3450 | K20: 0
A21: 7230 | C21: Tata | D21: 32 Feet | E21: Driver H | F21: 2026 | G21: April | H21: 13020 | I21: 15000 | J21: -1980 | K21: 0
A22: 9064 | C22: Tata | D22: 32 Feet | E22: Driver I | F22: 2026 | G22: April | H22: 6350 | I22: 15000 | J22: -8650 | K22: 0
A23: 5582 | C23: Tata | D23: 32 Feet | E23: Driver J | F23: 2026 | G23: April | H23: 8100 | I23: 15000 | J23: -6900 | K23: 0
A25: Truck No | B25: On Road Date | C25: Make | D25: Capacity | E25: Driver | F25: Year | G25: Month | H25: Actual Total KM Run | I25: Target KM / Month | J25: Veriation | K25: Incentive
A26: 2417 | C26: Tata | D26: 32 Feet | E26: Driver A | F26: 2026 | G26: May | H26: 12550 | I26: 15000 | J26: -2450 | K26: 0
A27: 0526 | C27: Tata | D27: 32 Feet | E27: Driver B | F27: 2026 | G27: May | H27: 9500 | I27: 15000 | J27: -5500 | K27: 0
A28: 3958 | C28: Tata | D28: 32 Feet | E28: Driver K | F28: 2026 | G28: May | H28: 11550 | I28: 15000 | J28: -3450 | K28: 0
A29: 6142 | C29: Tata | D29: 32 Feet | E29: Driver D | F29: 2026 | G29: May | H29: 14300 | I29: 15000 | J29: -700 | K29: 0
A30: 8803 | C30: Ashok | D30: 32 Feet | E30: Driver E | F30: 2026 | G30: May | H30: 11600 | I30: 15000 | J30: -3400 | K30: 0
A31: 4371 | C31: Ashok | D31: 24 Feet | E31: Driver L | F31: 2026 | G31: May | H31: 13000 | I31: 15000 | J31: -2000 | K31: 0
A32: 1695 | C32: Tata | D32: 32 Feet | E32: Driver G | F32: 2026 | G32: May | H32: 10600 | I32: 15000 | J32: -4400 | K32: 0
A33: 7230 | C33: Tata | D33: 32 Feet | E33: Driver H | F33: 2026 | G33: May | H33: 11000 | I33: 15000 | J33: -4000 | K33: 0
A34: 9064 | C34: Tata | D34: 32 Feet | E34: Driver I | F34: 2026 | G34: May | H34: 10500 | I34: 15000 | J34: -4500 | K34: 0
A35: 5582 | C35: Tata | D35: 32 Feet | E35: Driver J | F35: 2026 | G35: May | H35: 12000 | I35: 15000 | J35: -3000 | K35: 0
A38: Truck No | B38: On Road Date | C38: Make | D38: Capacity | E38: Driver | F38: Year | G38: Month | H38: Actual Total KM Run | I38: Target KM / Month | J38: Veriation | K38: Incentive
A39: 2417 | C39: Tata | D39: 32 Feet | E39: Driver A | F39: 2026 | G39: JUNE | H39: 11300 | I39: 15000 | J39: -3700 | K39: 0
A40: 0526 | C40: Tata | D40: 32 Feet | E40: Driver B | F40: 2026 | G40: JUNE | H40: 12300 | I40: 15000 | J40: -2700 | K40: 0
A41: 3958 | C41: Tata | D41: 32 Feet | E41: Driver K | F41: 2026 | G41: JUNE | H41: 14300 | I41: 15000 | J41: -700 | K41: 0
A42: 6142 | C42: Tata | D42: 32 Feet | E42: Driver D | F42: 2026 | G42: JUNE | H42: 14150 | I42: 15000 | J42: -850 | K42: 0
A43: 8803 | C43: Ashok | D43: 32 Feet | E43: Driver E | F43: 2026 | G43: JUNE | H43: 14500 | I43: 15000 | J43: -500 | K43: 0
A44: 4371 | C44: Ashok | D44: 24 Feet | E44: Driver L | F44: 2026 | G44: JUNE | H44: 12600 | I44: 15000 | J44: -2400 | K44: 0
A45: 1695 | C45: Tata | D45: 32 Feet | E45: Driver G | F45: 2026 | G45: JUNE | H45: 14700 | I45: 15000 | J45: -300 | K45: 0
A46: 7230 | C46: Tata | D46: 32 Feet | E46: Driver H | F46: 2026 | G46: JUNE | H46: 9300 | I46: 15000 | J46: -5700 | K46: 0
A47: 9064 | C47: Tata | D47: 32 Feet | E47: Driver I | F47: 2026 | G47: JUNE | H47: 8350 | I47: 15000 | J47: -6650 | K47: 0
A48: 5582 | C48: Tata | D48: 32 Feet | E48: Driver J | F48: 2026 | G48: JUNE | H48: 11500 | I48: 15000 | J48: -3500 | K48: 0
H50: Running k.m.123000 | I50: Total Target,150000 | J50: Loss k.m.27000
A52: Truck No | B52: On Road Date | C52: Make | D52: Capacity | E52: Driver | F52: Year | G52: Month | H52: Actual Total KM Run | I52: Target KM / Month | J52: Veriation | K52: Incentive
A53: 2417 | C53: Tata | D53: 32 Feet | E53: Driver A | F53: 2026 | G53: JULY | H53: 13050 | I53: 15000 | J53: -1950 | K53: 0
A54: 0526 | C54: Tata | D54: 32 Feet | E54: Driver B | F54: 2026 | G54: JULY | H54: 15450 | I54: 15000 | J54: - | K54: 450
A55: 3958 | C55: Tata | D55: 32 Feet | E55: Driver K | F55: 2026 | G55: JULY | H55: 12950 | I55: 15000 | J55: -2050 | K55: 0
A56: 6142 | C56: Tata | D56: 32 Feet | E56: Driver D | F56: 2026 | G56: JULY | H56: 11950 | I56: 15000 | J56: -3050 | K56: 0
A57: 8803 | C57: Ashok | D57: 32 Feet | E57: Driver E | F57: 2026 | G57: JULY | H57: 12600 | I57: 15000 | J57: -2400 | K57: 0
A58: 4371 | C58: Ashok | D58: 24 Feet | E58: Driver L | F58: 2026 | G58: JULY | H58: 14500 | I58: 15000 | J58: -500 | K58: 0
A59: 1695 | C59: Tata | D59: 32 Feet | E59: Driver G | F59: 2026 | G59: JULY | H59: 13850 | I59: 15000 | J59: -1150 | K59: 0
A60: 7230 | C60: Tata | D60: 32 Feet | E60: Driver H | F60: 2026 | G60: JULY | H60: 13300 | I60: 15000 | J60: -1700 | K60: 0
A61: 9064 | C61: Tata | D61: 32 Feet | E61: Driver I | F61: 2026 | G61: JULY | H61: 10200 | I61: 15000 | J61: -4800 | K61: 0
A62: 5582 | C62: Tata | D62: 32 Feet | E62: Driver J | F62: 2026 | G62: JULY | H62: 6100 | I62: 15000 | J62: -8900 | K62: 0
H64: Running k.m.123950 | I64: Total Target,150000 | J64: Loss k.m.26050
A66: Truck No | B66: On Road Date | C66: Make | D66: Capacity | E66: Driver | F66: Year | G66: Month | H66: Actual Total KM Run | I66: Target KM / Month | J66: Veriation | K66: Incentive
A67: 2417 | C67: Tata | D67: 32 Feet | E67: Driver A | F67: 2026 | G67: AUG | H67: 9800 | I67: 15000 | J67: 5200 | K67: 0
A68: 0526 | C68: Tata | D68: 32 Feet | E68: Driver B | F68: 2026 | G68: AUG | H68: 11700 | I68: 15000 | J68: 3300 | K68: 0
A69: 3958 | C69: Tata | D69: 32 Feet | E69: Driver K | F69: 2026 | G69: AUG | H69: 11050 | I69: 15000 | J69: 3950 | K69: 0
A70: 6142 | C70: Tata | D70: 32 Feet | E70: Driver D | F70: 2026 | G70: AUG | H70: 15000 | I70: 15000 | J70: 0 | K70: 0
A71: 8803 | C71: Ashok | D71: 32 Feet | E71: Driver E | F71: 2026 | G71: AUG | H71: 10300 | I71: 15000 | J71: 4700 | K71: 0
A72: 4371 | C72: Ashok | D72: 24 Feet | E72: Driver L | F72: 2026 | G72: AUG | H72: 2300 | I72: 15000 | J72: 12700 | K72: 0
A73: 1695 | C73: Tata | D73: 32 Feet | E73: Driver G | F73: 2026 | G73: AUG | H73: 10400 | I73: 15000 | J73: 4600 | K73: 0
A74: 7230 | C74: Tata | D74: 32 Feet | E74: Driver I | F74: 2026 | G74: AUG | H74: 11800 | I74: 15000 | J74: 3200 | K74: 0
A75: 9064 | C75: Tata | D75: 32 Feet | E75: Driver H | F75: 2026 | G75: AUG | H75: 11900 | I75: 15000 | J75: 3100 | K75: 0
A76: 5582 | C76: Tata | D76: 32 Feet | E76: Driver J | F76: 2026 | G76: AUG | H76: 5800 | I76: 15000 | J76: 9200 | K76: 0
H78: Running k.m.100050 | I78: Total Target,150000 | J78: Loss k.m.49950

Sheet KM RUN CLEAN
A1: MONTHLY KM RUN vs TARGET — BN LOGISTICS
A2: INCENTIVE RATE (₹ per km over target) | D2: 1 | F2: TOTAL ACTUAL KM | G2: =SUM(KMRUN[ACTUAL KM]) -> 630420 | I2: FLEET UTILISATION | J2: =IFERROR($G$2/$G$3,"") -> 0.70046667
A3: DEFAULT TARGET KM / TRUCK / MONTH | D3: 15000 | F3: TOTAL TARGET KM | G3: =SUM(KMRUN[TARGET KM]) -> 900000 | I3: TRUCK-MONTHS AT TARGET | J3: =COUNTIF(KMRUN[UTILISATION %],">=1")&" of "&SUMPRODUCT(--(KMRUN[TRUCK NO.]<>"")) -> 2 of 60
I4: TOTAL INCENTIVE EARNED | J4: =SUM(KMRUN[INCENTIVE (₹)]) -> 450
A6: MONTH | B6: TRUCK NO. | C6: MAKE | D6: CAPACITY | E6: DRIVER | F6: ACTUAL KM | G6: TARGET KM | H6: VARIANCE (KM) | I6: UTILISATION % | J6: INCENTIVE (₹)
A7: 46082 | B7: 2417 | C7: Tata | D7: 32 Feet | E7: Driver A | F7: 12830 | G7: 15000 | H7: =IF(OR($F7="",$G7=""),"",$F7-$G7) -> -2170 | I7: =IF(OR($F7="",$G7="",$G7=0),"",$F7/$G7) -> 0.85533333 | J7: =IF($H7="","",MAX(0,$H7)*$D$2) -> 0
A8: 46082 | B8: 0526 | C8: Tata | D8: 32 Feet | E8: Driver B | F8: 13420 | G8: 15000 | H8: =IF(OR($F8="",$G8=""),"",$F8-$G8) -> -1580 | I8: =IF(OR($F8="",$G8="",$G8=0),"",$F8/$G8) -> 0.89466667 | J8: =IF($H8="","",MAX(0,$H8)*$D$2) -> 0
A9: 46082 | B9: 3958 | C9: Tata | D9: 32 Feet | E9: Driver C | F9: 12150 | G9: 15000 | H9: =IF(OR($F9="",$G9=""),"",$F9-$G9) -> -2850 | I9: =IF(OR($F9="",$G9="",$G9=0),"",$F9/$G9) -> 0.81 | J9: =IF($H9="","",MAX(0,$H9)*$D$2) -> 0
A10: 46082 | B10: 6142 | C10: Tata | D10: 32 Feet | E10: Driver D | F10: 9950 | G10: 15000 | H10: =IF(OR($F10="",$G10=""),"",$F10-$G10) -> -5050 | I10: =IF(OR($F10="",$G10="",$G10=0),"",$F10/$G10) -> 0.66333333 | J10: =IF($H10="","",MAX(0,$H10)*$D$2) -> 0
A11: 46082 | B11: 8803 | C11: Ashok | D11: 32 Feet | E11: Driver E | F11: 12500 | G11: 15000 | H11: =IF(OR($F11="",$G11=""),"",$F11-$G11) -> -2500 | I11: =IF(OR($F11="",$G11="",$G11=0),"",$F11/$G11) -> 0.83333333 | J11: =IF($H11="","",MAX(0,$H11)*$D$2) -> 0
A12: 46082 | B12: 4371 | C12: Ashok | D12: 24 Feet | E12: Driver F | F12: 6500 | G12: 15000 | H12: =IF(OR($F12="",$G12=""),"",$F12-$G12) -> -8500 | I12: =IF(OR($F12="",$G12="",$G12=0),"",$F12/$G12) -> 0.43333333 | J12: =IF($H12="","",MAX(0,$H12)*$D$2) -> 0
A13: 46082 | B13: 1695 | C13: Tata | D13: 32 Feet | E13: Driver G | G13: 15000 | H13: =IF(OR($F13="",$G13=""),"",$F13-$G13) | I13: =IF(OR($F13="",$G13="",$G13=0),"",$F13/$G13) | J13: =IF($H13="","",MAX(0,$H13)*$D$2)
A14: 46082 | B14: 7230 | C14: Tata | D14: 32 Feet | E14: Driver H | F14: 0 | G14: 15000 | H14: =IF(OR($F14="",$G14=""),"",$F14-$G14) -> -15000 | I14: =IF(OR($F14="",$G14="",$G14=0),"",$F14/$G14) -> 0 | J14: =IF($H14="","",MAX(0,$H14)*$D$2) -> 0
A15: 46082 | B15: 9064 | C15: Tata | D15: 32 Feet | E15: Driver I | F15: 0 | G15: 15000 | H15: =IF(OR($F15="",$G15=""),"",$F15-$G15) -> -15000 | I15: =IF(OR($F15="",$G15="",$G15=0),"",$F15/$G15) -> 0 | J15: =IF($H15="","",MAX(0,$H15)*$D$2) -> 0
A16: 46082 | B16: 5582 | C16: Tata | D16: 32 Feet | E16: Driver J | F16: 0 | G16: 15000 | H16: =IF(OR($F16="",$G16=""),"",$F16-$G16) -> -15000 | I16: =IF(OR($F16="",$G16="",$G16=0),"",$F16/$G16) -> 0 | J16: =IF($H16="","",MAX(0,$H16)*$D$2) -> 0
A17: 46113 | B17: 2417 | C17: Tata | D17: 32 Feet | E17: Driver A | F17: 10600 | G17: 15000 | H17: =IF(OR($F17="",$G17=""),"",$F17-$G17) -> -4400 | I17: =IF(OR($F17="",$G17="",$G17=0),"",$F17/$G17) -> 0.70666667 | J17: =IF($H17="","",MAX(0,$H17)*$D$2) -> 0
A18: 46113 | B18: 0526 | C18: Tata | D18: 32 Feet | E18: Driver B | F18: 10880 | G18: 15000 | H18: =IF(OR($F18="",$G18=""),"",$F18-$G18) -> -4120 | I18: =IF(OR($F18="",$G18="",$G18=0),"",$F18/$G18) -> 0.72533333 | J18: =IF($H18="","",MAX(0,$H18)*$D$2) -> 0
A19: 46113 | B19: 3958 | C19: Tata | D19: 32 Feet | E19: Driver K | F19: 11250 | G19: 15000 | H19: =IF(OR($F19="",$G19=""),"",$F19-$G19) -> -3750 | I19: =IF(OR($F19="",$G19="",$G19=0),"",$F19/$G19) -> 0.75 | J19: =IF($H19="","",MAX(0,$H19)*$D$2) -> 0
A20: 46113 | B20: 6142 | C20: Tata | D20: 32 Feet | E20: Driver D | F20: 12970 | G20: 15000 | H20: =IF(OR($F20="",$G20=""),"",$F20-$G20) -> -2030 | I20: =IF(OR($F20="",$G20="",$G20=0),"",$F20/$G20) -> 0.86466667 | J20: =IF($H20="","",MAX(0,$H20)*$D$2) -> 0
A21: 46113 | B21: 8803 | C21: Ashok | D21: 32 Feet | E21: Driver E | F21: 6500 | G21: 15000 | H21: =IF(OR($F21="",$G21=""),"",$F21-$G21) -> -8500 | I21: =IF(OR($F21="",$G21="",$G21=0),"",$F21/$G21) -> 0.43333333 | J21: =IF($H21="","",MAX(0,$H21)*$D$2) -> 0
A22: 46113 | B22: 4371 | C22: Ashok | D22: 24 Feet | E22: Driver L | F22: 8250 | G22: 15000 | H22: =IF(OR($F22="",$G22=""),"",$F22-$G22) -> -6750 | I22: =IF(OR($F22="",$G22="",$G22=0),"",$F22/$G22) -> 0.55 | J22: =IF($H22="","",MAX(0,$H22)*$D$2) -> 0
A23: 46113 | B23: 1695 | C23: Tata | D23: 32 Feet | E23: Driver G | F23: 11550 | G23: 15000 | H23: =IF(OR($F23="",$G23=""),"",$F23-$G23) -> -3450 | I23: =IF(OR($F23="",$G23="",$G23=0),"",$F23/$G23) -> 0.77 | J23: =IF($H23="","",MAX(0,$H23)*$D$2) -> 0
A24: 46113 | B24: 7230 | C24: Tata | D24: 32 Feet | E24: Driver H | F24: 13020 | G24: 15000 | H24: =IF(OR($F24="",$G24=""),"",$F24-$G24) -> -1980 | I24: =IF(OR($F24="",$G24="",$G24=0),"",$F24/$G24) -> 0.868 | J24: =IF($H24="","",MAX(0,$H24)*$D$2) -> 0
A25: 46113 | B25: 9064 | C25: Tata | D25: 32 Feet | E25: Driver I | F25: 6350 | G25: 15000 | H25: =IF(OR($F25="",$G25=""),"",$F25-$G25) -> -8650 | I25: =IF(OR($F25="",$G25="",$G25=0),"",$F25/$G25) -> 0.42333333 | J25: =IF($H25="","",MAX(0,$H25)*$D$2) -> 0
... A66: 46235 | B66: 5582 | C66: Tata | D66: 32 Feet | E66: Driver J | F66: 5800 | G66: 15000 | H66: =IF(OR($F66="",$G66=""),"",$F66-$G66) -> -9200 | I66: =IF(OR($F66="",$G66="",$G66=0),"",$F66/$G66) -> 0.38666667 | J66: =IF($H66="","",MAX(0,$H66)*$D$2) -> 0
A67: 46266 | H67: =IF(OR($F67="",$G67=""),"",$F67-$G67) | I67: =IF(OR($F67="",$G67="",$G67=0),"",$F67/$G67) | J67: =IF($H67="","",MAX(0,$H67)*$D$2)

Sheet Daily Tracking
B1: BN Logistics
B2: Daily Trucks Tracking Report
B3: Month : | C3: 46266
B4: Truck No | C4: Size | D4: Capacity ( Ton) | E4: Driver | F4: Details | G4: 1 | H4: 2 | I4: 3 | J4: 4 | K4: 5 | L4: 6 | M4: 7 | N4: 8 | O4: 9 | P4: 10 | Q4: 11 | R4: 12 | S4: 13 | T4: 14 | U4: 15 | V4: 16 | W4: 17 | X4: 18 | Y4: 19 | Z4: 20 | AA4: 21 | AB4: 22 | AC4: 23 | AD4: 24 | AE4: 25 | AF4: 26 | AG4: 27 | AH4: 28 | AI4: 29 | AJ4: 30 | AK4: 31 | AL4: Tgt | AM4: Blc to TGT | AN4: 1 | AO4: 2 | AP4: 3 | AQ4: 4 | AR4: 5 | AS4: 6 | AT4: 7 | AU4: 8 | AV4: 9 | AW4: 10 | AX4: 11 | AY4: 12 | AZ4: 13 | BA4: 14 | BB4: 15 | BC4: 16 | BD4: 17 | BE4: 18 | BF4: 19 | BG4: 20 | BH4: 21 | BI4: 22 | BJ4: 23 | BK4: 24 | BL4: 25 | BM4: 26 | BN4: 27 | BO4: 28 | BP4: 29 | BQ4: 30 | BR4: Total KM | BS4: Tgt | BT4: Blc to TGT | BU4: 1 | BV4: 2 | BW4: 3 | BX4: 4 | BY4: 5 | BZ4: 6 | CA4: 7 | CB4: 8 | CC4: 9 | CD4: 10 | CE4: 11 | CF4: 12 | CG4: 13 | CH4: 14 | CI4: 15 | CJ4: 16 | CK4: 17 | CL4: 18 | CM4: 19 | CN4: 20 | CO4: 21 | CP4: 22 | CQ4: 23 | CR4: 24 | CS4: 25 | CT4: 26 | CU4: 27 | CV4: 28 | CW4: 29 | CX4: 30 | CY4: 31 | CZ4: Total KM | DA4: Tgt | DB4: Blc to TGT | DC4: 1 | DD4: 2 | DE4: 3 | DF4: 4 | DG4: 5 | DH4: 6 | DI4: 7 | DJ4: 8 | DK4: 9 | DL4: 10 | DM4: 11 | DN4: 12 | DO4: 13 | DP4: 14 | DQ4: 15 | DR4: 16 | DS4: 17 | DT4: 18 | DU4: 19 | DV4: 20 | DW4: 21 | DX4: 22 | DY4: 23 | DZ4: 24 | EA4: 25 | EB4: 26 | EC4: 27 | ED4: 28 | EE4: 29 | EF4: 30 | EG4: Total KM | EH4: Tgt | EI4: Blc to TGT | EJ4: 1 | EK4: 2 | EL4: 3 | EM4: 4 | EN4: 5 | EO4: 6 | EP4: 7 | EQ4: 8 | ER4: 9 | ES4: 10 | ET4: 11 | EU4: 12 | EV4: 13 | EW4: 14 | EX4: 15 | EY4: 16 | EZ4: 17 | FA4: 18 | FB4: 19 | FC4: 20 | FD4: 21 | FE4: 22 | FF4: 23 | FG4: 24 | FH4: 25 | FI4: 26 | FJ4: 27 | FK4: 28 | FL4: 29 | FM4: 30 | FN4: 31 | FO4: Total KM | FP4: Tgt | FQ4: Blc to TGT | FS4: 1 | FT4: 2 | FU4: 3 | FV4: 4 | FW4: 5 | FX4: 6 | FY4: 7 | FZ4: 8 | GA4: 9 | GB4: 10 | GC4: 11 | GD4: 12 | GE4: 13 | GF4: 14 | GG4: 15 | GH4: 16 | GI4: 17 | GJ4: 18 | GK4: 19 | GL4: 20 | GM4: 21 | GN4: 22 | GO4: 23 | GP4: 24 | GQ4: 25 | GR4: 26 | GS4: 27 | GT4: 28 | GU4: 29 | GV4: 30 | GW4: 31 | GX4: Total KM | GY4: Tgt | GZ4: Blc to TGT | HA4: 1 | HB4: 2 | HC4: 3 | HD4: 4 | HE4: 5 | HF4: 6 | HG4: 7 | HH4: 8 | HI4: 9 | HJ4: 10 | HK4: 11 | HL4: 12 | HM4: 13 | HN4: 14 | HO4: 15 | HP4: 16 | HQ4: 17 | HR4: 18 | HS4: 19 | HT4: 20 | HU4: 21 | HV4: 22 | HW4: 23 | HX4: 24 | HY4: 25 | HZ4: 26 | IA4: 27 | IB4: 28 | IC4: 29 | ID4: 30 | IE4: 31 | IF4: Total KM | IG4: UTILITY % | IH4: Tgt | II4: Blc to TGT
B5: 1 | C5: 32 Feet | E5: Driver A | F5: Plan | G5: Tripur to Ranchi | J5: Ranchi to Narshpur / Hoskotey | N5: HK to Tripur | Q5: Tirpur to Ranchi | V5: Ranchi to Narshapur | AA5: Narshpur to Culcutta | AD5: Calcutta to Ranchi | AG5: Ranchi to Narsapur/Hoskote | AK5: Hoskote to Mysore | AN5: Hoskote to Mysore | AO5: Mysore to Tiruppur | AP5: Tiruppur to Ranchi | AU5: Ranchi to Cuttack | AW5: Cuttack to Banglore | BA5: Banglore to Tirppur | BC5: Tiruppur to Ranchi | BG5: Ranchi to Narsapur | BL5: Banglore to Kolkata | BZ5: Kolkata to Ranchi | CB5: Ranchi to narsapur/Hoskote | CG5: Hoskote to Tirupur | CH5: Tirupur to ranchi | CM5: Ranchi to Narsapur | CP5: Narsapur to Erode | CQ5: Erode to Ranchi | CT5: Ranchi to Narsapur | CX5: Mysore road to Kolkata | DF5: Kolkata to Banglore | DK5: Banglore to Patna | DR5: Patna to Odissa | DT5: Odissa to Ranchi | DU5: Ranchi to Narsapur/Hoskote | DY5: Narsapur,Service Centre | DZ5: Narsapur to Tiruppur | EA5: Tiruppur to Ranchi | EE5: Ranchi to Narsapur/Hoskote | EL5: Bng to Tiruppur | EM5: Tiruppur to Ranchi | EQ5: Ranchi to Narsapur/Hoskote | ET5: Narsapur to Tiruppur | EW5: Tiruppur to Ranchi | FA5: Ranchi to Hoskote | FF5: Hoskote to Bng/Tiruppur | FH5: Tiruppur to Ranchi | FL5: Ranchi to Narsapur/Hoskote | FV5: Bng to Cuttack | GA5: Odissa to Ranchi | GC5: Ranchi to Narsapur/Hoskote | GG5: Hoskote to Tiruppur | GJ5: Tiruppur to Ranchi | GN5: Ranchi to Narsapur/Hoskote | GR5: Bng to Kolkata | HA5: Kolkata to Muri Ranchi | HD5: Ranchi to Narsapur/Hassan
C6: 2417 | D6: 9 | F6: Actual
F7: KM | G7: 2300 | J7: 1900 | Q7: 2300 | V7: 1900 | AA7: 1900 | AD7: 390 | AG7: 1900 | AK7: 240 | AL7: 15000 | AM7: =#REF!-AL7 -> #REF! | AO7: 200 | AP7: 2300 | AU7: 500 | AW7: 1500 | BC7: 2300 | BG7: 1900 | BL7: 1900 | BR7: =SUM(AN7:BQ7) -> 10600 | BS7: 15000 | BT7: =BR7-BS7 -> -4400 | BY7: 1900 | BZ7: 450 | CB7: 1900 | CH7: 2300 | CM7: 1900 | CQ7: 2100 | CT7: 1900 | CX7: 2000 | CZ7: 12550 | DA7: 15000 | DB7: =CZ7-DA7 -> -2450 | DF7: 1900 | DK7: 2300 | DR7: 1000 | DU7: 1900 | EA7: 2300 | EE7: 1900 | EG7: 11300 | EH7: 15000 | EI7: =EG7-EH7 -> -3700 | EM7: 2300 | EQ7: 1900 | EW7: 2300 | FA7: 1900 | FF7: 450 | FH7: 2300 | FL7: 1900 | FO7: 13050 | FP7: 15000 | FQ7: 1950 | FV7: 1300 | GA7: 400 | GC7: 1900 | GJ7: 2300 | GN7: 1900 | GR7: 2000 | GX7: 9800 | GY7: 15000 | GZ7: 5200 | HA7: 400 | HD7: 2300 | IF7: =SUM(HA7:IE7) -> 2700 | IG7: =IFERROR(IF7/IH7,"") -> 0.18 | IH7: 15000 | II7: 12300
B8: 2 | C8: 32 feet | E8: Driver B | F8: Plan | H8: Tiruppur to Ranchi | M8: Ranchi to Naesapur/Hoskote | P8: HK to Tiruppur | R8: Tiruppur to Ranchi | V8: Ranchi to Narsapur/Hoskote | Z8: Hoskote to Jigni bng | AA8: Banglore to Patna | AF8: Patna to Kolkata | AH8: Kolkata to Ranchi | AJ8: Ranchi to Narsapur | AO8: Narsapur to Jigni/Atiballi | AP8: Atiballi to Bhagalpur | AU8: Patna to Simdega | AW8: Simdega to Ranchi | AX8: Jamshedpur to Chennai | BC8: Chennai to Patna | BH8: Patna to Bokaro | BK8: Ranchi to Narsapur | BN8: Narsapur to Tirupur | BO8: Tiruppur to Ranchi | BY8: Jamshedpur to Mysore | CC8: Banglore to Patna | CJ8: Patna to Banglore | CN8: Banglore to Bhubneshwar | CU8: Bhubneshwar to Ranchi | CV8: Ranchi to Narsapur | DD8: Tiruppur to Ranchi | DH8: Ranchi to Narsapur/Hoskote | DK8: Narsapur to Tiruppur | DM8: Tiruppur to Ranchi | DS8: Ranchi to Narsapur/Hoskote | DW8: Service Centre | DZ8: Bng to Kolkata | EC8: Kolkata to Bng | EK8: Tiruppur to Ranchi | EO8: Ranchi to Narsapur/Hoskote/Hassan | ER8: Hoskote to Tiruppur | EU8: Tiruppur to Erode/Ranchi | EX8: Ranchi to Narsapur/Hoskote/Hassan | FD8: Hassan to Tiruppur | FF8: Tiruppur to Ranchi | FJ8: Ranchi to Narsapur/Hoskote | FM8: Bng to Ranchi | FV8: Ranchi to Bng | FY8: Bng to Ranchi | GB8: Ranchi to Narsapur/hoskote | GE8: Hoskote to Bidadi | GG8: Bidadi bng to Ranchi | GL8: Ranchi to Narsapur/Hoskote | GR8: Hoskote to Bidadi Bng | GS8: Bidadi Bng to Kolkata | HD8: Kolkata to Ranchi
C9: 0526 | D9: 9 | F9: Actual
F10: KM | H10: 2300 | M10: 1900 | R10: 2300 | V10: 1900 | AA10: 2150 | AF10: 580 | AH10: 390 | AJ10: 1900 | AL10: 15000 | AM10: =#REF!-AL10 -> #REF! | AP10: 2180 | AU10: 500 | AX10: 1600 | BC10: 2100 | BH10: 300 | BK10: 1900 | BO10: 2300 | BR10: =SUM(AN10:BQ10) -> 10880 | BS10: 15000 | BT10: =BR10-BS10 -> -4120 | BY10: 1900 | CC10: 2100 | CJ10: 2100 | CN10: 1500 | CV10: 1900 | CZ10: 9500 | DA10: 15000 | DB10: =CZ10-DA10 -> -5500 | DD10: 2300 | DH10: 1900 | DM10: 2300 | DS10: 1900 | DZ10: 1900 | EC10: 1900 | EG10: 12300 | EH10: 15000 | EI10: =EG10-EH10 -> -2700 | EK10: 2300 | EO10: 2250 | EU10: 2300 | EX10: 2300 | FF10: 2300 | FJ10: 1900 | FM10: 2100 | FO10: 15450 | FP10: 15000 | FQ10: - | FV10: 1900 | FY10: 2000 | GB10: 1900 | GG10: 2000 | GL10: 1900 | GS10: 2000 | GX10: 11700 | GY10: 15000 | GZ10: 3300 | HD10: 400 | IF10: =SUM(HA10:IE10) -> 400 | IG10: =IFERROR(IF10/IH10,"") -> 0.026666667 | IH10: 15000 | II10: 14600
B11: 3 | C11: 32feet | D11: 9 | E11: Driver K | F11: Plan | J11: Tiruppur to Ranchi | Q11: Ranchi to Narsapur/Hoskote | U11: Hoskote to Sambalpur Odissa | Y11: Odissa to Ranchi | Z11: Ranchi to Hassan | AD11: Hassan to Tiruppur | AF11: Tiruppur to Ranchi | AI11: Ranchi to Hoskote | AP11: Hoskote to Tiruppur | AQ11: Tiruppur to Ranchi | AV11: Ranchi to Kolkata | AY11: Kolkata to Madurai | BF11: Banglore to Kolkata | BK11: Kolkata to Ranchi | BO11: Ranchi to Narsapur/Hoskote | BQ11: Tirupur to Ranchi | BV11: Tirupur to ranchi | BZ11: Ranchi to Narsapur/Hoskote | CD11: Tirupur to Ranchi | CI11: Ranchi to Jamshedpur | CJ11: Jamshedpur to Goa | CN11: Goa to Banglore | CU11: Banglore to Tirupur | CV11: Tirupur to Ranchi | DD11: Ranchi to Narsapur/Hoskote | DH11: Hoskote to Tiruppur | DI11: Tiruppur to Ranchi | DL11: Ranchi to Narsapur/Hoskote | DP11: Service Cenre | DR11: Hoskote to Tiruppur | DS11: Tiruppur to Ranchi | DV11: Ranchi to Narsapur/Hoskote | DY11: Narsapur to Tiruppur | DZ11: Tiruppur to Ranchi | EE11: Ranchi to Chittoor | EK11: Service Center | EM11: Bng to Patna | ER11: Mujjafarpur to Odissa | EV11: Odissa to Banglore | FA11: Bng to Bankura w.b. | FE11: Bankuda to Ranchi | FG11: Ranchi to Narsapur/Hoskote | FJ11: Hoskote to Tiruppur | FK11: Tiruppur to Ranchi | FN11: Ranchi to narsapur/Hoskote | FV11: Bng to patna | GB11: Patna to Ranchi | GD11: Ranchi to Narsapur/Hoskote | GJ11: Hoskote to VENDOR E | GK11: VENDOR E to VENDOR F | GL11: VENDOR U tiruppur to Ranchi | GP11: Ranchi to Narsapur | GT11: Narsapur to Tiruppur | GU11: Tiruppur to Ranchi | HC11: Ranchi to Narsapur/Hoskote
C12: 3958 | F12: Actual
F13: KM | J13: 2300 | Q13: 1900 | U13: 1600 | Z13: 2150 | AF13: 2300 | AI13: 1900 | AL13: 15000 | AM13: =#REF!-AL13 -> #REF! | AQ13: 2300 | AV13: 350 | AY13: 2100 | BF13: 1900 | BK13: 400 | BO13: 1900 | BQ13: 2300 | BR13: =SUM(AN13:BQ13) -> 11250 | BS13: 15000 | BT13: =BR13-BS13 -> -3750 | BV13: 2300 | BZ13: 1900 | CD13: 2300 | CJ13: 2100 | CN13: 650 | CV13: 2300 | CZ13: 11550 | DA13: 15000 | DB13: =CZ13-DA13 -> -3450 | DD13: 1900 | DI13: 2300 | DL13: 1900 | DS13: 2300 | DV13: 1900 | DZ13: 2300 | EE13: 1700 | EG13: 14300 | EH13: 15000 | EI13: =EG13-EH13 -> -700 | EM13: 2200 | ER13: 1100 | EV13: 1550 | FA13: 2000 | FG13: 1900 | FK13: 2300 | FN13: 1900 | FO13: 12950 | FP13: 15000 | FQ13: 2050 | FV13: 2300 | GD13: 1900 | GK13: 350 | GL13: 2300 | GP13: 1900 | GU13: 2300 | GX13: 11050 | GY13: 15000 | GZ13: 3950 | HC13: 1900 | IF13: =SUM(HA13:IE13) -> 1900 | IG13: =IFERROR(IF13/IH13,"") -> 0.12666667 | IH13: 15000 | II13: 13100
